Workbook

Sheet FINAL
A1: NO. IMP. / EXP. (NOMBRE) | B1: REF.A.A. | C1: PATENTE | D1: PEDIMENTO | E1: PEDIMENTO ORIG. (RECT.) | F1: T.O | G1: CLAVE PEDIMENTO | H1: Tasa Partida IVA | I1: Importe Partida IVA | J1: Tasa Partida CC | K1: Importe Partida CC | L1: Tasa Partida IEPS | M1: Importe Partida IEPS | N1: Tasa Partida IGI/IGE | O1: Importe Partida IGI/IGE | P1: TIPO CAMBIO | Q1: PESO BRUTO | R1: ADUANA DESPACHO | S1: NO. DE CONTENEDOR | T1: BULTOS ARRIBO | U1: Valor Comercial MXP | V1: TOTAL VALOR ADUANA | W1: Seguros | X1: Fletes | Y1: EMBALAJES | Z1: OTROS INC. | AA1: MERCANCÍA (PED.) | AB1: EJE UNIDAD DE NEGOCIO | AC1: VALOR ADUANA (P. PART.) | AD1: PRECIO UNITARIO | AE1: Tasas P/Pedimento | AF1: TASAS P/PARTIDA | AG1: IGI / IGE | AH1: REC | AI1: IVA PREV | AJ1: DTA | AK1: Importe DTA FP2 | AL1: IVA | AM1: PREV | AN1: IMPUESTOS | AO1: Cuenta Origen | AP1: PROVEEDOR / COMPRADOR | AQ1: NO(S) FACTURA(S) | AR1: INCOTERM | AS1: MONEDA | AT1: NO. GUÍA (MASTER) | AU1: NO. GUÍA HOUSE | AV1: Temperatura | AW1: FRACCION(ES) | AX1: NICO | AY1: Cantidad Factura | AZ1: UMC (CANTIDAD) | BA1: Descripcion UMC | BB1: CÓDIGO PRODUCTO | BC1: PAIS O/D | BD1: PAIS V/C | BE1: Resultado Selección | BF1: MOTIVO RETRASO / OTROS | BG1: NO. PERMISOS POR PARTIDA | BH1: PERMISOS POR PARTIDA | BI1: OBSERVACIONES ARRIBO | BJ1: ObservacionesPedimento | BK1: NO. DE COVE | BL1: FOLIO | BM1: 073 ALMACENAJE, MANEJO Y CUSTODIA (P.P.) | BN1: 110 MANIOBRAS (P.P.) | BO1: 077 DESCONSOLIDACION (P.P.) | BP1: 106 SERVICIO EXTRAORDIONARIO (P.P.) | BQ1: 033 CUENTA AMERICANA (P.P.) | BR1: 133 RECONOCIMIENTO ADUANERO (P.P.) | BS1: 034 MONTACARGAS (P.P.) | BT1: 008 HIELO SECO (P.P.) | BU1: 117 TRAMITE SAGARPA (P.P.) | BV1: 012 PAGO DE DERECHOS (P.P.) | BW1: 087 OTROS GASTOS (P.P.) | BX1: 136 SERVICIO DE CUSTODIA (P.P.) | BY1: OTROS GASTOS | BZ1: DESCARGAS | CA1: DEMORAS | CB1: HONORARIOS | CC1: I.V.A. | CD1: SALDO | CE1: EstatusCuentaGastos | CF1: Monto Cuenta de Gastos | CG1: Anticipos o Pagos Registrados | CH1: Saldo2 | CI1: Ejecutivo | CJ1: Ejecutivo_ABC | CK1: Aduana/Sección Despacho | CL1: MES | CM1: FECHA ENTRADA2 | CN1: FECHA PAGO2 | CO1: Entrada de pago | CP1: Etiqueta Entrada a Pago | CQ1: FECHA DE CRUCE2 | CR1: Entrada a Cruce | CS1: Entrada a cruce excel | CT1: ETIQUETA ENTRADA A CRUCE excel | CU1: KPI ENTRADA A CRUCE | CV1: Etiqueta entrada a Cruce2 | CW1: FECHA ENTREGA DE MERCANCIA | CX1: Entrada a entrega excel | CY1: ETIQUETA ENTRADA A ENTREGA excel | CZ1: KPI DE ENTRADA A ENTREGA | DA1: Entrada a Entrega | DB1: Etiqueta Entrada a Entrega | DC1: Entrada a Factura | DD1: Etiqueta Entrada a Factura | DE1: Pago Pedimento a Cruce | DF1: Etiqueta Pago Pedimento a Cruce | DG1: Pago a Cruce | DH1: CRUCE A ENTREGA | DI1: ETIQUETA CRUCE A ENTREGA | DJ1: FECHA DE FACTURACIÓN | DK1: ENTREGA A ENTREGA DE FACTURA | DL1: ENTREGA A FACTURA | DM1: FECHA RECIBE FACT | DN1: FECHA TIMBRADO | DO1: TIEMPO DE FACTURACION | DP1: ETIQUETA ENTREGA A FACTURA | DQ1: CuentaG_FechaFactura | DR1: Entrega de mercancia a factura excel | DS1: ETIQUETA ENTREGA A FACTURA excel | DT1: KPI entrega a factura | DU1: VERIFICADOR | DV1: Comparacion | DW1: Clave Pedimento2 | DX1: Ejecutivo_ABC3 | DY1: Guia Master | DZ1: Guia House | EA1: Pedimento4 | EB1: Tipo Operación Desc | EC1: Mercancía | ED1: TIPO MERCANCIA OK | EE1: CLASIFICACIÓN DE MERCANCIA | EF1: TIPO DE MERCANCIA | EG1: Cliente | EH1: Unidad de negocio | EI1: MOTIVO DE RETRASO | EJ1: MOTIVO DE RETRASO OTRO | EK1: MOTIVO DE RETRASO COMPLETO | EL1: Ejecutivo_Tipo_Mercancia | EM1: Primera Selección | EN1: TRANSPORTISTA. | EO1: UNIDAD RENTADA | EP1: UNIDAD SUPER EXPRESS | EQ1: RFC_Importador | ER1: OtrosIncPed | ES1: Nico5 | ET1: Mercancia_CovesSubModelo | EU1: Días Credito | EV1: Valor Moneda Factura | EW1: UMT DESCRIPCION | EX1: Motivo de Rectificación | EY1: Nombre País Origen/Destino | EZ1: Nombre País Vendedor/Comprador | FA1: Clave de País Origen/Destino | FB1: Clave de País Vendedor/Comprador | FC1: Aduana/Sección Despacho2 | FD1: Fecha de Pago3 | FE1: MES4 | FF1: Fecha Entrada/Presentación5 | FG1: Fecha de Pago funcion6 | FH1: Entrada de pago7 | FI1: Etiqueta Entrada a Pago8 | FJ1: Fecha primera Selección9 | FK1: Entrada a Cruce10 | FL1: Etiqueta entrada a Cruce | FM1: Pago Pedimento a Cruce11 | FN1: Etiqueta Pago Pedimento a Cruce12 | FO1: Pago a Cruce13 | FP1: CRUCE A ENTREGA14 | FQ1: ETIQUETA CRUCE A ENTREGA15 | FR1: FECHA ENTREGA DE MERCANCIA16 | FS1: Entrada a Entrega17 | FT1: Etiqueta Entrada a Entrega18 | FU1: Entrada a Factura19 | FV1: Etiqueta Entrada a Factura20 | FW1: FECHA DE FACTURACIÓN21 | FX1: ENTREGA A ENTREGA DE FACTURA 22 | FY1: ENTREGA A FACTURA23 | FZ1: FECHA RECIBE FACT24 | GA1: FECHA TIMBRADO25 | GB1: CuentaG_FechaFactura26 | GC1: TIEMPO DE FACTURACION27 | GD1: CuentaG_FechaFactura2 | GE1: ETIQUETA ENTREGA A FACTURA28 | GF1: CuentaG_FechaFactura3 | GG1: VERIFICADOR29 | GH1: Comparacion30 | GI1: Clave Pedimento31 | GJ1: Ejecutivo_ABC32 | GK1: Guia Master33 | GL1: Guia House34 | GM1: Pedimento35 | GN1: Tipo Operación Desc36 | GO1: Mercancía37 | GP1: TIPO MERCANCIA OK38 | GQ1: CLASIFICACIÓN DE MERCANCIA39 | GR1: TIPO DE MERCANCIA40 | GS1: Cliente41 | GT1: Unidad de negocio42 | GU1: MOTIVO DE RETRASO43 | GV1: MOTIVO DE RETRASO OTRO44 | GW1: MOTIVO DE RETRASO COMPLETO45 | GX1: Ejecutivo_Tipo_Mercancia46 | GY1: Primera Selección47 | GZ1: TRANSPORTISTA.48 | HA1: UNIDAD RENTADA49 | HB1: UNIDAD SUPER EXPRESS50 | HC1: RFC_Importador51 | HD1: OtrosIncPed52 | HE1: Nico53 | HF1: Mercancia_CovesSubModelo54 | HG1: Días Credito55 | HH1: Valor Moneda Factura 56 | HI1: UMT DESCRIPCION57 | HJ1: Motivo de Rectificación58 | HK1: Nombre País Origen/Destino59 | HL1: Nombre País Vendedor/Comprador60 | HM1: Clave de País Origen/Destino61 | HN1: Clave de País Vendedor/Comprador62 | HO1: Valor Aduana | HP1: Importe DTA FP1 | HQ1: Importe IVA 1 | HR1: IGI | HS1: TotalCuentadeGastos | HT1: Sucursal | HU1: Tipo Sucursal
A2: INTERVET MEXICO SA DE CV | B2: 26-001222 | C2: 3942 | D2: 6001223 | F2: Importación | G2: A1 | H2: 16 | I2: 93586 | J2: 0 | K2: 0 | L2: 0 | M2: 0 | N2: 0 | O2: 0 | P2: 17.17 | Q2: 122 | R2: 470 | T2: 1 BULTOS | U2: 586895 | V2: 586895 | W2: 0 | X2: 0 | Y2: 0 | Z2: 0 | AA2: ESTACION BASE (CONTROLLER SENSEHUB US) | AC2: 580268 | AD2: 13815.905 | AE2: 354 | AF2: 16.00, 16.00 | AG2: 0 | AH2: 0 | AI2: 53 | AJ2: 4695 | AK2: 0 | AL2: 94655 | AM2: 330 | AN2: 99733 | AO2: Cliente | AP2: INTERVET INTERNATIONAL B.V. | AQ2: 210367184 | AR2: CIP | AS2: MXP | AT2: 057-02191140 | AV2: SECO | AW2: 85176101 | AX2: 0 | AY2: 42 | AZ2: 42 | BA2: PIEZA | BC2: ISR | BD2: ZYA | BE2: DESADUANAMIENTO LIBRE | BJ2: PROCEDENCIA: ISRAEL FACTURA C | BK2: COVE267ZLBAN6 | BL2: 44228 | BM2: 0 | BN2: 0 | BO2: 0 | BP2: 0 | BQ2: 0 | BR2: 0 | BS2: 0 | BT2: 0 | BU2: 0 | BV2: 0 | BW2: 0 | BX2: 0 | BY2: 0 | BZ2: 0 | CA2: 0 | CB2: 5300 | CC2: 952 | CD2: 20944.87 | CE2: PEDIENTE DE PAGO | CF2: 20944.87 | CG2: 0 | CH2: 0 | CI2: DANIEL ULISES MORALES REYES | CJ2: KAREN MARTINEZ | CK2: =_xlfn.XLOOKUP($B$2,'BASE DE EXCEL'!C:C,'BASE DE EXCEL'!D:D,"NO HAY REFERENCIA") -> 470 | CL2: =_xlfn.XLOOKUP($B$2,'BASE DE EXCEL'!$C:$C,'BASE DE EXCEL'!F:F,"NO HAY REFERENCIA") -> 3 | CM2: =_xlfn.XLOOKUP($B$2,'BASE DE EXCEL'!$C:$C,'BASE DE EXCEL'!G:G,"NO HAY REFERENCIA") -> 46080 | CN2: =_xlfn.XLOOKUP($B$2,'BASE DE EXCEL'!$C:$C,'BASE DE EXCEL'!H:H,"NO HAY REFERENCIA") -> 46086 | CO2: =_xlfn.XLOOKUP($B$2,'BASE DE EXCEL'!$C:$C,'BASE DE EXCEL'!I:I,"NO HAY REFERENCIA") -> 4 | CP2: =_xlfn.XLOOKUP($B$2,'BASE DE EXCEL'!$C:$C,'BASE DE EXCEL'!J:J,"NO HAY REFERENCIA") -> 4 a 5 días | CQ2: =_xlfn.XLOOKUP($B$2,'BASE DE EXCEL'!$C:$C,'BASE DE EXCEL'!K:K,"NO HAY REFERENCIA") -> 46087 | CR2: =_xlfn.XLOOKUP($B$2,'BASE DE EXCEL'!$C:$C,'BASE DE EXCEL'!L:L,"NO HAY REFERENCIA") -> 5 | CS2: =_xlfn.XLOOKUP($B$2,'BASE DE EXCEL'!$C:$C,'BASE DE EXCEL'!M:M,"NO HAY REFERENCIA") -> 6 | CT2: =_xlfn.XLOOKUP($B$2,'BASE DE EXCEL'!$C:$C,'BASE DE EXCEL'!N:N,"NO HAY REFERENCIA") -> 6 a 10 días | CU2: =_xlfn.XLOOKUP($B$2,'BASE DE EXCEL'!$C:$C,'BASE DE EXCEL'!O:O,"NO HAY REFERENCIA") -> On Time | CV2: =_xlfn.XLOOKUP(B2,'BASE DE EXCEL'!$C:$C,'BASE DE EXCEL'!P:P,"NO HAY REFERENCIA") -> 6 a 10 días | CW2: =_xlfn.XLOOKUP(B2,'BASE DE EXCEL'!$C:$C,'BASE DE EXCEL'!Q:Q,"NO HAY REFERENCIA") -> 46087 | CX2: =_xlfn.XLOOKUP(B2,'BASE DE EXCEL'!$C:$C,'BASE DE EXCEL'!R:R,"NO HAY REFERENCIA") -> 6 | CY2: =_xlfn.XLOOKUP(B2,'BASE DE EXCEL'!$C:$C,'BASE DE EXCEL'!S:S,"NO HAY REFERENCIA") -> 6 a 10 días | CZ2: =_xlfn.XLOOKUP(B2,'BASE DE EXCEL'!$C:$C,'BASE DE EXCEL'!T:T,"NO HAY REFERENCIA") -> On Time | DA2: =_xlfn.XLOOKUP(B2,'BASE DE EXCEL'!$C:$C,'BASE DE EXCEL'!U:U,"NO HAY REFERENCIA") -> 7 | DB2: =_xlfn.XLOOKUP(B2,'BASE DE EXCEL'!$C:$C,'BASE DE EXCEL'!V:V,"NO HAY REFERENCIA") -> 4 a 5 días | DC2: =_xlfn.XLOOKUP(B2,'BASE DE EXCEL'!$C:$C,'BASE DE EXCEL'!W:W,"NO HAY REFERENCIA") -> NULL | DD2: =_xlfn.XLOOKUP(B2,'BASE DE EXCEL'!$C:$C,'BASE DE EXCEL'!X:X,"NO HAY REFERENCIA") -> SIN DATO | DE2: =_xlfn.XLOOKUP(B2,'BASE DE EXCEL'!$C:$C,'BASE DE EXCEL'!Y:Y,"NO HAY REFERENCIA") -> 1 | DF2: =_xlfn.XLOOKUP(B2,'BASE DE EXCEL'!$C:$C,'BASE DE EXCEL'!Z:Z,"NO HAY REFERENCIA") -> 1 día o menos | DG2: =_xlfn.XLOOKUP(B2,'BASE DE EXCEL'!$C:$C,'BASE DE EXCEL'!AA:AA,"NO HAY REFERENCIA") -> 6 | DH2: =_xlfn.XLOOKUP(B2,'BASE DE EXCEL'!$C:$C,'BASE DE EXCEL'!AB:AB,"NO HAY REFERENCIA") -> 0 | DI2: =_xlfn.XLOOKUP(B2,'BASE DE EXCEL'!$C:$C,'BASE DE EXCEL'!AC:AC,"NO HAY REFERENCIA") -> 1 día o menos | DJ2: =_xlfn.XLOOKUP(B2,'BASE DE EXCEL'!$C:$C,'BASE DE EXCEL'!AD:AD,"NO HAY REFERENCIA") -> 46113 | DK2: =_xlfn.XLOOKUP(B2,'BASE DE EXCEL'!$C:$C,'BASE DE EXCEL'!AE:AE,"NO HAY REFERENCIA") -> 5 | DL2: =_xlfn.XLOOKUP(B2,'BASE DE EXCEL'!$C:$C,'BASE DE EXCEL'!AF:AF,"NO HAY REFERENCIA") -> 18 | DM2: =_xlfn.XLOOKUP(B2,'BASE DE EXCEL'!$C:$C,'BASE DE EXCEL'!AG:AG,"NO HAY REFERENCIA") -> 46092 | DN2: =_xlfn.XLOOKUP(B2,'BASE DE EXCEL'!$C:$C,'BASE DE EXCEL'!AH:AH,"NO HAY REFERENCIA") -> 46093 | DO2: =_xlfn.XLOOKUP(B2,'BASE DE EXCEL'!$C:$C,'BASE DE EXCEL'!AI:AI,"NO HAY REFERENCIA") -> NULL | DP2: =_xlfn.XLOOKUP(B2,'BASE DE EXCEL'!$C:$C,'BASE DE EXCEL'!AJ:AJ,"NO HAY REFERENCIA") -> más de 16 días | DQ2: =_xlfn.XLOOKUP(B2,'BASE DE EXCEL'!$C:$C,'BASE DE EXCEL'!AK:AK,"NO HAY REFERENCIA") -> 46113 | DR2: =_xlfn.XLOOKUP(B2,'BASE DE EXCEL'!$C:$C,'BASE DE EXCEL'!AL:AL,"NO HAY REFERENCIA") -> 18 | DS2: =_xlfn.XLOOKUP(B2,'BASE DE EXCEL'!$C:$C,'BASE DE EXCEL'!AM:AM,"NO HAY REFERENCIA") -> más de 16 días | DT2: =_xlfn.XLOOKUP(B2,'BASE DE EXCEL'!$C:$C,'BASE DE EXCEL'!AN:AN,"NO HAY REFERENCIA") -> On Time | DU2: =_xlfn.XLOOKUP(B2,'BASE DE EXCEL'!$C:$C,'BASE DE EXCEL'!AO:AO,"NO HAY REFERENCIA") -> 1 | DV2: =_xlfn.XLOOKUP(B2,'BASE DE EXCEL'!$C:$C,'BASE DE EXCEL'!AP:AP,"NO HAY REFERENCIA") -> Es anterior | DW2: =_xlfn.XLOOKUP(B2,'BASE DE EXCEL'!$C:$C,'BASE DE EXCEL'!AQ:AQ,"NO HAY REFERENCIA") -> A1 | DX2: =_xlfn.XLOOKUP(B2,'BASE DE EXCEL'!$C:$C,'BASE DE EXCEL'!AR:AR,"NO HAY REFERENCIA") -> KAREN MARTINEZ | DY2: =_xlfn.XLOOKUP(B2,'BASE DE EXCEL'!$C:$C,'BASE DE EXCEL'!AS:AS,"NO HAY REFERENCIA") -> 057-02191140 | DZ2: =_xlfn.XLOOKUP(B2,'BASE DE EXCEL'!$C:$C,'BASE DE EXCEL'!AT:AT,"NO HAY REFERENCIA") -> NULL | EA2: =_xlfn.XLOOKUP(B2,'BASE DE EXCEL'!$C:$C,'BASE DE EXCEL'!AU:AU,"NO HAY REFERENCIA") -> 6001223 | EB2: =_xlfn.XLOOKUP(B2,'BASE DE EXCEL'!$C:$C,'BASE DE EXCEL'!AV:AV,"NO HAY REFERENCIA") -> Importación | EC2: =_xlfn.XLOOKUP(B2,'BASE DE EXCEL'!$C:$C,'BASE DE EXCEL'!AW:AW,"NO HAY REFERENCIA") -> ESTACION BASE (CONTROLLER SENSEHUB US) | ED2: =_xlfn.XLOOKUP(B2,'BASE DE EXCEL'!$C:$C,'BASE DE EXCEL'!AX:AX,"NO HAY REFERENCIA") -> SIN CLASIFICACION | EE2: =_xlfn.XLOOKUP(B2,'BASE DE EXCEL'!$C:$C,'BASE DE EXCEL'!AY:AY,"NO HAY REFERENCIA") -> 0 | EF2: =_xlfn.XLOOKUP(B2,'BASE DE EXCEL'!$C:$C,'BASE DE EXCEL'!AZ:AZ,"NO HAY REFERENCIA") -> Cargas de Importación | EG2: =_xlfn.XLOOKUP(B2,'BASE DE EXCEL'!$C:$C,'BASE DE EXCEL'!BA:BA,"NO HAY REFERENCIA") -> INTERVET MEXICO SA DE CV | EH2: =_xlfn.XLOOKUP(B2,'BASE DE EXCEL'!$C:$C,'BASE DE EXCEL'!BB:BB,"NO HAY REFERENCIA") -> 0 | EI2: =_xlfn.XLOOKUP(B2,'BASE DE EXCEL'!$C:$C,'BASE DE EXCEL'!BC:BC,"NO HAY REFERENCIA") -> 0 | EJ2: =_xlfn.XLOOKUP(B2,'BASE DE EXCEL'!$C:$C,'BASE DE EXCEL'!BD:BD,"NO HAY REFERENCIA") -> 0 | EK2: =_xlfn.XLOOKUP(B2,'BASE DE EXCEL'!$C:$C,'BASE DE EXCEL'!BE:BE,"NO HAY REFERENCIA") -> 0 | EL2: =_xlfn.XLOOKUP(B2,'BASE DE EXCEL'!$C:$C,'BASE DE EXCEL'!BF:BF,"NO HAY REFERENCIA") -> REFACCIONES | EM2: =_xlfn.XLOOKUP(B2,'BASE DE EXCEL'!$C:$C,'BASE DE EXCEL'!BG:BG,"NO HAY REFERENCIA") -> Verde | EN2: =_xlfn.XLOOKUP(B2,'BASE DE EXCEL'!$C:$C,'BASE DE EXCEL'!BH:BH,"NO HAY REFERENCIA") -> NULL | EO2: =_xlfn.XLOOKUP(B2,'BASE DE EXCEL'!$C:$C,'BASE DE EXCEL'!BI:BI,"NO HAY REFERENCIA") -> 0 | EP2: =_xlfn.XLOOKUP(B2,'BASE DE EXCEL'!$C:$C,'BASE DE EXCEL'!BJ:BJ,"NO HAY REFERENCIA") -> NISSAN 3 | EQ2: =_xlfn.XLOOKUP(B2,'BASE DE EXCEL'!$C:$C,'BASE DE EXCEL'!BK:BK,"NO HAY REFERENCIA") -> IME850329RH2 | ER2: =_xlfn.XLOOKUP(B2,'BASE DE EXCEL'!$C:$C,'BASE DE EXCEL'!BL:BL,"NO HAY REFERENCIA") -> 0 | ES2: =_xlfn.XLOOKUP(B2,'BASE DE EXCEL'!$C:$C,'BASE DE EXCEL'!BM:BM,"NO HAY REFERENCIA") -> 0 | ET2: =_xlfn.XLOOKUP(B2,'BASE DE EXCEL'!$C:$C,'BASE DE EXCEL'!BN:BN,"NO HAY REFERENCIA") -> LOTE: IL20260101 | EU2: =_xlfn.XLOOKUP(B2,'BASE DE EXCEL'!$C:$C,'BASE DE EXCEL'!BO:BO,"NO HAY REFERENCIA") -> 90 | EV2: =_xlfn.XLOOKUP(B2,'BASE DE EXCEL'!$C:$C,'BASE DE EXCEL'!BP:BP,"NO HAY REFERENCIA") -> 586894.97 | EW2: =_xlfn.XLOOKUP(B2,'BASE DE EXCEL'!$C:$C,'BASE DE EXCEL'!BQ:BQ,"NO HAY REFERENCIA") -> PIEZA,PIEZA | EX2: =_xlfn.XLOOKUP(B2,'BASE DE EXCEL'!$C:$C,'BASE DE EXCEL'!BR:BR,"NO HAY REFERENCIA") -> 0 | EY2: =_xlfn.XLOOKUP(B2,'BASE DE EXCEL'!$C:$C,'BASE DE EXCEL'!BS:BS,"NO HAY REFERENCIA") -> ISRAEL (ESTADO DE) | EZ2: =_xlfn.XLOOKUP(B2,'BASE DE EXCEL'!$C:$C,'BASE DE EXCEL'!BT:BT,"NO HAY REFERENCIA") -> PAISES BAJOS (REINO DE LOS) (HOLANDA) | FA2: =_xlfn.XLOOKUP(B2,'BASE DE EXCEL'!$C:$C,'BASE DE EXCEL'!BU:BU,"NO HAY REFERENCIA") -> ISR | FB2: =_xlfn.XLOOKUP(B2,'BASE DE EXCEL'!$C:$C,'BASE DE EXCEL'!BV:BV,"NO HAY REFERENCIA") -> ZYA | FC2: =_xlfn.XLOOKUP(B2,QUERY!$C:$C,QUERY!D:D) -> 470 | FD2: =_xlfn.XLOOKUP(B2,QUERY!$C:$C,QUERY!E:E) -> 46086 | FE2: =_xlfn.XLOOKUP(B2,QUERY!$C:$C,QUERY!F:F) -> 3 | FF2: =_xlfn.XLOOKUP(B2,QUERY!$C:$C,QUERY!G:G) -> 46080 | FG2: =_xlfn.XLOOKUP(B2,QUERY!$C:$C,QUERY!H:H) -> 46086 | FH2: =_xlfn.XLOOKUP(B2,QUERY!$C:$C,QUERY!I:I) -> 4 | FI2: =_xlfn.XLOOKUP(B2,QUERY!$C:$C,QUERY!J:J) -> 4 a 5 días | FJ2: =_xlfn.XLOOKUP(B2,QUERY!$C:$C,QUERY!K:K) -> 46087 | FK2: =_xlfn.XLOOKUP(B2,QUERY!$C:$C,QUERY!L:L) -> 5 | FL2: =_xlfn.XLOOKUP(B2,QUERY!$C:$C,QUERY!M:M) -> 4 a 5 días | FM2: =_xlfn.XLOOKUP(B2,QUERY!$C:$C,QUERY!N:N) -> 1 | FN2: =_xlfn.XLOOKUP(B2,QUERY!$C:$C,QUERY!O:O) -> 1 día o menos | FO2: =_xlfn.XLOOKUP(B2,QUERY!$C:$C,QUERY!P:P) -> 1 | FP2: =_xlfn.XLOOKUP(B2,QUERY!$C:$C,QUERY!Q:Q) -> 0 | FQ2: =_xlfn.XLOOKUP(B2,QUERY!$C:$C,QUERY!R:R) -> 1 día o menos | FR2: =_xlfn.XLOOKUP(B2,QUERY!$C:$C,QUERY!S:S) -> 46087 | FS2: =_xlfn.XLOOKUP(B2,QUERY!$C:$C,QUERY!T:T) -> 5 | FT2: =_xlfn.XLOOKUP(B2,QUERY!$C:$C,QUERY!U:U) -> 4 a 5 días | FU2: =_xlfn.XLOOKUP(B2,QUERY!$C:$C,QUERY!V:V) -> 23 | FV2: =_xlfn.XLOOKUP(B2,QUERY!$C:$C,QUERY!W:W) -> más de 16 días | FW2: =_xlfn.XLOOKUP(B2,QUERY!$C:$C,QUERY!X:X) -> 46113 | FX2: =_xlfn.XLOOKUP(B2,QUERY!$C:$C,QUERY!Y:Y) -> 3 | FY2: =_xlfn.XLOOKUP(B2,QUERY!$C:$C,QUERY!Z:Z) -> 18 | FZ2: =_xlfn.XLOOKUP(B2,QUERY!$C:$C,QUERY!AA:AA) -> más de 16 días | GA2: =_xlfn.XLOOKUP(B2,QUERY!$C:$C,QUERY!AB:AB) -> 46092 | GB2: =_xlfn.XLOOKUP(B2,QUERY!$C:$C,QUERY!AC:AC) -> 46093 | GC2: =_xlfn.XLOOKUP(B2,QUERY!$C:$C,QUERY!AD:AD) -> 15 | GD2: =_xlfn.XLOOKUP(B2,QUERY!$C:$C,QUERY!AE:AE) -> 46113 | GE2: =_xlfn.XLOOKUP(B2,QUERY!$C:$C,QUERY!AF:AF) -> 1 | GF2: =_xlfn.XLOOKUP(B2,QUERY!$C:$C,QUERY!AG:AG) -> Es anterior | GG2: =_xlfn.XLOOKUP(B2,QUERY!$C:$C,QUERY!AH:AH) -> A1 | GH2: =_xlfn.XLOOKUP(B2,QUERY!$C:$C,QUERY!AI:AI) -> KAREN MARTINEZ | GI2: =_xlfn.XLOOKUP(B2,QUERY!$C:$C,QUERY!AJ:AJ) -> 057-02191140 | GJ2: =_xlfn.XLOOKUP(B2,QUERY!$C:$C,QUERY!AK:AK) -> NULL | GK2: =_xlfn.XLOOKUP(B2,QUERY!$C:$C,QUERY!AL:AL) -> 6001223 | GL2: =_xlfn.XLOOKUP(B2,QUERY!$C:$C,QUERY!AM:AM) -> Importación | GM2: =_xlfn.XLOOKUP(B2,QUERY!$C:$C,QUERY!AN:AN) -> ESTACION BASE (CONTROLLER SENSEHUB US) | GN2: =_xlfn.XLOOKUP(B2,QUERY!$C:$C,QUERY!AO:AO) -> SIN CLASIFICACION | GO2: =_xlfn.XLOOKUP(B2,QUERY!$C:$C,QUERY!AP:AP) -> 0 | GP2: =_xlfn.XLOOKUP(B2,QUERY!$C:$C,QUERY!AQ:AQ) -> Cargas de Importación | GQ2: =_xlfn.XLOOKUP(B2,QUERY!$C:$C,QUERY!AR:AR) -> INTERVET MEXICO SA DE CV | GR2: =_xlfn.XLOOKUP(B2,QUERY!$C:$C,QUERY!AS:AS) -> 0 | GS2: =_xlfn.XLOOKUP(B2,QUERY!$C:$C,QUERY!AT:AT) -> 0 | GT2: =_xlfn.XLOOKUP(B2,QUERY!$C:$C,QUERY!AU:AU) -> 0 | GU2: =_xlfn.XLOOKUP(B2,QUERY!$C:$C,QUERY!AV:AV) -> 0 | GV2: =_xlfn.XLOOKUP(B2,QUERY!$C:$C,QUERY!AW:AW) -> REFACCIONES | GW2: =_xlfn.XLOOKUP(B2,QUERY!$C:$C,QUERY!AX:AX) -> Verde | GX2: =_xlfn.XLOOKUP(B2,QUERY!$C:$C,QUERY!AY:AY) -> NULL | GY2: =_xlfn.XLOOKUP(B2,QUERY!$C:$C,QUERY!AZ:AZ) -> 0 | GZ2: =_xlfn.XLOOKUP(B2,QUERY!$C:$C,QUERY!BA:BA) -> NISSAN 3 | HA2: =_xlfn.XLOOKUP(B2,QUERY!$C:$C,QUERY!BB:BB) -> IME850329RH2 | HB2: =_xlfn.XLOOKUP(B2,QUERY!$C:$C,QUERY!BC:BC) -> 0 | HC2: =_xlfn.XLOOKUP(B2,QUERY!$C:$C,QUERY!BD:BD) -> 0 | HD2: =_xlfn.XLOOKUP(B2,QUERY!$C:$C,QUERY!BE:BE) -> LOTE: IL20260101 | HE2: =_xlfn.XLOOKUP(B2,QUERY!$C:$C,QUERY!BF:BF) -> 90 | HF2: =_xlfn.XLOOKUP(B2,QUERY!$C:$C,QUERY!BG:BG) -> 586894.97 | HG2: =_xlfn.XLOOKUP(B2,QUERY!$C:$C,QUERY!BH:BH) -> PIEZA,PIEZA | HH2: =_xlfn.XLOOKUP(B2,QUERY!$C:$C,QUERY!BI:BI) -> 0 | HI2: =_xlfn.XLOOKUP(B2,QUERY!$C:$C,QUERY!BJ:BJ) -> ISRAEL (ESTADO DE) | HJ2: =_xlfn.XLOOKUP(B2,QUERY!$C:$C,QUERY!BK:BK) -> PAISES BAJOS (REINO DE LOS) (HOLANDA) | HK2: =_xlfn.XLOOKUP(B2,QUERY!$C:$C,QUERY!BL:BL) -> ISR | HL2: =_xlfn.XLOOKUP(B2,QUERY!$C:$C,QUERY!BM:BM) -> ZYA | HM2: =_xlfn.XLOOKUP(B2,QUERY!$C:$C,QUERY!BN:BN) -> 586895 | HN2: =_xlfn.XLOOKUP(B2,QUERY!$C:$C,QUERY!BO:BO) -> 4695.00 | HO2: =_xlfn.XLOOKUP(B2,QUERY!$C:$C,QUERY!BP:BP) -> 94655.00 | HP2: =_xlfn.XLOOKUP(B2,QUERY!$C:$C,QUERY!BQ:BQ) -> NULL | HQ2: =_xlfn.XLOOKUP(B2,QUERY!$C:$C,QUERY!BR:BR) -> 20944.87 | HR2: =_xlfn.XLOOKUP(B2,QUERY!$C:$C,QUERY!BS:BS) -> 0 | HS2: =_xlfn.XLOOKUP(B2,QUERY!$C:$C,QUERY!BT:BT) -> 0 | HT2: =_xlfn.XLOOKUP(B2,QUERY!$C:$C,QUERY!A:A) -> CIUDAD DE MÉXICO | HU2: =_xlfn.XLOOKUP(B2,QUERY!$C:$C,QUERY!B:B) -> AÉREO AICM
A3: INTERVET MEXICO SA DE CV | B3: 26-001222 | C3: 3942 | D3: 6001223 | F3: Importación | G3: A1 | H3: 16 | I3: 1069 | J3: 0 | K3: 0 | L3: 0 | M3: 0 | N3: 0 | O3: 0 | P3: 0 | Q3: 0 | R3: 470 | T3: 0 | U3: 0 | V3: 0 | W3: 0 | X3: 0 | Y3: 0 | Z3: 0 | AA3: PARTES PARA APARATO DE CONTROL (PANEL KIT FOR ED200N BLUE) | AC3: 6627 | AD3: 265.08 | AE3: 0 | AF3: 0 | AG3: 0 | AH3: 0 | AI3: 0 | AJ3: 0 | AK3: 0 | AL3: 0 | AM3: 0 | AN3: 0 | AP3: INTERVET INTERNATIONAL B.V. | AQ3: 210367184 | AR3: CIP | AS3: MXP | AT3: 0 | AU3: 0 | AV3: 0 | AW3: 85389001 | AX3: 0 | AY3: 25 | AZ3: 25 | BA3: PIEZA | BC3: ISR | BD3: ZYA | BK3: COVE267ZLBAN6 | BL3: 0 | BM3: 0 | BN3: 0 | BO3: 0 | BP3: 0 | BQ3: 0 | BR3: 0 | BS3: 0 | BT3: 0 | BU3: 0 | BV3: 0 | BW3: 0 | BX3: 0 | BY3: 0 | BZ3: 0 | CA3: 0 | CB3: 0 | CC3: 0 | CD3: 0 | CE3: PEDIENTE DE PAGO | CF3: 0 | CG3: 0 | CH3: 0 | CI3: DANIEL ULISES MORALES REYES | CJ3: KAREN MARTINEZ | CK3: =_xlfn.XLOOKUP($B$2,'BASE DE EXCEL'!C:C,'BASE DE EXCEL'!D:D,"NO HAY REFERENCIA") -> 470 | CL3: =_xlfn.XLOOKUP($B$2,'BASE DE EXCEL'!$C:$C,'BASE DE EXCEL'!F:F,"NO HAY REFERENCIA") -> 3 | CM3: =_xlfn.XLOOKUP($B$2,'BASE DE EXCEL'!$C:$C,'BASE DE EXCEL'!G:G,"NO HAY REFERENCIA") -> 46080 | CN3: =_xlfn.XLOOKUP($B$2,'BASE DE EXCEL'!$C:$C,'BASE DE EXCEL'!H:H,"NO HAY REFERENCIA") -> 46086 | CO3: =_xlfn.XLOOKUP($B$2,'BASE DE EXCEL'!$C:$C,'BASE DE EXCEL'!I:I,"NO HAY REFERENCIA") -> 4 | CP3: =_xlfn.XLOOKUP($B$2,'BASE DE EXCEL'!$C:$C,'BASE DE EXCEL'!J:J,"NO HAY REFERENCIA") -> 4 a 5 días | CQ3: =_xlfn.XLOOKUP($B$2,'BASE DE EXCEL'!$C:$C,'BASE DE EXCEL'!K:K,"NO HAY REFERENCIA") -> 46087 | CR3: =_xlfn.XLOOKUP($B$2,'BASE DE EXCEL'!$C:$C,'BASE DE EXCEL'!L:L,"NO HAY REFERENCIA") -> 5 | CS3: =_xlfn.XLOOKUP($B$2,'BASE DE EXCEL'!$C:$C,'BASE DE EXCEL'!M:M,"NO HAY REFERENCIA") -> 6 | CT3: =_xlfn.XLOOKUP($B$2,'BASE DE EXCEL'!$C:$C,'BASE DE EXCEL'!N:N,"NO HAY REFERENCIA") -> 6 a 10 días | CU3: =_xlfn.XLOOKUP($B$2,'BASE DE EXCEL'!$C:$C,'BASE DE EXCEL'!O:O,"NO HAY REFERENCIA") -> On Time | CV3: =_xlfn.XLOOKUP(B3,'BASE DE EXCEL'!$C:$C,'BASE DE EXCEL'!P:P,"NO HAY REFERENCIA") -> 6 a 10 días | CW3: =_xlfn.XLOOKUP(B3,'BASE DE EXCEL'!$C:$C,'BASE DE EXCEL'!Q:Q,"NO HAY REFERENCIA") -> 46087 | CX3: =_xlfn.XLOOKUP(B3,'BASE DE EXCEL'!$C:$C,'BASE DE EXCEL'!R:R,"NO HAY REFERENCIA") -> 6 | CY3: =_xlfn.XLOOKUP(B3,'BASE DE EXCEL'!$C:$C,'BASE DE EXCEL'!S:S,"NO HAY REFERENCIA") -> 6 a 10 días | CZ3: =_xlfn.XLOOKUP(B3,'BASE DE EXCEL'!$C:$C,'BASE DE EXCEL'!T:T,"NO HAY REFERENCIA") -> On Time | DA3: =_xlfn.XLOOKUP(B3,'BASE DE EXCEL'!$C:$C,'BASE DE EXCEL'!U:U,"NO HAY REFERENCIA") -> 7 | DB3: =_xlfn.XLOOKUP(B3,'BASE DE EXCEL'!$C:$C,'BASE DE EXCEL'!V:V,"NO HAY REFERENCIA") -> 4 a 5 días | DC3: =_xlfn.XLOOKUP(B3,'BASE DE EXCEL'!$C:$C,'BASE DE EXCEL'!W:W,"NO HAY REFERENCIA") -> NULL | DD3: =_xlfn.XLOOKUP(B3,'BASE DE EXCEL'!$C:$C,'BASE DE EXCEL'!X:X,"NO HAY REFERENCIA") -> SIN DATO | DE3: =_xlfn.XLOOKUP(B3,'BASE DE EXCEL'!$C:$C,'BASE DE EXCEL'!Y:Y,"NO HAY REFERENCIA") -> 1 | DF3: =_xlfn.XLOOKUP(B3,'BASE DE EXCEL'!$C:$C,'BASE DE EXCEL'!Z:Z,"NO HAY REFERENCIA") -> 1 día o menos | DG3: =_xlfn.XLOOKUP(B3,'BASE DE EXCEL'!$C:$C,'BASE DE EXCEL'!AA:AA,"NO HAY REFERENCIA") -> 6 | DH3: =_xlfn.XLOOKUP(B3,'BASE DE EXCEL'!$C:$C,'BASE DE EXCEL'!AB:AB,"NO HAY REFERENCIA") -> 0 | DI3: =_xlfn.XLOOKUP(B3,'BASE DE EXCEL'!$C:$C,'BASE DE EXCEL'!AC:AC,"NO HAY REFERENCIA") -> 1 día o menos | DJ3: =_xlfn.XLOOKUP(B3,'BASE DE EXCEL'!$C:$C,'BASE DE EXCEL'!AD:AD,"NO HAY REFERENCIA") -> 46113 | DK3: =_xlfn.XLOOKUP(B3,'BASE DE EXCEL'!$C:$C,'BASE DE EXCEL'!AE:AE,"NO HAY REFERENCIA") -> 5 | DL3: =_xlfn.XLOOKUP(B3,'BASE DE EXCEL'!$C:$C,'BASE DE EXCEL'!AF:AF,"NO HAY REFERENCIA") -> 18 | DM3: =_xlfn.XLOOKUP(B3,'BASE DE EXCEL'!$C:$C,'BASE DE EXCEL'!AG:AG,"NO HAY REFERENCIA") -> 46092 | DN3: =_xlfn.XLOOKUP(B3,'BASE DE EXCEL'!$C:$C,'BASE DE EXCEL'!AH:AH,"NO HAY REFERENCIA") -> 46093 | DO3: =_xlfn.XLOOKUP(B3,'BASE DE EXCEL'!$C:$C,'BASE DE EXCEL'!AI:AI,"NO HAY REFERENCIA") -> NULL | DP3: =_xlfn.XLOOKUP(B3,'BASE DE EXCEL'!$C:$C,'BASE DE EXCEL'!AJ:AJ,"NO HAY REFERENCIA") -> más de 16 días | DQ3: =_xlfn.XLOOKUP(B3,'BASE DE EXCEL'!$C:$C,'BASE DE EXCEL'!AK:AK,"NO HAY REFERENCIA") -> 46113 | DR3: =_xlfn.XLOOKUP(B3,'BASE DE EXCEL'!$C:$C,'BASE DE EXCEL'!AL:AL,"NO HAY REFERENCIA") -> 18 | DS3: =_xlfn.XLOOKUP(B3,'BASE DE EXCEL'!$C:$C,'BASE DE EXCEL'!AM:AM,"NO HAY REFERENCIA") -> más de 16 días | DT3: =_xlfn.XLOOKUP(B3,'BASE DE EXCEL'!$C:$C,'BASE DE EXCEL'!AN:AN,"NO HAY REFERENCIA") -> On Time | DU3: =_xlfn.XLOOKUP(B3,'BASE DE EXCEL'!$C:$C,'BASE DE EXCEL'!AO:AO,"NO HAY REFERENCIA") -> 1 | DV3: =_xlfn.XLOOKUP(B3,'BASE DE EXCEL'!$C:$C,'BASE DE EXCEL'!AP:AP,"NO HAY REFERENCIA") -> Es anterior | DW3: =_xlfn.XLOOKUP(B3,'BASE DE EXCEL'!$C:$C,'BASE DE EXCEL'!AQ:AQ,"NO HAY REFERENCIA") -> A1 | DX3: =_xlfn.XLOOKUP(B3,'BASE DE EXCEL'!$C:$C,'BASE DE EXCEL'!AR:AR,"NO HAY REFERENCIA") -> KAREN MARTINEZ | DY3: =_xlfn.XLOOKUP(B3,'BASE DE EXCEL'!$C:$C,'BASE DE EXCEL'!AS:AS,"NO HAY REFERENCIA") -> 057-02191140 | DZ3: =_xlfn.XLOOKUP(B3,'BASE DE EXCEL'!$C:$C,'BASE DE EXCEL'!AT:AT,"NO HAY REFERENCIA") -> NULL | EA3: =_xlfn.XLOOKUP(B3,'BASE DE EXCEL'!$C:$C,'BASE DE EXCEL'!AU:AU,"NO HAY REFERENCIA") -> 6001223 | EB3: =_xlfn.XLOOKUP(B3,'BASE DE EXCEL'!$C:$C,'BASE DE EXCEL'!AV:AV,"NO HAY REFERENCIA") -> Importación | EC3: =_xlfn.XLOOKUP(B3,'BASE DE EXCEL'!$C:$C,'BASE DE EXCEL'!AW:AW,"NO HAY REFERENCIA") -> ESTACION BASE (CONTROLLER SENSEHUB US) | ED3: =_xlfn.XLOOKUP(B3,'BASE DE EXCEL'!$C:$C,'BASE DE EXCEL'!AX:AX,"NO HAY REFERENCIA") -> SIN CLASIFICACION | EE3: =_xlfn.XLOOKUP(B3,'BASE DE EXCEL'!$C:$C,'BASE DE EXCEL'!AY:AY,"NO HAY REFERENCIA") -> 0 | EF3: =_xlfn.XLOOKUP(B3,'BASE DE EXCEL'!$C:$C,'BASE DE EXCEL'!AZ:AZ,"NO HAY REFERENCIA") -> Cargas de Importación | EG3: =_xlfn.XLOOKUP(B3,'BASE DE EXCEL'!$C:$C,'BASE DE EXCEL'!BA:BA,"NO HAY REFERENCIA") -> INTERVET MEXICO SA DE CV | EH3: =_xlfn.XLOOKUP(B3,'BASE DE EXCEL'!$C:$C,'BASE DE EXCEL'!BB:BB,"NO HAY REFERENCIA") -> 0 | EI3: =_xlfn.XLOOKUP(B3,'BASE DE EXCEL'!$C:$C,'BASE DE EXCEL'!BC:BC,"NO HAY REFERENCIA") -> 0 | EJ3: =_xlfn.XLOOKUP(B3,'BASE DE EXCEL'!$C:$C,'BASE DE EXCEL'!BD:BD,"NO HAY REFERENCIA") -> 0 | EK3: =_xlfn.XLOOKUP(B3,'BASE DE EXCEL'!$C:$C,'BASE DE EXCEL'!BE:BE,"NO HAY REFERENCIA") -> 0 | EL3: =_xlfn.XLOOKUP(B3,'BASE DE EXCEL'!$C:$C,'BASE DE EXCEL'!BF:BF,"NO HAY REFERENCIA") -> REFACCIONES | EM3: =_xlfn.XLOOKUP(B3,'BASE DE EXCEL'!$C:$C,'BASE DE EXCEL'!BG:BG,"NO HAY REFERENCIA") -> Verde | EN3: =_xlfn.XLOOKUP(B3,'BASE DE EXCEL'!$C:$C,'BASE DE EXCEL'!BH:BH,"NO HAY REFERENCIA") -> NULL | EO3: =_xlfn.XLOOKUP(B3,'BASE DE EXCEL'!$C:$C,'BASE DE EXCEL'!BI:BI,"NO HAY REFERENCIA") -> 0 | EP3: =_xlfn.XLOOKUP(B3,'BASE DE EXCEL'!$C:$C,'BASE DE EXCEL'!BJ:BJ,"NO HAY REFERENCIA") -> NISSAN 3 | EQ3: =_xlfn.XLOOKUP(B3,'BASE DE EXCEL'!$C:$C,'BASE DE EXCEL'!BK:BK,"NO HAY REFERENCIA") -> IME850329RH2 | ER3: =_xlfn.XLOOKUP(B3,'BASE DE EXCEL'!$C:$C,'BASE DE EXCEL'!BL:BL,"NO HAY REFERENCIA") -> 0 | ES3: =_xlfn.XLOOKUP(B3,'BASE DE EXCEL'!$C:$C,'BASE DE EXCEL'!BM:BM,"NO HAY REFERENCIA") -> 0 | ET3: =_xlfn.XLOOKUP(B3,'BASE DE EXCEL'!$C:$C,'BASE DE EXCEL'!BN:BN,"NO HAY REFERENCIA") -> LOTE: IL20260101 | EU3: =_xlfn.XLOOKUP(B3,'BASE DE EXCEL'!$C:$C,'BASE DE EXCEL'!BO:BO,"NO HAY REFERENCIA") -> 90 | EV3: =_xlfn.XLOOKUP(B3,'BASE DE EXCEL'!$C:$C,'BASE DE EXCEL'!BP:BP,"NO HAY REFERENCIA") -> 586894.97 | EW3: =_xlfn.XLOOKUP(B3,'BASE DE EXCEL'!$C:$C,'BASE DE EXCEL'!BQ:BQ,"NO HAY REFERENCIA") -> PIEZA,PIEZA | EX3: =_xlfn.XLOOKUP(B3,'BASE DE EXCEL'!$C:$C,'BASE DE EXCEL'!BR:BR,"NO HAY REFERENCIA") -> 0 | EY3: =_xlfn.XLOOKUP(B3,'BASE DE EXCEL'!$C:$C,'BASE DE EXCEL'!BS:BS,"NO HAY REFERENCIA") -> ISRAEL (ESTADO DE) | EZ3: =_xlfn.XLOOKUP(B3,'BASE DE EXCEL'!$C:$C,'BASE DE EXCEL'!BT:BT,"NO HAY REFERENCIA") -> PAISES BAJOS (REINO DE LOS) (HOLANDA) | FA3: =_xlfn.XLOOKUP(B3,'BASE DE EXCEL'!$C:$C,'BASE DE EXCEL'!BU:BU,"NO HAY REFERENCIA") -> ISR | FB3: =_xlfn.XLOOKUP(B3,'BASE DE EXCEL'!$C:$C,'BASE DE EXCEL'!BV:BV,"NO HAY REFERENCIA") -> ZYA | FC3: =_xlfn.XLOOKUP(B3,QUERY!$C:$C,QUERY!D:D) -> 470 | FD3: =_xlfn.XLOOKUP(B3,QUERY!$C:$C,QUERY!E:E) -> 46086 | FE3: =_xlfn.XLOOKUP(B3,QUERY!$C:$C,QUERY!F:F) -> 3 | FF3: =_xlfn.XLOOKUP(B3,QUERY!$C:$C,QUERY!G:G) -> 46080 | FG3: =_xlfn.XLOOKUP(B3,QUERY!$C:$C,QUERY!H:H) -> 46086 | FH3: =_xlfn.XLOOKUP(B3,QUERY!$C:$C,QUERY!I:I) -> 4 | FI3: =_xlfn.XLOOKUP(B3,QUERY!$C:$C,QUERY!J:J) -> 4 a 5 días | FJ3: =_xlfn.XLOOKUP(B3,QUERY!$C:$C,QUERY!K:K) -> 46087 | FK3: =_xlfn.XLOOKUP(B3,QUERY!$C:$C,QUERY!L:L) -> 5 | FL3: =_xlfn.XLOOKUP(B3,QUERY!$C:$C,QUERY!M:M) -> 4 a 5 días | FM3: =_xlfn.XLOOKUP(B3,QUERY!$C:$C,QUERY!N:N) -> 1 | FN3: =_xlfn.XLOOKUP(B3,QUERY!$C:$C,QUERY!O:O) -> 1 día o menos | FO3: =_xlfn.XLOOKUP(B3,QUERY!$C:$C,QUERY!P:P) -> 1 | FP3: =_xlfn.XLOOKUP(B3,QUERY!$C:$C,QUERY!Q:Q) -> 0 | FQ3: =_xlfn.XLOOKUP(B3,QUERY!$C:$C,QUERY!R:R) -> 1 día o menos | FR3: =_xlfn.XLOOKUP(B3,QUERY!$C:$C,QUERY!S:S) -> 46087 | FS3: =_xlfn.XLOOKUP(B3,QUERY!$C:$C,QUERY!T:T) -> 5 | FT3: =_xlfn.XLOOKUP(B3,QUERY!$C:$C,QUERY!U:U) -> 4 a 5 días | FU3: =_xlfn.XLOOKUP(B3,QUERY!$C:$C,QUERY!V:V) -> 23 | FV3: =_xlfn.XLOOKUP(B3,QUERY!$C:$C,QUERY!W:W) -> más de 16 días | FW3: =_xlfn.XLOOKUP(B3,QUERY!$C:$C,QUERY!X:X) -> 46113 | FX3: =_xlfn.XLOOKUP(B3,QUERY!$C:$C,QUERY!Y:Y) -> 3 | FY3: =_xlfn.XLOOKUP(B3,QUERY!$C:$C,QUERY!Z:Z) -> 18 | FZ3: =_xlfn.XLOOKUP(B3,QUERY!$C:$C,QUERY!AA:AA) -> más de 16 días | GA3: =_xlfn.XLOOKUP(B3,QUERY!$C:$C,QUERY!AB:AB) -> 46092 | GB3: =_xlfn.XLOOKUP(B3,QUERY!$C:$C,QUERY!AC:AC) -> 46093 | GC3: =_xlfn.XLOOKUP(B3,QUERY!$C:$C,QUERY!AD:AD) -> 15 | GD3: =_xlfn.XLOOKUP(B3,QUERY!$C:$C,QUERY!AE:AE) -> 46113 | GE3: =_xlfn.XLOOKUP(B3,QUERY!$C:$C,QUERY!AF:AF) -> 1 | GF3: =_xlfn.XLOOKUP(B3,QUERY!$C:$C,QUERY!AG:AG) -> Es anterior | GG3: =_xlfn.XLOOKUP(B3,QUERY!$C:$C,QUERY!AH:AH) -> A1 | GH3: =_xlfn.XLOOKUP(B3,QUERY!$C:$C,QUERY!AI:AI) -> KAREN MARTINEZ | GI3: =_xlfn.XLOOKUP(B3,QUERY!$C:$C,QUERY!AJ:AJ) -> 057-02191140 | GJ3: =_xlfn.XLOOKUP(B3,QUERY!$C:$C,QUERY!AK:AK) -> NULL | GK3: =_xlfn.XLOOKUP(B3,QUERY!$C:$C,QUERY!AL:AL) -> 6001223 | GL3: =_xlfn.XLOOKUP(B3,QUERY!$C:$C,QUERY!AM:AM) -> Importación | GM3: =_xlfn.XLOOKUP(B3,QUERY!$C:$C,QUERY!AN:AN) -> ESTACION BASE (CONTROLLER SENSEHUB US) | GN3: =_xlfn.XLOOKUP(B3,QUERY!$C:$C,QUERY!AO:AO) -> SIN CLASIFICACION | GO3: =_xlfn.XLOOKUP(B3,QUERY!$C:$C,QUERY!AP:AP) -> 0 | GP3: =_xlfn.XLOOKUP(B3,QUERY!$C:$C,QUERY!AQ:AQ) -> Cargas de Importación | GQ3: =_xlfn.XLOOKUP(B3,QUERY!$C:$C,QUERY!AR:AR) -> INTERVET MEXICO SA DE CV | GR3: =_xlfn.XLOOKUP(B3,QUERY!$C:$C,QUERY!AS:AS) -> 0 | GS3: =_xlfn.XLOOKUP(B3,QUERY!$C:$C,QUERY!AT:AT) -> 0 | GT3: =_xlfn.XLOOKUP(B3,QUERY!$C:$C,QUERY!AU:AU) -> 0 | GU3: =_xlfn.XLOOKUP(B3,QUERY!$C:$C,QUERY!AV:AV) -> 0 | GV3: =_xlfn.XLOOKUP(B3,QUERY!$C:$C,QUERY!AW:AW) -> REFACCIONES | GW3: =_xlfn.XLOOKUP(B3,QUERY!$C:$C,QUERY!AX:AX) -> Verde | GX3: =_xlfn.XLOOKUP(B3,QUERY!$C:$C,QUERY!AY:AY) -> NULL | GY3: =_xlfn.XLOOKUP(B3,QUERY!$C:$C,QUERY!AZ:AZ) -> 0 | GZ3: =_xlfn.XLOOKUP(B3,QUERY!$C:$C,QUERY!BA:BA) -> NISSAN 3 | HA3: =_xlfn.XLOOKUP(B3,QUERY!$C:$C,QUERY!BB:BB) -> IME850329RH2 | HB3: =_xlfn.XLOOKUP(B3,QUERY!$C:$C,QUERY!BC:BC) -> 0 | HC3: =_xlfn.XLOOKUP(B3,QUERY!$C:$C,QUERY!BD:BD) -> 0 | HD3: =_xlfn.XLOOKUP(B3,QUERY!$C:$C,QUERY!BE:BE) -> LOTE: IL20260101 | HE3: =_xlfn.XLOOKUP(B3,QUERY!$C:$C,QUERY!BF:BF) -> 90 | HF3: =_xlfn.XLOOKUP(B3,QUERY!$C:$C,QUERY!BG:BG) -> 586894.97 | HG3: =_xlfn.XLOOKUP(B3,QUERY!$C:$C,QUERY!BH:BH) -> PIEZA,PIEZA | HH3: =_xlfn.XLOOKUP(B3,QUERY!$C:$C,QUERY!BI:BI) -> 0 | HI3: =_xlfn.XLOOKUP(B3,QUERY!$C:$C,QUERY!BJ:BJ) -> ISRAEL (ESTADO DE) | HJ3: =_xlfn.XLOOKUP(B3,QUERY!$C:$C,QUERY!BK:BK) -> PAISES BAJOS (REINO DE LOS) (HOLANDA) | HK3: =_xlfn.XLOOKUP(B3,QUERY!$C:$C,QUERY!BL:BL) -> ISR | HL3: =_xlfn.XLOOKUP(B3,QUERY!$C:$C,QUERY!BM:BM) -> ZYA | HM3: =_xlfn.XLOOKUP(B3,QUERY!$C:$C,QUERY!BN:BN) -> 586895 | HN3: =_xlfn.XLOOKUP(B3,QUERY!$C:$C,QUERY!BO:BO) -> 4695.00 | HO3: =_xlfn.XLOOKUP(B3,QUERY!$C:$C,QUERY!BP:BP) -> 94655.00 | HP3: =_xlfn.XLOOKUP(B3,QUERY!$C:$C,QUERY!BQ:BQ) -> NULL | HQ3: =_xlfn.XLOOKUP(B3,QUERY!$C:$C,QUERY!BR:BR) -> 20944.87 | HR3: =_xlfn.XLOOKUP(B3,QUERY!$C:$C,QUERY!BS:BS) -> 0 | HS3: =_xlfn.XLOOKUP(B3,QUERY!$C:$C,QUERY!BT:BT) -> 0 | HT3: =_xlfn.XLOOKUP(B3,QUERY!$C:$C,QUERY!A:A) -> CIUDAD DE MÉXICO | HU3: =_xlfn.XLOOKUP(B3,QUERY!$C:$C,QUERY!B:B) -> AÉREO AICM
A4: INTERVET MEXICO SA DE CV | B4: 26-002651 | C4: 3942 | D4: 6002421 | F4: Importación | G4: A1 | H4: 0 | I4: 0 | J4: 0 | K4: 0 | L4: 0 | M4: 0 | N4: 0 | O4: 0 | P4: 17.2723 | Q4: 128 | R4: 470 | T4: 1 BULTOS | U4: 356771 | V4: 356771 | W4: 0 | X4: 0 | Y4: 0 | Z4: 0 | AA4: OTOMAX | AC4: 356771 | AD4: 122.14002 | AE4: 808 | AF4: 0 | AG4: 0 | AH4: 0 | AI4: 53 | AJ4: 462 | AK4: 0 | AL4: 0 | AM4: 330 | AN4: 845 | AO4: Cliente | AP4: INTERVET INTERNATIONAL BV | AQ4: 210372466 | AR4: CIP | AS4: MXP | AT4: 125-21466701 | AU4: 1073938896 | AV4: TEC | AW4: 30042099 | AX4: 0 | AY4: 2921 | AZ4: 2921 | BA4: PIEZA | BC4: DEU | BD4: ZYA | BE4: DESADUANAMIENTO LIBRE | BG4: 4.7002012e+16 | BH4: A1 | BI4: MERCANCIA EN BUEN ESTADO | BJ4: FACTURA COMERCIAL 210372466 DE | BK4: COVE2682GPM92 | BL4: 45913 | BM4: 0 | BN4: 0 | BO4: 0 | BP4: 0 | BQ4: 0 | BR4: 0 | BS4: 0 | BT4: 0 | BU4: 0 | BV4: 0 | BW4: 0 | BX4: 0 | BY4: 0 | BZ4: 0 | CA4: 0 | CB4: 5300 | CC4: 1272 | CD4: 30905.43 | CE4: PEDIENTE DE PAGO | CF4: 30905.43 | CG4: 0 | CH4: 0 | CI4: YAIR JOSE MIRANDA ARANO | CJ4: KAREN MARTINEZ | CK4: =_xlfn.XLOOKUP($B$2,'BASE DE EXCEL'!C:C,'BASE DE EXCEL'!D:D,"NO HAY REFERENCIA") -> 470 | CL4: =_xlfn.XLOOKUP($B$2,'BASE DE EXCEL'!$C:$C,'BASE DE EXCEL'!F:F,"NO HAY REFERENCIA") -> 3 | CM4: =_xlfn.XLOOKUP($B$2,'BASE DE EXCEL'!$C:$C,'BASE DE EXCEL'!G:G,"NO HAY REFERENCIA") -> 46080 | CN4: =_xlfn.XLOOKUP($B$2,'BASE DE EXCEL'!$C:$C,'BASE DE EXCEL'!H:H,"NO HAY REFERENCIA") -> 46086 | CO4: =_xlfn.XLOOKUP($B$2,'BASE DE EXCEL'!$C:$C,'BASE DE EXCEL'!I:I,"NO HAY REFERENCIA") -> 4 | CP4: =_xlfn.XLOOKUP($B$2,'BASE DE EXCEL'!$C:$C,'BASE DE EXCEL'!J:J,"NO HAY REFERENCIA") -> 4 a 5 días | CQ4: =_xlfn.XLOOKUP($B$2,'BASE DE EXCEL'!$C:$C,'BASE DE EXCEL'!K:K,"NO HAY REFERENCIA") -> 46087 | CR4: =_xlfn.XLOOKUP($B$2,'BASE DE EXCEL'!$C:$C,'BASE DE EXCEL'!L:L,"NO HAY REFERENCIA") -> 5 | CS4: =_xlfn.XLOOKUP($B$2,'BASE DE EXCEL'!$C:$C,'BASE DE EXCEL'!M:M,"NO HAY REFERENCIA") -> 6 | CT4: =_xlfn.XLOOKUP($B$2,'BASE DE EXCEL'!$C:$C,'BASE DE EXCEL'!N:N,"NO HAY REFERENCIA") -> 6 a 10 días | CU4: =_xlfn.XLOOKUP($B$2,'BASE DE EXCEL'!$C:$C,'BASE DE EXCEL'!O:O,"NO HAY REFERENCIA") -> On Time | CV4: =_xlfn.XLOOKUP(B4,'BASE DE EXCEL'!$C:$C,'BASE DE EXCEL'!P:P,"NO HAY REFERENCIA") -> 6 a 10 días | CW4: =_xlfn.XLOOKUP(B4,'BASE DE EXCEL'!$C:$C,'BASE DE EXCEL'!Q:Q,"NO HAY REFERENCIA") -> 46142 | CX4: =_xlfn.XLOOKUP(B4,'BASE DE EXCEL'!$C:$C,'BASE DE EXCEL'!R:R,"NO HAY REFERENCIA") -> 9 | CY4: =_xlfn.XLOOKUP(B4,'BASE DE EXCEL'!$C:$C,'BASE DE EXCEL'!S:S,"NO HAY REFERENCIA") -> 6 a 10 días | CZ4: =_xlfn.XLOOKUP(B4,'BASE DE EXCEL'!$C:$C,'BASE DE EXCEL'!T:T,"NO HAY REFERENCIA") -> On Time | DA4: =_xlfn.XLOOKUP(B4,'BASE DE EXCEL'!$C:$C,'BASE DE EXCEL'!U:U,"NO HAY REFERENCIA") -> 10 | DB4: =_xlfn.XLOOKUP(B4,'BASE DE EXCEL'!$C:$C,'BASE DE EXCEL'!V:V,"NO HAY REFERENCIA") -> 6 a 10 días | DC4: =_xlfn.XLOOKUP(B4,'BASE DE EXCEL'!$C:$C,'BASE DE EXCEL'!W:W,"NO HAY REFERENCIA") -> 14 | DD4: =_xlfn.XLOOKUP(B4,'BASE DE EXCEL'!$C:$C,'BASE DE EXCEL'!X:X,"NO HAY REFERENCIA") -> 11 a 15 días | DE4: =_xlfn.XLOOKUP(B4,'BASE DE EXCEL'!$C:$C,'BASE DE EXCEL'!Y:Y,"NO HAY REFERENCIA") -> 1 | DF4: =_xlfn.XLOOKUP(B4,'BASE DE EXCEL'!$C:$C,'BASE DE EXCEL'!Z:Z,"NO HAY REFERENCIA") -> 1 día o menos | DG4: =_xlfn.XLOOKUP(B4,'BASE DE EXCEL'!$C:$C,'BASE DE EXCEL'!AA:AA,"NO HAY REFERENCIA") -> 9 | DH4: =_xlfn.XLOOKUP(B4,'BASE DE EXCEL'!$C:$C,'BASE DE EXCEL'!AB:AB,"NO HAY REFERENCIA") -> 0 | DI4: =_xlfn.XLOOKUP(B4,'BASE DE EXCEL'!$C:$C,'BASE DE EXCEL'!AC:AC,"NO HAY REFERENCIA") -> 1 día o menos | DJ4: =_xlfn.XLOOKUP(B4,'BASE DE EXCEL'!$C:$C,'BASE DE EXCEL'!AD:AD,"NO HAY REFERENCIA") -> 46150 | DK4: =_xlfn.XLOOKUP(B4,'BASE DE EXCEL'!$C:$C,'BASE DE EXCEL'!AE:AE,"NO HAY REFERENCIA") -> 8 | DL4: =_xlfn.XLOOKUP(B4,'BASE DE EXCEL'!$C:$C,'BASE DE EXCEL'!AF:AF,"NO HAY REFERENCIA") -> 6 | DM4: =_xlfn.XLOOKUP(B4,'BASE DE EXCEL'!$C:$C,'BASE DE EXCEL'!AG:AG,"NO HAY REFERENCIA") -> 46150 | DN4: =_xlfn.XLOOKUP(B4,'BASE DE EXCEL'!$C:$C,'BASE DE EXCEL'!AH:AH,"NO HAY REFERENCIA") -> 46150 | DO4: =_xlfn.XLOOKUP(B4,'BASE DE EXCEL'!$C:$C,'BASE DE EXCEL'!AI:AI,"NO HAY REFERENCIA") -> 0 | DP4: =_xlfn.XLOOKUP(B4,'BASE DE EXCEL'!$C:$C,'BASE DE EXCEL'!AJ:AJ,"NO HAY REFERENCIA") -> 6 a 10 días | DQ4: =_xlfn.XLOOKUP(B4,'BASE DE EXCEL'!$C:$C,'BASE DE EXCEL'!AK:AK,"NO HAY REFERENCIA") -> 46150 | DR4: =_xlfn.XLOOKUP(B4,'BASE DE EXCEL'!$C:$C,'BASE DE EXCEL'!AL:AL,"NO HAY REFERENCIA") -> 6 | DS4: =_xlfn.XLOOKUP(B4,'BASE DE EXCEL'!$C:$C,'BASE DE EXCEL'!AM:AM,"NO HAY REFERENCIA") -> 6 a 10 días | DT4: =_xlfn.XLOOKUP(B4,'BASE DE EXCEL'!$C:$C,'BASE DE EXCEL'!AN:AN,"NO HAY REFERENCIA") -> On Time | DU4: =_xlfn.XLOOKUP(B4,'BASE DE EXCEL'!$C:$C,'BASE DE EXCEL'!AO:AO,"NO HAY REFERENCIA") -> 1 | DV4: =_xlfn.XLOOKUP(B4,'BASE DE EXCEL'!$C:$C,'BASE DE EXCEL'!AP:AP,"NO HAY REFERENCIA") -> Es anterior | DW4: =_xlfn.XLOOKUP(B4,'BASE DE EXCEL'!$C:$C,'BASE DE EXCEL'!AQ:AQ,"NO HAY REFERENCIA") -> A1 | DX4: =_xlfn.XLOOKUP(B4,'BASE DE EXCEL'!$C:$C,'BASE DE EXCEL'!AR:AR,"NO HAY REFERENCIA") -> KAREN MARTINEZ | DY4: =_xlfn.XLOOKUP(B4,'BASE DE EXCEL'!$C:$C,'BASE DE EXCEL'!AS:AS,"NO HAY REFERENCIA") -> 125-21466701 | DZ4: =_xlfn.XLOOKUP(B4,'BASE DE EXCEL'!$C:$C,'BASE DE EXCEL'!AT:AT,"NO HAY REFERENCIA") -> 1073938896 | EA4: =_xlfn.XLOOKUP(B4,'BASE DE EXCEL'!$C:$C,'BASE DE EXCEL'!AU:AU,"NO HAY REFERENCIA") -> 6002421 | EB4: =_xlfn.XLOOKUP(B4,'BASE DE EXCEL'!$C:$C,'BASE DE EXCEL'!AV:AV,"NO HAY REFERENCIA") -> Importación | EC4: =_xlfn.XLOOKUP(B4,'BASE DE EXCEL'!$C:$C,'BASE DE EXCEL'!AW:AW,"NO HAY REFERENCIA") -> OTOMAX | ED4: =_xlfn.XLOOKUP(B4,'BASE DE EXCEL'!$C:$C,'BASE DE EXCEL'!AX:AX,"NO HAY REFERENCIA") -> SIN CLASIFICACION | EE4: =_xlfn.XLOOKUP(B4,'BASE DE EXCEL'!$C:$C,'BASE DE EXCEL'!AY:AY,"NO HAY REFERENCIA") -> 0 | EF4: =_xlfn.XLOOKUP(B4,'BASE DE EXCEL'!$C:$C,'BASE DE EXCEL'!AZ:AZ,"NO HAY REFERENCIA") -> Cargas de Importación | EG4: =_xlfn.XLOOKUP(B4,'BASE DE EXCEL'!$C:$C,'BASE DE EXCEL'!BA:BA,"NO HAY REFERENCIA") -> INTERVET MEXICO SA DE CV | EH4: =_xlfn.XLOOKUP(B4,'BASE DE EXCEL'!$C:$C,'BASE DE EXCEL'!BB:BB,"NO HAY REFERENCIA") -> 0 | EI4: =_xlfn.XLOOKUP(B4,'BASE DE EXCEL'!$C:$C,'BASE DE EXCEL'!BC:BC,"NO HAY REFERENCIA") -> 0 | EJ4: =_xlfn.XLOOKUP(B4,'BASE DE EXCEL'!$C:$C,'BASE DE EXCEL'!BD:BD,"NO HAY REFERENCIA") -> 0 | EK4: =_xlfn.XLOOKUP(B4,'BASE DE EXCEL'!$C:$C,'BASE DE EXCEL'!BE:BE,"NO HAY REFERENCIA") -> 0 | EL4: =_xlfn.XLOOKUP(B4,'BASE DE EXCEL'!$C:$C,'BASE DE EXCEL'!BF:BF,"NO HAY REFERENCIA") -> MATERIA PRIMA | EM4: =_xlfn.XLOOKUP(B4,'BASE DE EXCEL'!$C:$C,'BASE DE EXCEL'!BG:BG,"NO HAY REFERENCIA") -> Verde | EN4: =_xlfn.XLOOKUP(B4,'BASE DE EXCEL'!$C:$C,'BASE DE EXCEL'!BH:BH,"NO HAY REFERENCIA") -> NULL | EO4: =_xlfn.XLOOKUP(B4,'BASE DE EXCEL'!$C:$C,'BASE DE EXCEL'!BI:BI,"NO HAY REFERENCIA") -> 0 | EP4: =_xlfn.XLOOKUP(B4,'BASE DE EXCEL'!$C:$C,'BASE DE EXCEL'!BJ:BJ,"NO HAY REFERENCIA") -> NISSAN 6 | EQ4: =_xlfn.XLOOKUP(B4,'BASE DE EXCEL'!$C:$C,'BASE DE EXCEL'!BK:BK,"NO HAY REFERENCIA") -> IME850329RH2 | ER4: =_xlfn.XLOOKUP(B4,'BASE DE EXCEL'!$C:$C,'BASE DE EXCEL'!BL:BL,"NO HAY REFERENCIA") -> 0 | ES4: =_xlfn.XLOOKUP(B4,'BASE DE EXCEL'!$C:$C,'BASE DE EXCEL'!BM:BM,"NO HAY REFERENCIA") -> 0 | ET4: =_xlfn.XLOOKUP(B4,'BASE DE EXCEL'!$C:$C,'BASE DE EXCEL'!BN:BN,"NO HAY REFERENCIA") -> LOTE: 6507301 | EU4: =_xlfn.XLOOKUP(B4,'BASE DE EXCEL'!$C:$C,'BASE DE EXCEL'!BO:BO,"NO HAY REFERENCIA") -> 90 | EV4: =_xlfn.XLOOKUP(B4,'BASE DE EXCEL'!$C:$C,'BASE DE EXCEL'!BP:BP,"NO HAY REFERENCIA") -> 356770.94 | EW4: =_xlfn.XLOOKUP(B4,'BASE DE EXCEL'!$C:$C,'BASE DE EXCEL'!BQ:BQ,"NO HAY REFERENCIA") -> KILO | EX4: =_xlfn.XLOOKUP(B4,'BASE DE EXCEL'!$C:$C,'BASE DE EXCEL'!BR:BR,"NO HAY REFERENCIA") -> 0 | EY4: =_xlfn.XLOOKUP(B4,'BASE DE EXCEL'!$C:$C,'BASE DE EXCEL'!BS:BS,"NO HAY REFERENCIA") -> ALEMANIA (REPUBLICA FEDERAL DE) | EZ4: =_xlfn.XLOOKUP(B4,'BASE DE EXCEL'!$C:$C,'BASE DE EXCEL'!BT:BT,"NO HAY REFERENCIA") -> PAISES BAJOS (REINO DE LOS) (HOLANDA) | FA4: =_xlfn.XLOOKUP(B4,'BASE DE EXCEL'!$C:$C,'BASE DE EXCEL'!BU:BU,"NO HAY REFERENCIA") -> DEU | FB4: =_xlfn.XLOOKUP(B4,'BASE DE EXCEL'!$C:$C,'BASE DE EXCEL'!BV:BV,"NO HAY REFERENCIA") -> ZYA | FC4: =_xlfn.XLOOKUP(B4,QUERY!$C:$C,QUERY!D:D) -> 470 | FD4: =_xlfn.XLOOKUP(B4,QUERY!$C:$C,QUERY!E:E) -> 46141 | FE4: =_xlfn.XLOOKUP(B4,QUERY!$C:$C,QUERY!F:F) -> 4 | FF4: =_xlfn.XLOOKUP(B4,QUERY!$C:$C,QUERY!G:G) -> 46132 | FG4: =_xlfn.XLOOKUP(B4,QUERY!$C:$C,QUERY!H:H) -> 46141 | FH4: =_xlfn.XLOOKUP(B4,QUERY!$C:$C,QUERY!I:I) -> 7 | FI4: =_xlfn.XLOOKUP(B4,QUERY!$C:$C,QUERY!J:J) -> 6 a 10 días | FJ4: =_xlfn.XLOOKUP(B4,QUERY!$C:$C,QUERY!K:K) -> 46142 | FK4: =_xlfn.XLOOKUP(B4,QUERY!$C:$C,QUERY!L:L) -> 8 | FL4: =_xlfn.XLOOKUP(B4,QUERY!$C:$C,QUERY!M:M) -> 6 a 10 días | FM4: =_xlfn.XLOOKUP(B4,QUERY!$C:$C,QUERY!N:N) -> 1 | FN4: =_xlfn.XLOOKUP(B4,QUERY!$C:$C,QUERY!O:O) -> 1 día o menos | FO4: =_xlfn.XLOOKUP(B4,QUERY!$C:$C,QUERY!P:P) -> 1 | FP4: =_xlfn.XLOOKUP(B4,QUERY!$C:$C,QUERY!Q:Q) -> 0 | FQ4: =_xlfn.XLOOKUP(B4,QUERY!$C:$C,QUERY!R:R) -> 1 día o menos | FR4: =_xlfn.XLOOKUP(B4,QUERY!$C:$C,QUERY!S:S) -> 46142 | FS4: =_xlfn.XLOOKUP(B4,QUERY!$C:$C,QUERY!T:T) -> 8 | FT4: =_xlfn.XLOOKUP(B4,QUERY!$C:$C,QUERY!U:U) -> 6 a 10 días | FU4: =_xlfn.XLOOKUP(B4,QUERY!$C:$C,QUERY!V:V) -> 14 | FV4: =_xlfn.XLOOKUP(B4,QUERY!$C:$C,QUERY!W:W) -> 11 a 15 días | FW4: =_xlfn.XLOOKUP(B4,QUERY!$C:$C,QUERY!X:X) -> 46150 | FX4: =_xlfn.XLOOKUP(B4,QUERY!$C:$C,QUERY!Y:Y) -> 6 | FY4: =_xlfn.XLOOKUP(B4,QUERY!$C:$C,QUERY!Z:Z) -> 6 | FZ4: =_xlfn.XLOOKUP(B4,QUERY!$C:$C,QUERY!AA:AA) -> 6 a 10 días | GA4: =_xlfn.XLOOKUP(B4,QUERY!$C:$C,QUERY!AB:AB) -> 46150 | GB4: =_xlfn.XLOOKUP(B4,QUERY!$C:$C,QUERY!AC:AC) -> 46150 | GC4: =_xlfn.XLOOKUP(B4,QUERY!$C:$C,QUERY!AD:AD) -> 0 | GD4: =_xlfn.XLOOKUP(B4,QUERY!$C:$C,QUERY!AE:AE) -> 46150 | GE4: =_xlfn.XLOOKUP(B4,QUERY!$C:$C,QUERY!AF:AF) -> 1 | GF4: =_xlfn.XLOOKUP(B4,QUERY!$C:$C,QUERY!AG:AG) -> Es anterior | GG4: =_xlfn.XLOOKUP(B4,QUERY!$C:$C,QUERY!AH:AH) -> A1 | GH4: =_xlfn.XLOOKUP(B4,QUERY!$C:$C,QUERY!AI:AI) -> KAREN MARTINEZ | GI4: =_xlfn.XLOOKUP(B4,QUERY!$C:$C,QUERY!AJ:AJ) -> 125-21466701 | GJ4: =_xlfn.XLOOKUP(B4,QUERY!$C:$C,QUERY!AK:AK) -> 1073938896 | GK4: =_xlfn.XLOOKUP(B4,QUERY!$C:$C,QUERY!AL:AL) -> 6002421 | GL4: =_xlfn.XLOOKUP(B4,QUERY!$C:$C,QUERY!AM:AM) -> Importación | GM4: =_xlfn.XLOOKUP(B4,QUERY!$C:$C,QUERY!AN:AN) -> OTOMAX | GN4: =_xlfn.XLOOKUP(B4,QUERY!$C:$C,QUERY!AO:AO) -> SIN CLASIFICACION | GO4: =_xlfn.XLOOKUP(B4,QUERY!$C:$C,QUERY!AP:AP) -> 0 | GP4: =_xlfn.XLOOKUP(B4,QUERY!$C:$C,QUERY!AQ:AQ) -> Cargas de Importación | GQ4: =_xlfn.XLOOKUP(B4,QUERY!$C:$C,QUERY!AR:AR) -> INTERVET MEXICO SA DE CV | GR4: =_xlfn.XLOOKUP(B4,QUERY!$C:$C,QUERY!AS:AS) -> 0 | GS4: =_xlfn.XLOOKUP(B4,QUERY!$C:$C,QUERY!AT:AT) -> 0 | GT4: =_xlfn.XLOOKUP(B4,QUERY!$C:$C,QUERY!AU:AU) -> 0 | GU4: =_xlfn.XLOOKUP(B4,QUERY!$C:$C,QUERY!AV:AV) -> 0 | GV4: =_xlfn.XLOOKUP(B4,QUERY!$C:$C,QUERY!AW:AW) -> MATERIA PRIMA | GW4: =_xlfn.XLOOKUP(B4,QUERY!$C:$C,QUERY!AX:AX) -> Verde | GX4: =_xlfn.XLOOKUP(B4,QUERY!$C:$C,QUERY!AY:AY) -> NULL | GY4: =_xlfn.XLOOKUP(B4,QUERY!$C:$C,QUERY!AZ:AZ) -> 0 | GZ4: =_xlfn.XLOOKUP(B4,QUERY!$C:$C,QUERY!BA:BA) -> NISSAN 6 | HA4: =_xlfn.XLOOKUP(B4,QUERY!$C:$C,QUERY!BB:BB) -> IME850329RH2 | HB4: =_xlfn.XLOOKUP(B4,QUERY!$C:$C,QUERY!BC:BC) -> 0 | HC4: =_xlfn.XLOOKUP(B4,QUERY!$C:$C,QUERY!BD:BD) -> 0 | HD4: =_xlfn.XLOOKUP(B4,QUERY!$C:$C,QUERY!BE:BE) -> LOTE: 6507301 | HE4: =_xlfn.XLOOKUP(B4,QUERY!$C:$C,QUERY!BF:BF) -> 90 | HF4: =_xlfn.XLOOKUP(B4,QUERY!$C:$C,QUERY!BG:BG) -> 356770.94 | HG4: =_xlfn.XLOOKUP(B4,QUERY!$C:$C,QUERY!BH:BH) -> KILO | HH4: =_xlfn.XLOOKUP(B4,QUERY!$C:$C,QUERY!BI:BI) -> 0 | HI4: =_xlfn.XLOOKUP(B4,QUERY!$C:$C,QUERY!BJ:BJ) -> ALEMANIA (REPUBLICA FEDERAL DE) | HJ4: =_xlfn.XLOOKUP(B4,QUERY!$C:$C,QUERY!BK:BK) -> PAISES BAJOS (REINO DE LOS) (HOLANDA) | HK4: =_xlfn.XLOOKUP(B4,QUERY!$C:$C,QUERY!BL:BL) -> DEU | HL4: =_xlfn.XLOOKUP(B4,QUERY!$C:$C,QUERY!BM:BM) -> ZYA | HM4: =_xlfn.XLOOKUP(B4,QUERY!$C:$C,QUERY!BN:BN) -> 356771 | HN4: =_xlfn.XLOOKUP(B4,QUERY!$C:$C,QUERY!BO:BO) -> 462.00 | HO4: =_xlfn.XLOOKUP(B4,QUERY!$C:$C,QUERY!BP:BP) -> NULL | HP4: =_xlfn.XLOOKUP(B4,QUERY!$C:$C,QUERY!BQ:BQ) -> NULL | HQ4: =_xlfn.XLOOKUP(B4,QUERY!$C:$C,QUERY!BR:BR) -> 30905.43 | HR4: =_xlfn.XLOOKUP(B4,QUERY!$C:$C,QUERY!BS:BS) -> 0 | HS4: =_xlfn.XLOOKUP(B4,QUERY!$C:$C,QUERY!BT:BT) -> 0 | HT4: =_xlfn.XLOOKUP(B4,QUERY!$C:$C,QUERY!A:A) -> CIUDAD DE MÉXICO | HU4: =_xlfn.XLOOKUP(B4,QUERY!$C:$C,QUERY!B:B) -> AÉREO AICM
A5: INTERVET MEXICO SA DE CV | B5: VER-25-1248 | C5: 3942 | D5: 6000072 | F5: Importación | G5: A1 | H5: 0 | I5: 0 | J5: 0 | K5: 0 | L5: 0 | M5: 0 | N5: 0 | O5: 0 | P5: 18.0012 | Q5: 5918 | R5: 430 | S5: CAAU4072651 | T5: 1 CONTENEDOR DE 40' RH | U5: 3997122 | V5: 3997122 | W5: 0 | X5: 0 | Y5: 0 | Z5: 0 | AA5: CEFA SAFE (MEDICAMENTO DOSIFICADO DE USO VETERINARIO) | AC5: 211379 | AD5: 2486.8118 | AE5: 808 | AF5: 0 | AG5: 0 | AH5: 0 | AI5: 53 | AJ5: 462 | AK5: 0 | AL5: 0 | AM5: 330 | AN5: 845 | AO5: Cliente | AP5: INTERVET INTERNATIONAL BV | AQ5: 210358508 | AR5: CIP | AS5: MXP | AT5: HLCUANR251131095 | AV5: TEC | AW5: 30042099 | AX5: 0 | AY5: 85 | AZ5: 85 | BA5: PIEZA | BC5: ZYA | BD5: ZYA | BE5: DESADUANAMIENTO LIBRE | BF5: NINGUNO | BG5: 43064022026004190, 4306402202 | BH5: A1, A1, A1, A1, A1 | BJ5: DE CONFORMIDAD CON EL ART. 36- | BK5: COVE267WG87A1 | BL5: 41647 | BM5: 0 | BN5: 0 | BO5: 0 | BP5: 0 | BQ5: 0 | BR5: 0 | BS5: 0 | BT5: 0 | BU5: 0 | BV5: 0 | BW5: 0 | BX5: 20545.92 | BY5: 0 | BZ5: 0 | CA5: 0 | CB5: 5779.19 | CC5: 1367.87 | CD5: 139939.61 | CE5: PAGADO | CF5: 139939.61 | CG5: 139939.61 | CH5: 0 | CI5: ZULEIMA PEREZ RUIZ | CJ5: ZULEIMA PEREZ RUIZ | CK5: =_xlfn.XLOOKUP($B$2,'BASE DE EXCEL'!C:C,'BASE DE EXCEL'!D:D,"NO HAY REFERENCIA") -> 470 | CL5: =_xlfn.XLOOKUP($B$2,'BASE DE EXCEL'!$C:$C,'BASE DE EXCEL'!F:F,"NO HAY REFERENCIA") -> 3 | CM5: =_xlfn.XLOOKUP($B$2,'BASE DE EXCEL'!$C:$C,'BASE DE EXCEL'!G:G,"NO HAY REFERENCIA") -> 46080 | CN5: =_xlfn.XLOOKUP($B$2,'BASE DE EXCEL'!$C:$C,'BASE DE EXCEL'!H:H,"NO HAY REFERENCIA") -> 46086 | CO5: =_xlfn.XLOOKUP($B$2,'BASE DE EXCEL'!$C:$C,'BASE DE EXCEL'!I:I,"NO HAY REFERENCIA") -> 4 | CP5: =_xlfn.XLOOKUP($B$2,'BASE DE EXCEL'!$C:$C,'BASE DE EXCEL'!J:J,"NO HAY REFERENCIA") -> 4 a 5 días | CQ5: =_xlfn.XLOOKUP($B$2,'BASE DE EXCEL'!$C:$C,'BASE DE EXCEL'!K:K,"NO HAY REFERENCIA") -> 46087 | CR5: =_xlfn.XLOOKUP($B$2,'BASE DE EXCEL'!$C:$C,'BASE DE EXCEL'!L:L,"NO HAY REFERENCIA") -> 5 | CS5: =_xlfn.XLOOKUP($B$2,'BASE DE EXCEL'!$C:$C,'BASE DE EXCEL'!M:M,"NO HAY REFERENCIA") -> 6 | CT5: =_xlfn.XLOOKUP($B$2,'BASE DE EXCEL'!$C:$C,'BASE DE EXCEL'!N:N,"NO HAY REFERENCIA") -> 6 a 10 días | CU5: =_xlfn.XLOOKUP($B$2,'BASE DE EXCEL'!$C:$C,'BASE DE EXCEL'!O:O,"NO HAY REFERENCIA") -> On Time | CV5: =_xlfn.XLOOKUP(B5,'BASE DE EXCEL'!$C:$C,'BASE DE EXCEL'!P:P,"NO HAY REFERENCIA") -> 4 a 5 días | CW5: =_xlfn.XLOOKUP(B5,'BASE DE EXCEL'!$C:$C,'BASE DE EXCEL'!Q:Q,"NO HAY REFERENCIA") -> 46031 | CX5: =_xlfn.XLOOKUP(B5,'BASE DE EXCEL'!$C:$C,'BASE DE EXCEL'!R:R,"NO HAY REFERENCIA") -> 5 | CY5: =_xlfn.XLOOKUP(B5,'BASE DE EXCEL'!$C:$C,'BASE DE EXCEL'!S:S,"NO HAY REFERENCIA") -> 4 a 5 días | CZ5: =_xlfn.XLOOKUP(B5,'BASE DE EXCEL'!$C:$C,'BASE DE EXCEL'!T:T,"NO HAY REFERENCIA") -> On Time | DA5: =_xlfn.XLOOKUP(B5,'BASE DE EXCEL'!$C:$C,'BASE DE EXCEL'!U:U,"NO HAY REFERENCIA") -> 6 | DB5: =_xlfn.XLOOKUP(B5,'BASE DE EXCEL'!$C:$C,'BASE DE EXCEL'!V:V,"NO HAY REFERENCIA") -> 4 a 5 días | DC5: =_xlfn.XLOOKUP(B5,'BASE DE EXCEL'!$C:$C,'BASE DE EXCEL'!W:W,"NO HAY REFERENCIA") -> 9 | DD5: =_xlfn.XLOOKUP(B5,'BASE DE EXCEL'!$C:$C,'BASE DE EXCEL'!X:X,"NO HAY REFERENCIA") -> 6 a 10 días | DE5: =_xlfn.XLOOKUP(B5,'BASE DE EXCEL'!$C:$C,'BASE DE EXCEL'!Y:Y,"NO HAY REFERENCIA") -> 1 | DF5: =_xlfn.XLOOKUP(B5,'BASE DE EXCEL'!$C:$C,'BASE DE EXCEL'!Z:Z,"NO HAY REFERENCIA") -> 1 día o menos | DG5: =_xlfn.XLOOKUP(B5,'BASE DE EXCEL'!$C:$C,'BASE DE EXCEL'!AA:AA,"NO HAY REFERENCIA") -> 4 | DH5: =_xlfn.XLOOKUP(B5,'BASE DE EXCEL'!$C:$C,'BASE DE EXCEL'!AB:AB,"NO HAY REFERENCIA") -> 1 | DI5: =_xlfn.XLOOKUP(B5,'BASE DE EXCEL'!$C:$C,'BASE DE EXCEL'!AC:AC,"NO HAY REFERENCIA") -> 1 día o menos | DJ5: =_xlfn.XLOOKUP(B5,'BASE DE EXCEL'!$C:$C,'BASE DE EXCEL'!AD:AD,"NO HAY REFERENCIA") -> 46038 | DK5: =_xlfn.XLOOKUP(B5,'BASE DE EXCEL'!$C:$C,'BASE DE EXCEL'!AE:AE,"NO HAY REFERENCIA") -> 7 | DL5: =_xlfn.XLOOKUP(B5,'BASE DE EXCEL'!$C:$C,'BASE DE EXCEL'!AF:AF,"NO HAY REFERENCIA") -> 5 | DM5: =_xlfn.XLOOKUP(B5,'BASE DE EXCEL'!$C:$C,'BASE DE EXCEL'!AG:AG,"NO HAY REFERENCIA") -> 46038 | DN5: =_xlfn.XLOOKUP(B5,'BASE DE EXCEL'!$C:$C,'BASE DE EXCEL'!AH:AH,"NO HAY REFERENCIA") -> 46038 | DO5: =_xlfn.XLOOKUP(B5,'BASE DE EXCEL'!$C:$C,'BASE DE EXCEL'!AI:AI,"NO HAY REFERENCIA") -> 0 | DP5: =_xlfn.XLOOKUP(B5,'BASE DE EXCEL'!$C:$C,'BASE DE EXCEL'!AJ:AJ,"NO HAY REFERENCIA") -> 6 a 10 días | DQ5: =_xlfn.XLOOKUP(B5,'BASE DE EXCEL'!$C:$C,'BASE DE EXCEL'!AK:AK,"NO HAY REFERENCIA") -> 46038 | DR5: =_xlfn.XLOOKUP(B5,'BASE DE EXCEL'!$C:$C,'BASE DE EXCEL'!AL:AL,"NO HAY REFERENCIA") -> 6 | DS5: =_xlfn.XLOOKUP(B5,'BASE DE EXCEL'!$C:$C,'BASE DE EXCEL'!AM:AM,"NO HAY REFERENCIA") -> 6 a 10 días | DT5: =_xlfn.XLOOKUP(B5,'BASE DE EXCEL'!$C:$C,'BASE DE EXCEL'!AN:AN,"NO HAY REFERENCIA") -> On Time | DU5: =_xlfn.XLOOKUP(B5,'BASE DE EXCEL'!$C:$C,'BASE DE EXCEL'!AO:AO,"NO HAY REFERENCIA") -> 1 | DV5: =_xlfn.XLOOKUP(B5,'BASE DE EXCEL'!$C:$C,'BASE DE EXCEL'!AP:AP,"NO HAY REFERENCIA") -> Es anterior | DW5: =_xlfn.XLOOKUP(B5,'BASE DE EXCEL'!$C:$C,'BASE DE EXCEL'!AQ:AQ,"NO HAY REFERENCIA") -> A1 | DX5: =_xlfn.XLOOKUP(B5,'BASE DE EXCEL'!$C:$C,'BASE DE EXCEL'!AR:AR,"NO HAY REFERENCIA") -> ZULEIMA PEREZ RUIZ | DY5: =_xlfn.XLOOKUP(B5,'BASE DE EXCEL'!$C:$C,'BASE DE EXCEL'!AS:AS,"NO HAY REFERENCIA") -> HLCUANR251131095 | DZ5: =_xlfn.XLOOKUP(B5,'BASE DE EXCEL'!$C:$C,'BASE DE EXCEL'!AT:AT,"NO HAY REFERENCIA") -> NULL | EA5: =_xlfn.XLOOKUP(B5,'BASE DE EXCEL'!$C:$C,'BASE DE EXCEL'!AU:AU,"NO HAY REFERENCIA") -> 6000072 | EB5: =_xlfn.XLOOKUP(B5,'BASE DE EXCEL'!$C:$C,'BASE DE EXCEL'!AV:AV,"NO HAY REFERENCIA") -> Importación | EC5: =_xlfn.XLOOKUP(B5,'BASE DE EXCEL'!$C:$C,'BASE DE EXCEL'!AW:AW,"NO HAY REFERENCIA") -> CEFA SAFE (MEDICAMENTO DOSIFICADO DE USO VETERINARIO) | ED5: =_xlfn.XLOOKUP(B5,'BASE DE EXCEL'!$C:$C,'BASE DE EXCEL'!AX:AX,"NO HAY REFERENCIA") -> SIN CLASIFICACION | EE5: =_xlfn.XLOOKUP(B5,'BASE DE EXCEL'!$C:$C,'BASE DE EXCEL'!AY:AY,"NO HAY REFERENCIA") -> 0 | EF5: =_xlfn.XLOOKUP(B5,'BASE DE EXCEL'!$C:$C,'BASE DE EXCEL'!AZ:AZ,"NO HAY REFERENCIA") -> Cargas de Importación | EG5: =_xlfn.XLOOKUP(B5,'BASE DE EXCEL'!$C:$C,'BASE DE EXCEL'!BA:BA,"NO HAY REFERENCIA") -> INTERVET MEXICO SA DE CV | EH5: =_xlfn.XLOOKUP(B5,'BASE DE EXCEL'!$C:$C,'BASE DE EXCEL'!BB:BB,"NO HAY REFERENCIA") -> 0 | EI5: =_xlfn.XLOOKUP(B5,'BASE DE EXCEL'!$C:$C,'BASE DE EXCEL'!BC:BC,"NO HAY REFERENCIA") -> NINGUNO | EJ5: =_xlfn.XLOOKUP(B5,'BASE DE EXCEL'!$C:$C,'BASE DE EXCEL'!BD:BD,"NO HAY REFERENCIA") -> 0 | EK5: =_xlfn.XLOOKUP(B5,'BASE DE EXCEL'!$C:$C,'BASE DE EXCEL'!BE:BE,"NO HAY REFERENCIA") -> NINGUNO | EL5: =_xlfn.XLOOKUP(B5,'BASE DE EXCEL'!$C:$C,'BASE DE EXCEL'!BF:BF,"NO HAY REFERENCIA") -> PRODUCTO TERMINADO | EM5: =_xlfn.XLOOKUP(B5,'BASE DE EXCEL'!$C:$C,'BASE DE EXCEL'!BG:BG,"NO HAY REFERENCIA") -> Verde | EN5: =_xlfn.XLOOKUP(B5,'BASE DE EXCEL'!$C:$C,'BASE DE EXCEL'!BH:BH,"NO HAY REFERENCIA") -> SUPER EXPRESS DE CARGA FEDERAL S.A. DE C.V. | EO5: =_xlfn.XLOOKUP(B5,'BASE DE EXCEL'!$C:$C,'BASE DE EXCEL'!BI:BI,"NO HAY REFERENCIA") -> 0 | EP5: =_xlfn.XLOOKUP(B5,'BASE DE EXCEL'!$C:$C,'BASE DE EXCEL'!BJ:BJ,"NO HAY REFERENCIA") -> IME-T006 | EQ5: =_xlfn.XLOOKUP(B5,'BASE DE EXCEL'!$C:$C,'BASE DE EXCEL'!BK:BK,"NO HAY REFERENCIA") -> IME850329RH2 | ER5: =_xlfn.XLOOKUP(B5,'BASE DE EXCEL'!$C:$C,'BASE DE EXCEL'!BL:BL,"NO HAY REFERENCIA") -> 0 | ES5: =_xlfn.XLOOKUP(B5,'BASE DE EXCEL'!$C:$C,'BASE DE EXCEL'!BM:BM,"NO HAY REFERENCIA") -> 00,99 | ET5: =_xlfn.XLOOKUP(B5,'BASE DE EXCEL'!$C:$C,'BASE DE EXCEL'!BN:BN,"NO HAY REFERENCIA") -> LOTE: A217A05,LOTE: A219A02,LOTE: A219A01,LOTE: A217A03,LOTE: H107A01,LOTES: J550A01, J607A01,LOTE: 5677101,LOTE: A217A04 | EU5: =_xlfn.XLOOKUP(B5,'BASE DE EXCEL'!$C:$C,'BASE DE EXCEL'!BO:BO,"NO HAY REFERENCIA") -> 90 | EV5: =_xlfn.XLOOKUP(B5,'BASE DE EXCEL'!$C:$C,'BASE DE EXCEL'!BP:BP,"NO HAY REFERENCIA") -> 952448.23, 2181141.30, 863532.00 | EW5: =_xlfn.XLOOKUP(B5,'BASE DE EXCEL'!$C:$C,'BASE DE EXCEL'!BQ:BQ,"NO HAY REFERENCIA") -> KILO,KILO,KILO,KILO,KILO,KILO,KILO,KILO | EX5: =_xlfn.XLOOKUP(B5,'BASE DE EXCEL'!$C:$C,'BASE DE EXCEL'!BR:BR,"NO HAY REFERENCIA") -> 0 | EY5: =_xlfn.XLOOKUP(B5,'BASE DE EXCEL'!$C:$C,'BASE DE EXCEL'!BS:BS,"NO HAY REFERENCIA") -> ALEMANIA (REPUBLICA FEDERAL DE),PAISES BAJOS (REINO DE LOS) (HOLANDA) | EZ5: =_xlfn.XLOOKUP(B5,'BASE DE EXCEL'!$C:$C,'BASE DE EXCEL'!BT:BT,"NO HAY REFERENCIA") -> PAISES BAJOS (REINO DE LOS) (HOLANDA) | FA5: =_xlfn.XLOOKUP(B5,'BASE DE EXCEL'!$C:$C,'BASE DE EXCEL'!BU:BU,"NO HAY REFERENCIA") -> DEU,ZYA | FB5: =_xlfn.XLOOKUP(B5,'BASE DE EXCEL'!$C:$C,'BASE DE EXCEL'!BV:BV,"NO HAY REFERENCIA") -> ZYA | FC5: =_xlfn.XLOOKUP(B5,QUERY!$C:$C,QUERY!D:D) -> 430 | FD5: =_xlfn.XLOOKUP(B5,QUERY!$C:$C,QUERY!E:E) -> 46029 | FE5: =_xlfn.XLOOKUP(B5,QUERY!$C:$C,QUERY!F:F) -> 1 | FF5: =_xlfn.XLOOKUP(B5,QUERY!$C:$C,QUERY!G:G) -> 46025 | FG5: =_xlfn.XLOOKUP(B5,QUERY!$C:$C,QUERY!H:H) -> 46029 | FH5: =_xlfn.XLOOKUP(B5,QUERY!$C:$C,QUERY!I:I) -> 2 | FI5: =_xlfn.XLOOKUP(B5,QUERY!$C:$C,QUERY!J:J) -> 2 a 3 días | FJ5: =_xlfn.XLOOKUP(B5,QUERY!$C:$C,QUERY!K:K) -> 46030 | FK5: =_xlfn.XLOOKUP(B5,QUERY!$C:$C,QUERY!L:L) -> 3 | FL5: =_xlfn.XLOOKUP(B5,QUERY!$C:$C,QUERY!M:M) -> 2 a 3 días | FM5: =_xlfn.XLOOKUP(B5,QUERY!$C:$C,QUERY!N:N) -> 1 | FN5: =_xlfn.XLOOKUP(B5,QUERY!$C:$C,QUERY!O:O) -> 1 día o menos | FO5: =_xlfn.XLOOKUP(B5,QUERY!$C:$C,QUERY!P:P) -> 1 | FP5: =_xlfn.XLOOKUP(B5,QUERY!$C:$C,QUERY!Q:Q) -> 1 | FQ5: =_xlfn.XLOOKUP(B5,QUERY!$C:$C,QUERY!R:R) -> 1 día o menos | FR5: =_xlfn.XLOOKUP(B5,QUERY!$C:$C,QUERY!S:S) -> 46031 | FS5: =_xlfn.XLOOKUP(B5,QUERY!$C:$C,QUERY!T:T) -> 4 | FT5: =_xlfn.XLOOKUP(B5,QUERY!$C:$C,QUERY!U:U) -> 4 a 5 días | FU5: =_xlfn.XLOOKUP(B5,QUERY!$C:$C,QUERY!V:V) -> 9 | FV5: =_xlfn.XLOOKUP(B5,QUERY!$C:$C,QUERY!W:W) -> 6 a 10 días | FW5: =_xlfn.XLOOKUP(B5,QUERY!$C:$C,QUERY!X:X) -> 46038 | FX5: =_xlfn.XLOOKUP(B5,QUERY!$C:$C,QUERY!Y:Y) -> 5 | FY5: =_xlfn.XLOOKUP(B5,QUERY!$C:$C,QUERY!Z:Z) -> 5 | FZ5: =_xlfn.XLOOKUP(B5,QUERY!$C:$C,QUERY!AA:AA) -> 6 a 10 días | GA5: =_xlfn.XLOOKUP(B5,QUERY!$C:$C,QUERY!AB:AB) -> 46038 | GB5: =_xlfn.XLOOKUP(B5,QUERY!$C:$C,QUERY!AC:AC) -> 46038 | GC5: =_xlfn.XLOOKUP(B5,QUERY!$C:$C,QUERY!AD:AD) -> 0 | GD5: =_xlfn.XLOOKUP(B5,QUERY!$C:$C,QUERY!AE:AE) -> 46038 | GE5: =_xlfn.XLOOKUP(B5,QUERY!$C:$C,QUERY!AF:AF) -> 1 | GF5: =_xlfn.XLOOKUP(B5,QUERY!$C:$C,QUERY!AG:AG) -> Es anterior | GG5: =_xlfn.XLOOKUP(B5,QUERY!$C:$C,QUERY!AH:AH) -> A1 | GH5: =_xlfn.XLOOKUP(B5,QUERY!$C:$C,QUERY!AI:AI) -> ZULEIMA PEREZ RUIZ | GI5: =_xlfn.XLOOKUP(B5,QUERY!$C:$C,QUERY!AJ:AJ) -> HLCUANR251131095 | GJ5: =_xlfn.XLOOKUP(B5,QUERY!$C:$C,QUERY!AK:AK) -> NULL | GK5: =_xlfn.XLOOKUP(B5,QUERY!$C:$C,QUERY!AL:AL) -> 6000072 | GL5: =_xlfn.XLOOKUP(B5,QUERY!$C:$C,QUERY!AM:AM) -> Importación | GM5: =_xlfn.XLOOKUP(B5,QUERY!$C:$C,QUERY!AN:AN) -> CEFA SAFE (MEDICAMENTO DOSIFICADO DE USO VETERINARIO) | GN5: =_xlfn.XLOOKUP(B5,QUERY!$C:$C,QUERY!AO:AO) -> SIN CLASIFICACION | GO5: =_xlfn.XLOOKUP(B5,QUERY!$C:$C,QUERY!AP:AP) -> 0 | GP5: =_xlfn.XLOOKUP(B5,QUERY!$C:$C,QUERY!AQ:AQ) -> Cargas de Importación | GQ5: =_xlfn.XLOOKUP(B5,QUERY!$C:$C,QUERY!AR:AR) -> INTERVET MEXICO SA DE CV | GR5: =_xlfn.XLOOKUP(B5,QUERY!$C:$C,QUERY!AS:AS) -> 0 | GS5: =_xlfn.XLOOKUP(B5,QUERY!$C:$C,QUERY!AT:AT) -> NINGUNO | GT5: =_xlfn.XLOOKUP(B5,QUERY!$C:$C,QUERY!AU:AU) -> 0 | GU5: =_xlfn.XLOOKUP(B5,QUERY!$C:$C,QUERY!AV:AV) -> NINGUNO | GV5: =_xlfn.XLOOKUP(B5,QUERY!$C:$C,QUERY!AW:AW) -> PRODUCTO TERMINADO | GW5: =_xlfn.XLOOKUP(B5,QUERY!$C:$C,QUERY!AX:AX) -> Verde | GX5: =_xlfn.XLOOKUP(B5,QUERY!$C:$C,QUERY!AY:AY) -> SUPER EXPRESS DE CARGA FEDERAL S.A. DE C.V. | GY5: =_xlfn.XLOOKUP(B5,QUERY!$C:$C,QUERY!AZ:AZ) -> 0 | GZ5: =_xlfn.XLOOKUP(B5,QUERY!$C:$C,QUERY!BA:BA) -> IME-T006 | HA5: =_xlfn.XLOOKUP(B5,QUERY!$C:$C,QUERY!BB:BB) -> IME850329RH2 | HB5: =_xlfn.XLOOKUP(B5,QUERY!$C:$C,QUERY!BC:BC) -> 0 | HC5: =_xlfn.XLOOKUP(B5,QUERY!$C:$C,QUERY!BD:BD) -> 0.99 | HD5: =_xlfn.XLOOKUP(B5,QUERY!$C:$C,QUERY!BE:BE) -> LOTE: A217A05,LOTE: A219A02,LOTE: A219A01,LOTE: A217A04,LOTE: A217A03,LOTE: H107A01,LOTES: J550A01, J607A01,LOTE: 5677101 | HE5: =_xlfn.XLOOKUP(B5,QUERY!$C:$C,QUERY!BF:BF) -> 90 | HF5: =_xlfn.XLOOKUP(B5,QUERY!$C:$C,QUERY!BG:BG) -> 952448.23, 2181141.30, 863532.00 | HG5: =_xlfn.XLOOKUP(B5,QUERY!$C:$C,QUERY!BH:BH) -> KILO,KILO,KILO,KILO,KILO,KILO,KILO,KILO | HH5: =_xlfn.XLOOKUP(B5,QUERY!$C:$C,QUERY!BI:BI) -> 0 | HI5: =_xlfn.XLOOKUP(B5,QUERY!$C:$C,QUERY!BJ:BJ) -> ALEMANIA (REPUBLICA FEDERAL DE),PAISES BAJOS (REINO DE LOS) (HOLANDA) | HJ5: =_xlfn.XLOOKUP(B5,QUERY!$C:$C,QUERY!BK:BK) -> PAISES BAJOS (REINO DE LOS) (HOLANDA) | HK5: =_xlfn.XLOOKUP(B5,QUERY!$C:$C,QUERY!BL:BL) -> DEU,ZYA | HL5: =_xlfn.XLOOKUP(B5,QUERY!$C:$C,QUERY!BM:BM) -> ZYA | HM5: =_xlfn.XLOOKUP(B5,QUERY!$C:$C,QUERY!BN:BN) -> 3997122 | HN5: =_xlfn.XLOOKUP(B5,QUERY!$C:$C,QUERY!BO:BO) -> 462.00 | HO5: =_xlfn.XLOOKUP(B5,QUERY!$C:$C,QUERY!BP:BP) -> NULL | HP5: =_xlfn.XLOOKUP(B5,QUERY!$C:$C,QUERY!BQ:BQ) -> NULL | HQ5: =_xlfn.XLOOKUP(B5,QUERY!$C:$C,QUERY!BR:BR) -> 139939.61 | HR5: =_xlfn.XLOOKUP(B5,QUERY!$C:$C,QUERY!BS:BS) -> 0 | HS5: =_xlfn.XLOOKUP(B5,QUERY!$C:$C,QUERY!BT:BT) -> 0 | HT5: =_xlfn.XLOOKUP(B5,QUERY!$C:$C,QUERY!A:A) -> VERACRUZ | HU5: =_xlfn.XLOOKUP(B5,QUERY!$C:$C,QUERY!B:B) -> MARÍTIMO VERACRUZ
A6: INTERVET MEXICO SA DE CV | B6: VER-25-1248 | C6: 3942 | D6: 6000072 | F6: Importación | G6: A1 | H6: 0 | I6: 0 | J6: 0 | K6: 0 | L6: 0 | M6: 0 | N6: 0 | O6: 0 | P6: 0 | Q6: 0 | R6: 430 | S6: CAAU4072651 | T6: 0 | U6: 0 | V6: 0 | W6: 0 | X6: 0 | Y6: 0 | Z6: 0 | AA6: CEFA SAFE (MEDICAMENTO DOSIFICADO DE USO VETERINARIO) | AC6: 370535 | AD6: 2486.8121 | AE6: 0 | AF6: 0 | AG6: 0 | AH6: 0 | AI6: 0 | AJ6: 0 | AK6: 0 | AL6: 0 | AM6: 0 | AN6: 0 | AP6: INTERVET INTERNATIONAL BV | AQ6: 210358508 | AR6: CIP | AS6: MXP | AT6: 0 | AU6: 0 | AV6: 0 | AW6: 30042099 | AX6: 0 | AY6: 149 | AZ6: 149 | BA6: CAJA | BC6: ZYA | BD6: ZYA | BK6: COVE267WG87A1 | BL6: 0 | BM6: 0 | BN6: 0 | BO6: 0 | BP6: 0 | BQ6: 0 | BR6: 0 | BS6: 0 | BT6: 0 | BU6: 0 | BV6: 0 | BW6: 0 | BX6: 0 | BY6: 0 | BZ6: 0 | CA6: 0 | CB6: 0 | CC6: 0 | CD6: 0 | CE6: PAGADO | CF6: 0 | CG6: 0 | CH6: 0 | CI6: ZULEIMA PEREZ RUIZ | CJ6: ZULEIMA PEREZ RUIZ | CK6: =_xlfn.XLOOKUP($B$2,'BASE DE EXCEL'!C:C,'BASE DE EXCEL'!D:D,"NO HAY REFERENCIA") -> 470 | CL6: =_xlfn.XLOOKUP($B$2,'BASE DE EXCEL'!$C:$C,'BASE DE EXCEL'!F:F,"NO HAY REFERENCIA") -> 3 | CM6: =_xlfn.XLOOKUP($B$2,'BASE DE EXCEL'!$C:$C,'BASE DE EXCEL'!G:G,"NO HAY REFERENCIA") -> 46080 | CN6: =_xlfn.XLOOKUP($B$2,'BASE DE EXCEL'!$C:$C,'BASE DE EXCEL'!H:H,"NO HAY REFERENCIA") -> 46086 | CO6: =_xlfn.XLOOKUP($B$2,'BASE DE EXCEL'!$C:$C,'BASE DE EXCEL'!I:I,"NO HAY REFERENCIA") -> 4 | CP6: =_xlfn.XLOOKUP($B$2,'BASE DE EXCEL'!$C:$C,'BASE DE EXCEL'!J:J,"NO HAY REFERENCIA") -> 4 a 5 días | CQ6: =_xlfn.XLOOKUP($B$2,'BASE DE EXCEL'!$C:$C,'BASE DE EXCEL'!K:K,"NO HAY REFERENCIA") -> 46087 | CR6: =_xlfn.XLOOKUP($B$2,'BASE DE EXCEL'!$C:$C,'BASE DE EXCEL'!L:L,"NO HAY REFERENCIA") -> 5 | CS6: =_xlfn.XLOOKUP($B$2,'BASE DE EXCEL'!$C:$C,'BASE DE EXCEL'!M:M,"NO HAY REFERENCIA") -> 6 | CT6: =_xlfn.XLOOKUP($B$2,'BASE DE EXCEL'!$C:$C,'BASE DE EXCEL'!N:N,"NO HAY REFERENCIA") -> 6 a 10 días | CU6: =_xlfn.XLOOKUP($B$2,'BASE DE EXCEL'!$C:$C,'BASE DE EXCEL'!O:O,"NO HAY REFERENCIA") -> On Time | CV6: =_xlfn.XLOOKUP(B6,'BASE DE EXCEL'!$C:$C,'BASE DE EXCEL'!P:P,"NO HAY REFERENCIA") -> 4 a 5 días | CW6: =_xlfn.XLOOKUP(B6,'BASE DE EXCEL'!$C:$C,'BASE DE EXCEL'!Q:Q,"NO HAY REFERENCIA") -> 46031 | CX6: =_xlfn.XLOOKUP(B6,'BASE DE EXCEL'!$C:$C,'BASE DE EXCEL'!R:R,"NO HAY REFERENCIA") -> 5 | CY6: =_xlfn.XLOOKUP(B6,'BASE DE EXCEL'!$C:$C,'BASE DE EXCEL'!S:S,"NO HAY REFERENCIA") -> 4 a 5 días | CZ6: =_xlfn.XLOOKUP(B6,'BASE DE EXCEL'!$C:$C,'BASE DE EXCEL'!T:T,"NO HAY REFERENCIA") -> On Time | DA6: =_xlfn.XLOOKUP(B6,'BASE DE EXCEL'!$C:$C,'BASE DE EXCEL'!U:U,"NO HAY REFERENCIA") -> 6 | DB6: =_xlfn.XLOOKUP(B6,'BASE DE EXCEL'!$C:$C,'BASE DE EXCEL'!V:V,"NO HAY REFERENCIA") -> 4 a 5 días | DC6: =_xlfn.XLOOKUP(B6,'BASE DE EXCEL'!$C:$C,'BASE DE EXCEL'!W:W,"NO HAY REFERENCIA") -> 9 | DD6: =_xlfn.XLOOKUP(B6,'BASE DE EXCEL'!$C:$C,'BASE DE EXCEL'!X:X,"NO HAY REFERENCIA") -> 6 a 10 días | DE6: =_xlfn.XLOOKUP(B6,'BASE DE EXCEL'!$C:$C,'BASE DE EXCEL'!Y:Y,"NO HAY REFERENCIA") -> 1 | DF6: =_xlfn.XLOOKUP(B6,'BASE DE EXCEL'!$C:$C,'BASE DE EXCEL'!Z:Z,"NO HAY REFERENCIA") -> 1 día o menos | DG6: =_xlfn.XLOOKUP(B6,'BASE DE EXCEL'!$C:$C,'BASE DE EXCEL'!AA:AA,"NO HAY REFERENCIA") -> 4 | DH6: =_xlfn.XLOOKUP(B6,'BASE DE EXCEL'!$C:$C,'BASE DE EXCEL'!AB:AB,"NO HAY REFERENCIA") -> 1 | DI6: =_xlfn.XLOOKUP(B6,'BASE DE EXCEL'!$C:$C,'BASE DE EXCEL'!AC:AC,"NO HAY REFERENCIA") -> 1 día o menos | DJ6: =_xlfn.XLOOKUP(B6,'BASE DE EXCEL'!$C:$C,'BASE DE EXCEL'!AD:AD,"NO HAY REFERENCIA") -> 46038 | DK6: =_xlfn.XLOOKUP(B6,'BASE DE EXCEL'!$C:$C,'BASE DE EXCEL'!AE:AE,"NO HAY REFERENCIA") -> 7 | DL6: =_xlfn.XLOOKUP(B6,'BASE DE EXCEL'!$C:$C,'BASE DE EXCEL'!AF:AF,"NO HAY REFERENCIA") -> 5 | DM6: =_xlfn.XLOOKUP(B6,'BASE DE EXCEL'!$C:$C,'BASE DE EXCEL'!AG:AG,"NO HAY REFERENCIA") -> 46038 | DN6: =_xlfn.XLOOKUP(B6,'BASE DE EXCEL'!$C:$C,'BASE DE EXCEL'!AH:AH,"NO HAY REFERENCIA") -> 46038 | DO6: =_xlfn.XLOOKUP(B6,'BASE DE EXCEL'!$C:$C,'BASE DE EXCEL'!AI:AI,"NO HAY REFERENCIA") -> 0 | DP6: =_xlfn.XLOOKUP(B6,'BASE DE EXCEL'!$C:$C,'BASE DE EXCEL'!AJ:AJ,"NO HAY REFERENCIA") -> 6 a 10 días | DQ6: =_xlfn.XLOOKUP(B6,'BASE DE EXCEL'!$C:$C,'BASE DE EXCEL'!AK:AK,"NO HAY REFERENCIA") -> 46038 | DR6: =_xlfn.XLOOKUP(B6,'BASE DE EXCEL'!$C:$C,'BASE DE EXCEL'!AL:AL,"NO HAY REFERENCIA") -> 6 | DS6: =_xlfn.XLOOKUP(B6,'BASE DE EXCEL'!$C:$C,'BASE DE EXCEL'!AM:AM,"NO HAY REFERENCIA") -> 6 a 10 días | DT6: =_xlfn.XLOOKUP(B6,'BASE DE EXCEL'!$C:$C,'BASE DE EXCEL'!AN:AN,"NO HAY REFERENCIA") -> On Time | DU6: =_xlfn.XLOOKUP(B6,'BASE DE EXCEL'!$C:$C,'BASE DE EXCEL'!AO:AO,"NO HAY REFERENCIA") -> 1 | DV6: =_xlfn.XLOOKUP(B6,'BASE DE EXCEL'!$C:$C,'BASE DE EXCEL'!AP:AP,"NO HAY REFERENCIA") -> Es anterior | DW6: =_xlfn.XLOOKUP(B6,'BASE DE EXCEL'!$C:$C,'BASE DE EXCEL'!AQ:AQ,"NO HAY REFERENCIA") -> A1 | DX6: =_xlfn.XLOOKUP(B6,'BASE DE EXCEL'!$C:$C,'BASE DE EXCEL'!AR:AR,"NO HAY REFERENCIA") -> ZULEIMA PEREZ RUIZ | DY6: =_xlfn.XLOOKUP(B6,'BASE DE EXCEL'!$C:$C,'BASE DE EXCEL'!AS:AS,"NO HAY REFERENCIA") -> HLCUANR251131095 | DZ6: =_xlfn.XLOOKUP(B6,'BASE DE EXCEL'!$C:$C,'BASE DE EXCEL'!AT:AT,"NO HAY REFERENCIA") -> NULL | EA6: =_xlfn.XLOOKUP(B6,'BASE DE EXCEL'!$C:$C,'BASE DE EXCEL'!AU:AU,"NO HAY REFERENCIA") -> 6000072 | EB6: =_xlfn.XLOOKUP(B6,'BASE DE EXCEL'!$C:$C,'BASE DE EXCEL'!AV:AV,"NO HAY REFERENCIA") -> Importación | EC6: =_xlfn.XLOOKUP(B6,'BASE DE EXCEL'!$C:$C,'BASE DE EXCEL'!AW:AW,"NO HAY REFERENCIA") -> CEFA SAFE (MEDICAMENTO DOSIFICADO DE USO VETERINARIO) | ED6: =_xlfn.XLOOKUP(B6,'BASE DE EXCEL'!$C:$C,'BASE DE EXCEL'!AX:AX,"NO HAY REFERENCIA") -> SIN CLASIFICACION | EE6: =_xlfn.XLOOKUP(B6,'BASE DE EXCEL'!$C:$C,'BASE DE EXCEL'!AY:AY,"NO HAY REFERENCIA") -> 0 | EF6: =_xlfn.XLOOKUP(B6,'BASE DE EXCEL'!$C:$C,'BASE DE EXCEL'!AZ:AZ,"NO HAY REFERENCIA") -> Cargas de Importación | EG6: =_xlfn.XLOOKUP(B6,'BASE DE EXCEL'!$C:$C,'BASE DE EXCEL'!BA:BA,"NO HAY REFERENCIA") -> INTERVET MEXICO SA DE CV | EH6: =_xlfn.XLOOKUP(B6,'BASE DE EXCEL'!$C:$C,'BASE DE EXCEL'!BB:BB,"NO HAY REFERENCIA") -> 0 | EI6: =_xlfn.XLOOKUP(B6,'BASE DE EXCEL'!$C:$C,'BASE DE EXCEL'!BC:BC,"NO HAY REFERENCIA") -> NINGUNO | EJ6: =_xlfn.XLOOKUP(B6,'BASE DE EXCEL'!$C:$C,'BASE DE EXCEL'!BD:BD,"NO HAY REFERENCIA") -> 0 | EK6: =_xlfn.XLOOKUP(B6,'BASE DE EXCEL'!$C:$C,'BASE DE EXCEL'!BE:BE,"NO HAY REFERENCIA") -> NINGUNO | EL6: =_xlfn.XLOOKUP(B6,'BASE DE EXCEL'!$C:$C,'BASE DE EXCEL'!BF:BF,"NO HAY REFERENCIA") -> PRODUCTO TERMINADO | EM6: =_xlfn.XLOOKUP(B6,'BASE DE EXCEL'!$C:$C,'BASE DE EXCEL'!BG:BG,"NO HAY REFERENCIA") -> Verde | EN6: =_xlfn.XLOOKUP(B6,'BASE DE EXCEL'!$C:$C,'BASE DE EXCEL'!BH:BH,"NO HAY REFERENCIA") -> SUPER EXPRESS DE CARGA FEDERAL S.A. DE C.V. | EO6: =_xlfn.XLOOKUP(B6,'BASE DE EXCEL'!$C:$C,'BASE DE EXCEL'!BI:BI,"NO HAY REFERENCIA") -> 0 | EP6: =_xlfn.XLOOKUP(B6,'BASE DE EXCEL'!$C:$C,'BASE DE EXCEL'!BJ:BJ,"NO HAY REFERENCIA") -> IME-T006 | EQ6: =_xlfn.XLOOKUP(B6,'BASE DE EXCEL'!$C:$C,'BASE DE EXCEL'!BK:BK,"NO HAY REFERENCIA") -> IME850329RH2 | ER6: =_xlfn.XLOOKUP(B6,'BASE DE EXCEL'!$C:$C,'BASE DE EXCEL'!BL:BL,"NO HAY REFERENCIA") -> 0 | ES6: =_xlfn.XLOOKUP(B6,'BASE DE EXCEL'!$C:$C,'BASE DE EXCEL'!BM:BM,"NO HAY REFERENCIA") -> 00,99 | ET6: =_xlfn.XLOOKUP(B6,'BASE DE EXCEL'!$C:$C,'BASE DE EXCEL'!BN:BN,"NO HAY REFERENCIA") -> LOTE: A217A05,LOTE: A219A02,LOTE: A219A01,LOTE: A217A03,LOTE: H107A01,LOTES: J550A01, J607A01,LOTE: 5677101,LOTE: A217A04 | EU6: =_xlfn.XLOOKUP(B6,'BASE DE EXCEL'!$C:$C,'BASE DE EXCEL'!BO:BO,"NO HAY REFERENCIA") -> 90 | EV6: =_xlfn.XLOOKUP(B6,'BASE DE EXCEL'!$C:$C,'BASE DE EXCEL'!BP:BP,"NO HAY REFERENCIA") -> 952448.23, 2181141.30, 863532.00 | EW6: =_xlfn.XLOOKUP(B6,'BASE DE EXCEL'!$C:$C,'BASE DE EXCEL'!BQ:BQ,"NO HAY REFERENCIA") -> KILO,KILO,KILO,KILO,KILO,KILO,KILO,KILO | EX6: =_xlfn.XLOOKUP(B6,'BASE DE EXCEL'!$C:$C,'BASE DE EXCEL'!BR:BR,"NO HAY REFERENCIA") -> 0 | EY6: =_xlfn.XLOOKUP(B6,'BASE DE EXCEL'!$C:$C,'BASE DE EXCEL'!BS:BS,"NO HAY REFERENCIA") -> ALEMANIA (REPUBLICA FEDERAL DE),PAISES BAJOS (REINO DE LOS) (HOLANDA) | EZ6: =_xlfn.XLOOKUP(B6,'BASE DE EXCEL'!$C:$C,'BASE DE EXCEL'!BT:BT,"NO HAY REFERENCIA") -> PAISES BAJOS (REINO DE LOS) (HOLANDA) | FA6: =_xlfn.XLOOKUP(B6,'BASE DE EXCEL'!$C:$C,'BASE DE EXCEL'!BU:BU,"NO HAY REFERENCIA") -> DEU,ZYA | FB6: =_xlfn.XLOOKUP(B6,'BASE DE EXCEL'!$C:$C,'BASE DE EXCEL'!BV:BV,"NO HAY REFERENCIA") -> ZYA | FC6: =_xlfn.XLOOKUP(B6,QUERY!$C:$C,QUERY!D:D) -> 430 | FD6: =_xlfn.XLOOKUP(B6,QUERY!$C:$C,QUERY!E:E) -> 46029 | FE6: =_xlfn.XLOOKUP(B6,QUERY!$C:$C,QUERY!F:F) -> 1 | FF6: =_xlfn.XLOOKUP(B6,QUERY!$C:$C,QUERY!G:G) -> 46025 | FG6: =_xlfn.XLOOKUP(B6,QUERY!$C:$C,QUERY!H:H) -> 46029 | FH6: =_xlfn.XLOOKUP(B6,QUERY!$C:$C,QUERY!I:I) -> 2 | FI6: =_xlfn.XLOOKUP(B6,QUERY!$C:$C,QUERY!J:J) -> 2 a 3 días | FJ6: =_xlfn.XLOOKUP(B6,QUERY!$C:$C,QUERY!K:K) -> 46030 | FK6: =_xlfn.XLOOKUP(B6,QUERY!$C:$C,QUERY!L:L) -> 3 | FL6: =_xlfn.XLOOKUP(B6,QUERY!$C:$C,QUERY!M:M) -> 2 a 3 días | FM6: =_xlfn.XLOOKUP(B6,QUERY!$C:$C,QUERY!N:N) -> 1 | FN6: =_xlfn.XLOOKUP(B6,QUERY!$C:$C,QUERY!O:O) -> 1 día o menos | FO6: =_xlfn.XLOOKUP(B6,QUERY!$C:$C,QUERY!P:P) -> 1 | FP6: =_xlfn.XLOOKUP(B6,QUERY!$C:$C,QUERY!Q:Q) -> 1 | FQ6: =_xlfn.XLOOKUP(B6,QUERY!$C:$C,QUERY!R:R) -> 1 día o menos | FR6: =_xlfn.XLOOKUP(B6,QUERY!$C:$C,QUERY!S:S) -> 46031 | FS6: =_xlfn.XLOOKUP(B6,QUERY!$C:$C,QUERY!T:T) -> 4 | FT6: =_xlfn.XLOOKUP(B6,QUERY!$C:$C,QUERY!U:U) -> 4 a 5 días | FU6: =_xlfn.XLOOKUP(B6,QUERY!$C:$C,QUERY!V:V) -> 9 | FV6: =_xlfn.XLOOKUP(B6,QUERY!$C:$C,QUERY!W:W) -> 6 a 10 días | FW6: =_xlfn.XLOOKUP(B6,QUERY!$C:$C,QUERY!X:X) -> 46038 | FX6: =_xlfn.XLOOKUP(B6,QUERY!$C:$C,QUERY!Y:Y) -> 5 | FY6: =_xlfn.XLOOKUP(B6,QUERY!$C:$C,QUERY!Z:Z) -> 5 | FZ6: =_xlfn.XLOOKUP(B6,QUERY!$C:$C,QUERY!AA:AA) -> 6 a 10 días | GA6: =_xlfn.XLOOKUP(B6,QUERY!$C:$C,QUERY!AB:AB) -> 46038 | GB6: =_xlfn.XLOOKUP(B6,QUERY!$C:$C,QUERY!AC:AC) -> 46038 | GC6: =_xlfn.XLOOKUP(B6,QUERY!$C:$C,QUERY!AD:AD) -> 0 | GD6: =_xlfn.XLOOKUP(B6,QUERY!$C:$C,QUERY!AE:AE) -> 46038 | GE6: =_xlfn.XLOOKUP(B6,QUERY!$C:$C,QUERY!AF:AF) -> 1 | GF6: =_xlfn.XLOOKUP(B6,QUERY!$C:$C,QUERY!AG:AG) -> Es anterior | GG6: =_xlfn.XLOOKUP(B6,QUERY!$C:$C,QUERY!AH:AH) -> A1 | GH6: =_xlfn.XLOOKUP(B6,QUERY!$C:$C,QUERY!AI:AI) -> ZULEIMA PEREZ RUIZ | GI6: =_xlfn.XLOOKUP(B6,QUERY!$C:$C,QUERY!AJ:AJ) -> HLCUANR251131095 | GJ6: =_xlfn.XLOOKUP(B6,QUERY!$C:$C,QUERY!AK:AK) -> NULL | GK6: =_xlfn.XLOOKUP(B6,QUERY!$C:$C,QUERY!AL:AL) -> 6000072 | GL6: =_xlfn.XLOOKUP(B6,QUERY!$C:$C,QUERY!AM:AM) -> Importación | GM6: =_xlfn.XLOOKUP(B6,QUERY!$C:$C,QUERY!AN:AN) -> CEFA SAFE (MEDICAMENTO DOSIFICADO DE USO VETERINARIO) | GN6: =_xlfn.XLOOKUP(B6,QUERY!$C:$C,QUERY!AO:AO) -> SIN CLASIFICACION | GO6: =_xlfn.XLOOKUP(B6,QUERY!$C:$C,QUERY!AP:AP) -> 0 | GP6: =_xlfn.XLOOKUP(B6,QUERY!$C:$C,QUERY!AQ:AQ) -> Cargas de Importación | GQ6: =_xlfn.XLOOKUP(B6,QUERY!$C:$C,QUERY!AR:AR) -> INTERVET MEXICO SA DE CV | GR6: =_xlfn.XLOOKUP(B6,QUERY!$C:$C,QUERY!AS:AS) -> 0 | GS6: =_xlfn.XLOOKUP(B6,QUERY!$C:$C,QUERY!AT:AT) -> NINGUNO | GT6: =_xlfn.XLOOKUP(B6,QUERY!$C:$C,QUERY!AU:AU) -> 0 | GU6: =_xlfn.XLOOKUP(B6,QUERY!$C:$C,QUERY!AV:AV) -> NINGUNO | GV6: =_xlfn.XLOOKUP(B6,QUERY!$C:$C,QUERY!AW:AW) -> PRODUCTO TERMINADO | GW6: =_xlfn.XLOOKUP(B6,QUERY!$C:$C,QUERY!AX:AX) -> Verde | GX6: =_xlfn.XLOOKUP(B6,QUERY!$C:$C,QUERY!AY:AY) -> SUPER EXPRESS DE CARGA FEDERAL S.A. DE C.V. | GY6: =_xlfn.XLOOKUP(B6,QUERY!$C:$C,QUERY!AZ:AZ) -> 0 | GZ6: =_xlfn.XLOOKUP(B6,QUERY!$C:$C,QUERY!BA:BA) -> IME-T006 | HA6: =_xlfn.XLOOKUP(B6,QUERY!$C:$C,QUERY!BB:BB) -> IME850329RH2 | HB6: =_xlfn.XLOOKUP(B6,QUERY!$C:$C,QUERY!BC:BC) -> 0 | HC6: =_xlfn.XLOOKUP(B6,QUERY!$C:$C,QUERY!BD:BD) -> 0.99 | HD6: =_xlfn.XLOOKUP(B6,QUERY!$C:$C,QUERY!BE:BE) -> LOTE: A217A05,LOTE: A219A02,LOTE: A219A01,LOTE: A217A04,LOTE: A217A03,LOTE: H107A01,LOTES: J550A01, J607A01,LOTE: 5677101 | HE6: =_xlfn.XLOOKUP(B6,QUERY!$C:$C,QUERY!BF:BF) -> 90 | HF6: =_xlfn.XLOOKUP(B6,QUERY!$C:$C,QUERY!BG:BG) -> 952448.23, 2181141.30, 863532.00 | HG6: =_xlfn.XLOOKUP(B6,QUERY!$C:$C,QUERY!BH:BH) -> KILO,KILO,KILO,KILO,KILO,KILO,KILO,KILO | HH6: =_xlfn.XLOOKUP(B6,QUERY!$C:$C,QUERY!BI:BI) -> 0 | HI6: =_xlfn.XLOOKUP(B6,QUERY!$C:$C,QUERY!BJ:BJ) -> ALEMANIA (REPUBLICA FEDERAL DE),PAISES BAJOS (REINO DE LOS) (HOLANDA) | HJ6: =_xlfn.XLOOKUP(B6,QUERY!$C:$C,QUERY!BK:BK) -> PAISES BAJOS (REINO DE LOS) (HOLANDA) | HK6: =_xlfn.XLOOKUP(B6,QUERY!$C:$C,QUERY!BL:BL) -> DEU,ZYA | HL6: =_xlfn.XLOOKUP(B6,QUERY!$C:$C,QUERY!BM:BM) -> ZYA | HM6: =_xlfn.XLOOKUP(B6,QUERY!$C:$C,QUERY!BN:BN) -> 3997122 | HN6: =_xlfn.XLOOKUP(B6,QUERY!$C:$C,QUERY!BO:BO) -> 462.00 | HO6: =_xlfn.XLOOKUP(B6,QUERY!$C:$C,QUERY!BP:BP) -> NULL | HP6: =_xlfn.XLOOKUP(B6,QUERY!$C:$C,QUERY!BQ:BQ) -> NULL | HQ6: =_xlfn.XLOOKUP(B6,QUERY!$C:$C,QUERY!BR:BR) -> 139939.61 | HR6: =_xlfn.XLOOKUP(B6,QUERY!$C:$C,QUERY!BS:BS) -> 0 | HS6: =_xlfn.XLOOKUP(B6,QUERY!$C:$C,QUERY!BT:BT) -> 0 | HT6: =_xlfn.XLOOKUP(B6,QUERY!$C:$C,QUERY!A:A) -> VERACRUZ | HU6: =_xlfn.XLOOKUP(B6,QUERY!$C:$C,QUERY!B:B) -> MARÍTIMO VERACRUZ
A7: INTERVET MEXICO SA DE CV | B7: VER-25-1248 | C7: 3942 | D7: 6000072 | F7: Importación | G7: A1 | H7: 0 | I7: 0 | J7: 0 | K7: 0 | L7: 0 | M7: 0 | N7: 0 | O7: 0 | P7: 0 | Q7: 0 | R7: 430 | S7: CAAU4072651 | T7: 0 | U7: 0 | V7: 0 | W7: 0 | X7: 0 | Y7: 0 | Z7: 0 | AA7: CEFA SAFE (MEDICAMENTO DOSIFICADO DE USO VETERINARIO) | AC7: 370535 | AD7: 2486.8121 | AE7: 0 | AF7: 0 | AG7: 0 | AH7: 0 | AI7: 0 | AJ7: 0 | AK7: 0 | AL7: 0 | AM7: 0 | AN7: 0 | AP7: INTERVET INTERNATIONAL BV | AQ7: 210358508 | AR7: CIP | AS7: MXP | AT7: 0 | AU7: 0 | AV7: 0 | AW7: 30042099 | AX7: 0 | AY7: 149 | AZ7: 149 | BA7: CAJA | BC7: ZYA | BD7: ZYA | BK7: COVE267WG87A1 | BL7: 0 | BM7: 0 | BN7: 0 | BO7: 0 | BP7: 0 | BQ7: 0 | BR7: 0 | BS7: 0 | BT7: 0 | BU7: 0 | BV7: 0 | BW7: 0 | BX7: 0 | BY7: 0 | BZ7: 0 | CA7: 0 | CB7: 0 | CC7: 0 | CD7: 0 | CE7: PAGADO | CF7: 0 | CG7: 0 | CH7: 0 | CI7: ZULEIMA PEREZ RUIZ | CJ7: ZULEIMA PEREZ RUIZ | CK7: =_xlfn.XLOOKUP($B$2,'BASE DE EXCEL'!C:C,'BASE DE EXCEL'!D:D,"NO HAY REFERENCIA") -> 470 | CL7: =_xlfn.XLOOKUP($B$2,'BASE DE EXCEL'!$C:$C,'BASE DE EXCEL'!F:F,"NO HAY REFERENCIA") -> 3 | CM7: =_xlfn.XLOOKUP($B$2,'BASE DE EXCEL'!$C:$C,'BASE DE EXCEL'!G:G,"NO HAY REFERENCIA") -> 46080 | CN7: =_xlfn.XLOOKUP($B$2,'BASE DE EXCEL'!$C:$C,'BASE DE EXCEL'!H:H,"NO HAY REFERENCIA") -> 46086 | CO7: =_xlfn.XLOOKUP($B$2,'BASE DE EXCEL'!$C:$C,'BASE DE EXCEL'!I:I,"NO HAY REFERENCIA") -> 4 | CP7: =_xlfn.XLOOKUP($B$2,'BASE DE EXCEL'!$C:$C,'BASE DE EXCEL'!J:J,"NO HAY REFERENCIA") -> 4 a 5 días | CQ7: =_xlfn.XLOOKUP($B$2,'BASE DE EXCEL'!$C:$C,'BASE DE EXCEL'!K:K,"NO HAY REFERENCIA") -> 46087 | CR7: =_xlfn.XLOOKUP($B$2,'BASE DE EXCEL'!$C:$C,'BASE DE EXCEL'!L:L,"NO HAY REFERENCIA") -> 5 | CS7: =_xlfn.XLOOKUP($B$2,'BASE DE EXCEL'!$C:$C,'BASE DE EXCEL'!M:M,"NO HAY REFERENCIA") -> 6 | CT7: =_xlfn.XLOOKUP($B$2,'BASE DE EXCEL'!$C:$C,'BASE DE EXCEL'!N:N,"NO HAY REFERENCIA") -> 6 a 10 días | CU7: =_xlfn.XLOOKUP($B$2,'BASE DE EXCEL'!$C:$C,'BASE DE EXCEL'!O:O,"NO HAY REFERENCIA") -> On Time | CV7: =_xlfn.XLOOKUP(B7,'BASE DE EXCEL'!$C:$C,'BASE DE EXCEL'!P:P,"NO HAY REFERENCIA") -> 4 a 5 días | CW7: =_xlfn.XLOOKUP(B7,'BASE DE EXCEL'!$C:$C,'BASE DE EXCEL'!Q:Q,"NO HAY REFERENCIA") -> 46031 | CX7: =_xlfn.XLOOKUP(B7,'BASE DE EXCEL'!$C:$C,'BASE DE EXCEL'!R:R,"NO HAY REFERENCIA") -> 5 | CY7: =_xlfn.XLOOKUP(B7,'BASE DE EXCEL'!$C:$C,'BASE DE EXCEL'!S:S,"NO HAY REFERENCIA") -> 4 a 5 días | CZ7: =_xlfn.XLOOKUP(B7,'BASE DE EXCEL'!$C:$C,'BASE DE EXCEL'!T:T,"NO HAY REFERENCIA") -> On Time | DA7: =_xlfn.XLOOKUP(B7,'BASE DE EXCEL'!$C:$C,'BASE DE EXCEL'!U:U,"NO HAY REFERENCIA") -> 6 | DB7: =_xlfn.XLOOKUP(B7,'BASE DE EXCEL'!$C:$C,'BASE DE EXCEL'!V:V,"NO HAY REFERENCIA") -> 4 a 5 días | DC7: =_xlfn.XLOOKUP(B7,'BASE DE EXCEL'!$C:$C,'BASE DE EXCEL'!W:W,"NO HAY REFERENCIA") -> 9 | DD7: =_xlfn.XLOOKUP(B7,'BASE DE EXCEL'!$C:$C,'BASE DE EXCEL'!X:X,"NO HAY REFERENCIA") -> 6 a 10 días | DE7: =_xlfn.XLOOKUP(B7,'BASE DE EXCEL'!$C:$C,'BASE DE EXCEL'!Y:Y,"NO HAY REFERENCIA") -> 1 | DF7: =_xlfn.XLOOKUP(B7,'BASE DE EXCEL'!$C:$C,'BASE DE EXCEL'!Z:Z,"NO HAY REFERENCIA") -> 1 día o menos | DG7: =_xlfn.XLOOKUP(B7,'BASE DE EXCEL'!$C:$C,'BASE DE EXCEL'!AA:AA,"NO HAY REFERENCIA") -> 4 | DH7: =_xlfn.XLOOKUP(B7,'BASE DE EXCEL'!$C:$C,'BASE DE EXCEL'!AB:AB,"NO HAY REFERENCIA") -> 1 | DI7: =_xlfn.XLOOKUP(B7,'BASE DE EXCEL'!$C:$C,'BASE DE EXCEL'!AC:AC,"NO HAY REFERENCIA") -> 1 día o menos | DJ7: =_xlfn.XLOOKUP(B7,'BASE DE EXCEL'!$C:$C,'BASE DE EXCEL'!AD:AD,"NO HAY REFERENCIA") -> 46038 | DK7: =_xlfn.XLOOKUP(B7,'BASE DE EXCEL'!$C:$C,'BASE DE EXCEL'!AE:AE,"NO HAY REFERENCIA") -> 7 | DL7: =_xlfn.XLOOKUP(B7,'BASE DE EXCEL'!$C:$C,'BASE DE EXCEL'!AF:AF,"NO HAY REFERENCIA") -> 5 | DM7: =_xlfn.XLOOKUP(B7,'BASE DE EXCEL'!$C:$C,'BASE DE EXCEL'!AG:AG,"NO HAY REFERENCIA") -> 46038 | DN7: =_xlfn.XLOOKUP(B7,'BASE DE EXCEL'!$C:$C,'BASE DE EXCEL'!AH:AH,"NO HAY REFERENCIA") -> 46038 | DO7: =_xlfn.XLOOKUP(B7,'BASE DE EXCEL'!$C:$C,'BASE DE EXCEL'!AI:AI,"NO HAY REFERENCIA") -> 0 | DP7: =_xlfn.XLOOKUP(B7,'BASE DE EXCEL'!$C:$C,'BASE DE EXCEL'!AJ:AJ,"NO HAY REFERENCIA") -> 6 a 10 días | DQ7: =_xlfn.XLOOKUP(B7,'BASE DE EXCEL'!$C:$C,'BASE DE EXCEL'!AK:AK,"NO HAY REFERENCIA") -> 46038 | DR7: =_xlfn.XLOOKUP(B7,'BASE DE EXCEL'!$C:$C,'BASE DE EXCEL'!AL:AL,"NO HAY REFERENCIA") -> 6 | DS7: =_xlfn.XLOOKUP(B7,'BASE DE EXCEL'!$C:$C,'BASE DE EXCEL'!AM:AM,"NO HAY REFERENCIA") -> 6 a 10 días | DT7: =_xlfn.XLOOKUP(B7,'BASE DE EXCEL'!$C:$C,'BASE DE EXCEL'!AN:AN,"NO HAY REFERENCIA") -> On Time | DU7: =_xlfn.XLOOKUP(B7,'BASE DE EXCEL'!$C:$C,'BASE DE EXCEL'!AO:AO,"NO HAY REFERENCIA") -> 1 | DV7: =_xlfn.XLOOKUP(B7,'BASE DE EXCEL'!$C:$C,'BASE DE EXCEL'!AP:AP,"NO HAY REFERENCIA") -> Es anterior | DW7: =_xlfn.XLOOKUP(B7,'BASE DE EXCEL'!$C:$C,'BASE DE EXCEL'!AQ:AQ,"NO HAY REFERENCIA") -> A1 | DX7: =_xlfn.XLOOKUP(B7,'BASE DE EXCEL'!$C:$C,'BASE DE EXCEL'!AR:AR,"NO HAY REFERENCIA") -> ZULEIMA PEREZ RUIZ | DY7: =_xlfn.XLOOKUP(B7,'BASE DE EXCEL'!$C:$C,'BASE DE EXCEL'!AS:AS,"NO HAY REFERENCIA") -> HLCUANR251131095 | DZ7: =_xlfn.XLOOKUP(B7,'BASE DE EXCEL'!$C:$C,'BASE DE EXCEL'!AT:AT,"NO HAY REFERENCIA") -> NULL | EA7: =_xlfn.XLOOKUP(B7,'BASE DE EXCEL'!$C:$C,'BASE DE EXCEL'!AU:AU,"NO HAY REFERENCIA") -> 6000072 | EB7: =_xlfn.XLOOKUP(B7,'BASE DE EXCEL'!$C:$C,'BASE DE EXCEL'!AV:AV,"NO HAY REFERENCIA") -> Importación | EC7: =_xlfn.XLOOKUP(B7,'BASE DE EXCEL'!$C:$C,'BASE DE EXCEL'!AW:AW,"NO HAY REFERENCIA") -> CEFA SAFE (MEDICAMENTO DOSIFICADO DE USO VETERINARIO) | ED7: =_xlfn.XLOOKUP(B7,'BASE DE EXCEL'!$C:$C,'BASE DE EXCEL'!AX:AX,"NO HAY REFERENCIA") -> SIN CLASIFICACION | EE7: =_xlfn.XLOOKUP(B7,'BASE DE EXCEL'!$C:$C,'BASE DE EXCEL'!AY:AY,"NO HAY REFERENCIA") -> 0 | EF7: =_xlfn.XLOOKUP(B7,'BASE DE EXCEL'!$C:$C,'BASE DE EXCEL'!AZ:AZ,"NO HAY REFERENCIA") -> Cargas de Importación | EG7: =_xlfn.XLOOKUP(B7,'BASE DE EXCEL'!$C:$C,'BASE DE EXCEL'!BA:BA,"NO HAY REFERENCIA") -> INTERVET MEXICO SA DE CV | EH7: =_xlfn.XLOOKUP(B7,'BASE DE EXCEL'!$C:$C,'BASE DE EXCEL'!BB:BB,"NO HAY REFERENCIA") -> 0 | EI7: =_xlfn.XLOOKUP(B7,'BASE DE EXCEL'!$C:$C,'BASE DE EXCEL'!BC:BC,"NO HAY REFERENCIA") -> NINGUNO | EJ7: =_xlfn.XLOOKUP(B7,'BASE DE EXCEL'!$C:$C,'BASE DE EXCEL'!BD:BD,"NO HAY REFERENCIA") -> 0 | EK7: =_xlfn.XLOOKUP(B7,'BASE DE EXCEL'!$C:$C,'BASE DE EXCEL'!BE:BE,"NO HAY REFERENCIA") -> NINGUNO | EL7: =_xlfn.XLOOKUP(B7,'BASE DE EXCEL'!$C:$C,'BASE DE EXCEL'!BF:BF,"NO HAY REFERENCIA") -> PRODUCTO TERMINADO | EM7: =_xlfn.XLOOKUP(B7,'BASE DE EXCEL'!$C:$C,'BASE DE EXCEL'!BG:BG,"NO HAY REFERENCIA") -> Verde | EN7: =_xlfn.XLOOKUP(B7,'BASE DE EXCEL'!$C:$C,'BASE DE EXCEL'!BH:BH,"NO HAY REFERENCIA") -> SUPER EXPRESS DE CARGA FEDERAL S.A. DE C.V. | EO7: =_xlfn.XLOOKUP(B7,'BASE DE EXCEL'!$C:$C,'BASE DE EXCEL'!BI:BI,"NO HAY REFERENCIA") -> 0 | EP7: =_xlfn.XLOOKUP(B7,'BASE DE EXCEL'!$C:$C,'BASE DE EXCEL'!BJ:BJ,"NO HAY REFERENCIA") -> IME-T006 | EQ7: =_xlfn.XLOOKUP(B7,'BASE DE EXCEL'!$C:$C,'BASE DE EXCEL'!BK:BK,"NO HAY REFERENCIA") -> IME850329RH2 | ER7: =_xlfn.XLOOKUP(B7,'BASE DE EXCEL'!$C:$C,'BASE DE EXCEL'!BL:BL,"NO HAY REFERENCIA") -> 0 | ES7: =_xlfn.XLOOKUP(B7,'BASE DE EXCEL'!$C:$C,'BASE DE EXCEL'!BM:BM,"NO HAY REFERENCIA") -> 00,99 | ET7: =_xlfn.XLOOKUP(B7,'BASE DE EXCEL'!$C:$C,'BASE DE EXCEL'!BN:BN,"NO HAY REFERENCIA") -> LOTE: A217A05,LOTE: A219A02,LOTE: A219A01,LOTE: A217A03,LOTE: H107A01,LOTES: J550A01, J607A01,LOTE: 5677101,LOTE: A217A04 | EU7: =_xlfn.XLOOKUP(B7,'BASE DE EXCEL'!$C:$C,'BASE DE EXCEL'!BO:BO,"NO HAY REFERENCIA") -> 90 | EV7: =_xlfn.XLOOKUP(B7,'BASE DE EXCEL'!$C:$C,'BASE DE EXCEL'!BP:BP,"NO HAY REFERENCIA") -> 952448.23, 2181141.30, 863532.00 | EW7: =_xlfn.XLOOKUP(B7,'BASE DE EXCEL'!$C:$C,'BASE DE EXCEL'!BQ:BQ,"NO HAY REFERENCIA") -> KILO,KILO,KILO,KILO,KILO,KILO,KILO,KILO | EX7: =_xlfn.XLOOKUP(B7,'BASE DE EXCEL'!$C:$C,'BASE DE EXCEL'!BR:BR,"NO HAY REFERENCIA") -> 0 | EY7: =_xlfn.XLOOKUP(B7,'BASE DE EXCEL'!$C:$C,'BASE DE EXCEL'!BS:BS,"NO HAY REFERENCIA") -> ALEMANIA (REPUBLICA FEDERAL DE),PAISES BAJOS (REINO DE LOS) (HOLANDA) | EZ7: =_xlfn.XLOOKUP(B7,'BASE DE EXCEL'!$C:$C,'BASE DE EXCEL'!BT:BT,"NO HAY REFERENCIA") -> PAISES BAJOS (REINO DE LOS) (HOLANDA) | FA7: =_xlfn.XLOOKUP(B7,'BASE DE EXCEL'!$C:$C,'BASE DE EXCEL'!BU:BU,"NO HAY REFERENCIA") -> DEU,ZYA | FB7: =_xlfn.XLOOKUP(B7,'BASE DE EXCEL'!$C:$C,'BASE DE EXCEL'!BV:BV,"NO HAY REFERENCIA") -> ZYA | FC7: =_xlfn.XLOOKUP(B7,QUERY!$C:$C,QUERY!D:D) -> 430 | FD7: =_xlfn.XLOOKUP(B7,QUERY!$C:$C,QUERY!E:E) -> 46029 | FE7: =_xlfn.XLOOKUP(B7,QUERY!$C:$C,QUERY!F:F) -> 1 | FF7: =_xlfn.XLOOKUP(B7,QUERY!$C:$C,QUERY!G:G) -> 46025 | FG7: =_xlfn.XLOOKUP(B7,QUERY!$C:$C,QUERY!H:H) -> 46029 | FH7: =_xlfn.XLOOKUP(B7,QUERY!$C:$C,QUERY!I:I) -> 2 | FI7: =_xlfn.XLOOKUP(B7,QUERY!$C:$C,QUERY!J:J) -> 2 a 3 días | FJ7: =_xlfn.XLOOKUP(B7,QUERY!$C:$C,QUERY!K:K) -> 46030 | FK7: =_xlfn.XLOOKUP(B7,QUERY!$C:$C,QUERY!L:L) -> 3 | FL7: =_xlfn.XLOOKUP(B7,QUERY!$C:$C,QUERY!M:M) -> 2 a 3 días | FM7: =_xlfn.XLOOKUP(B7,QUERY!$C:$C,QUERY!N:N) -> 1 | FN7: =_xlfn.XLOOKUP(B7,QUERY!$C:$C,QUERY!O:O) -> 1 día o menos | FO7: =_xlfn.XLOOKUP(B7,QUERY!$C:$C,QUERY!P:P) -> 1 | FP7: =_xlfn.XLOOKUP(B7,QUERY!$C:$C,QUERY!Q:Q) -> 1 | FQ7: =_xlfn.XLOOKUP(B7,QUERY!$C:$C,QUERY!R:R) -> 1 día o menos | FR7: =_xlfn.XLOOKUP(B7,QUERY!$C:$C,QUERY!S:S) -> 46031 | FS7: =_xlfn.XLOOKUP(B7,QUERY!$C:$C,QUERY!T:T) -> 4 | FT7: =_xlfn.XLOOKUP(B7,QUERY!$C:$C,QUERY!U:U) -> 4 a 5 días | FU7: =_xlfn.XLOOKUP(B7,QUERY!$C:$C,QUERY!V:V) -> 9 | FV7: =_xlfn.XLOOKUP(B7,QUERY!$C:$C,QUERY!W:W) -> 6 a 10 días | FW7: =_xlfn.XLOOKUP(B7,QUERY!$C:$C,QUERY!X:X) -> 46038 | FX7: =_xlfn.XLOOKUP(B7,QUERY!$C:$C,QUERY!Y:Y) -> 5 | FY7: =_xlfn.XLOOKUP(B7,QUERY!$C:$C,QUERY!Z:Z) -> 5 | FZ7: =_xlfn.XLOOKUP(B7,QUERY!$C:$C,QUERY!AA:AA) -> 6 a 10 días | GA7: =_xlfn.XLOOKUP(B7,QUERY!$C:$C,QUERY!AB:AB) -> 46038 | GB7: =_xlfn.XLOOKUP(B7,QUERY!$C:$C,QUERY!AC:AC) -> 46038 | GC7: =_xlfn.XLOOKUP(B7,QUERY!$C:$C,QUERY!AD:AD) -> 0 | GD7: =_xlfn.XLOOKUP(B7,QUERY!$C:$C,QUERY!AE:AE) -> 46038 | GE7: =_xlfn.XLOOKUP(B7,QUERY!$C:$C,QUERY!AF:AF) -> 1 | GF7: =_xlfn.XLOOKUP(B7,QUERY!$C:$C,QUERY!AG:AG) -> Es anterior | GG7: =_xlfn.XLOOKUP(B7,QUERY!$C:$C,QUERY!AH:AH) -> A1 | GH7: =_xlfn.XLOOKUP(B7,QUERY!$C:$C,QUERY!AI:AI) -> ZULEIMA PEREZ RUIZ | GI7: =_xlfn.XLOOKUP(B7,QUERY!$C:$C,QUERY!AJ:AJ) -> HLCUANR251131095 | GJ7: =_xlfn.XLOOKUP(B7,QUERY!$C:$C,QUERY!AK:AK) -> NULL | GK7: =_xlfn.XLOOKUP(B7,QUERY!$C:$C,QUERY!AL:AL) -> 6000072 | GL7: =_xlfn.XLOOKUP(B7,QUERY!$C:$C,QUERY!AM:AM) -> Importación | GM7: =_xlfn.XLOOKUP(B7,QUERY!$C:$C,QUERY!AN:AN) -> CEFA SAFE (MEDICAMENTO DOSIFICADO DE USO VETERINARIO) | GN7: =_xlfn.XLOOKUP(B7,QUERY!$C:$C,QUERY!AO:AO) -> SIN CLASIFICACION | GO7: =_xlfn.XLOOKUP(B7,QUERY!$C:$C,QUERY!AP:AP) -> 0 | GP7: =_xlfn.XLOOKUP(B7,QUERY!$C:$C,QUERY!AQ:AQ) -> Cargas de Importación | GQ7: =_xlfn.XLOOKUP(B7,QUERY!$C:$C,QUERY!AR:AR) -> INTERVET MEXICO SA DE CV | GR7: =_xlfn.XLOOKUP(B7,QUERY!$C:$C,QUERY!AS:AS) -> 0 | GS7: =_xlfn.XLOOKUP(B7,QUERY!$C:$C,QUERY!AT:AT) -> NINGUNO | GT7: =_xlfn.XLOOKUP(B7,QUERY!$C:$C,QUERY!AU:AU) -> 0 | GU7: =_xlfn.XLOOKUP(B7,QUERY!$C:$C,QUERY!AV:AV) -> NINGUNO | GV7: =_xlfn.XLOOKUP(B7,QUERY!$C:$C,QUERY!AW:AW) -> PRODUCTO TERMINADO | GW7: =_xlfn.XLOOKUP(B7,QUERY!$C:$C,QUERY!AX:AX) -> Verde | GX7: =_xlfn.XLOOKUP(B7,QUERY!$C:$C,QUERY!AY:AY) -> SUPER EXPRESS DE CARGA FEDERAL S.A. DE C.V. | GY7: =_xlfn.XLOOKUP(B7,QUERY!$C:$C,QUERY!AZ:AZ) -> 0 | GZ7: =_xlfn.XLOOKUP(B7,QUERY!$C:$C,QUERY!BA:BA) -> IME-T006 | HA7: =_xlfn.XLOOKUP(B7,QUERY!$C:$C,QUERY!BB:BB) -> IME850329RH2 | HB7: =_xlfn.XLOOKUP(B7,QUERY!$C:$C,QUERY!BC:BC) -> 0 | HC7: =_xlfn.XLOOKUP(B7,QUERY!$C:$C,QUERY!BD:BD) -> 0.99 | HD7: =_xlfn.XLOOKUP(B7,QUERY!$C:$C,QUERY!BE:BE) -> LOTE: A217A05,LOTE: A219A02,LOTE: A219A01,LOTE: A217A04,LOTE: A217A03,LOTE: H107A01,LOTES: J550A01, J607A01,LOTE: 5677101 | HE7: =_xlfn.XLOOKUP(B7,QUERY!$C:$C,QUERY!BF:BF) -> 90 | HF7: =_xlfn.XLOOKUP(B7,QUERY!$C:$C,QUERY!BG:BG) -> 952448.23, 2181141.30, 863532.00 | HG7: =_xlfn.XLOOKUP(B7,QUERY!$C:$C,QUERY!BH:BH) -> KILO,KILO,KILO,KILO,KILO,KILO,KILO,KILO | HH7: =_xlfn.XLOOKUP(B7,QUERY!$C:$C,QUERY!BI:BI) -> 0 | HI7: =_xlfn.XLOOKUP(B7,QUERY!$C:$C,QUERY!BJ:BJ) -> ALEMANIA (REPUBLICA FEDERAL DE),PAISES BAJOS (REINO DE LOS) (HOLANDA) | HJ7: =_xlfn.XLOOKUP(B7,QUERY!$C:$C,QUERY!BK:BK) -> PAISES BAJOS (REINO DE LOS) (HOLANDA) | HK7: =_xlfn.XLOOKUP(B7,QUERY!$C:$C,QUERY!BL:BL) -> DEU,ZYA | HL7: =_xlfn.XLOOKUP(B7,QUERY!$C:$C,QUERY!BM:BM) -> ZYA | HM7: =_xlfn.XLOOKUP(B7,QUERY!$C:$C,QUERY!BN:BN) -> 3997122 | HN7: =_xlfn.XLOOKUP(B7,QUERY!$C:$C,QUERY!BO:BO) -> 462.00 | HO7: =_xlfn.XLOOKUP(B7,QUERY!$C:$C,QUERY!BP:BP) -> NULL | HP7: =_xlfn.XLOOKUP(B7,QUERY!$C:$C,QUERY!BQ:BQ) -> NULL | HQ7: =_xlfn.XLOOKUP(B7,QUERY!$C:$C,QUERY!BR:BR) -> 139939.61 | HR7: =_xlfn.XLOOKUP(B7,QUERY!$C:$C,QUERY!BS:BS) -> 0 | HS7: =_xlfn.XLOOKUP(B7,QUERY!$C:$C,QUERY!BT:BT) -> 0 | HT7: =_xlfn.XLOOKUP(B7,QUERY!$C:$C,QUERY!A:A) -> VERACRUZ | HU7: =_xlfn.XLOOKUP(B7,QUERY!$C:$C,QUERY!B:B) -> MARÍTIMO VERACRUZ
A8: INTERVET MEXICO SA DE CV | B8: VER-25-1248 | C8: 3942 | D8: 6000072 | F8: Importación | G8: A1 | H8: 0 | I8: 0 | J8: 0 | K8: 0 | L8: 0 | M8: 0 | N8: 0 | O8: 0 | P8: 0 | Q8: 0 | R8: 430 | S8: CAAU4072651 | T8: 0 | U8: 0 | V8: 0 | W8: 0 | X8: 0 | Y8: 0 | Z8: 0 | AA8: CEFA SAFE (MEDICAMENTO DOSIFICADO DE USO VETERINARIO) | AC8: 181537 | AD8: 2486.8082 | AE8: 0 | AF8: 0 | AG8: 0 | AH8: 0 | AI8: 0 | AJ8: 0 | AK8: 0 | AL8: 0 | AM8: 0 | AN8: 0 | AP8: INTERVET INTERNATIONAL BV | AQ8: 210358509 | AR8: CIP | AS8: MXP | AT8: 0 | AU8: 0 | AV8: 0 | AW8: 30042099 | AX8: 0 | AY8: 73 | AZ8: 73 | BA8: CAJA | BC8: ZYA | BD8: ZYA | BK8: COVE267WH9PS7 | BL8: 0 | BM8: 0 | BN8: 0 | BO8: 0 | BP8: 0 | BQ8: 0 | BR8: 0 | BS8: 0 | BT8: 0 | BU8: 0 | BV8: 0 | BW8: 0 | BX8: 0 | BY8: 0 | BZ8: 0 | CA8: 0 | CB8: 0 | CC8: 0 | CD8: 0 | CE8: PAGADO | CF8: 0 | CG8: 0 | CH8: 0 | CI8: ZULEIMA PEREZ RUIZ | CJ8: ZULEIMA PEREZ RUIZ | CK8: =_xlfn.XLOOKUP($B$2,'BASE DE EXCEL'!C:C,'BASE DE EXCEL'!D:D,"NO HAY REFERENCIA") -> 470 | CL8: =_xlfn.XLOOKUP($B$2,'BASE DE EXCEL'!$C:$C,'BASE DE EXCEL'!F:F,"NO HAY REFERENCIA") -> 3 | CM8: =_xlfn.XLOOKUP($B$2,'BASE DE EXCEL'!$C:$C,'BASE DE EXCEL'!G:G,"NO HAY REFERENCIA") -> 46080 | CN8: =_xlfn.XLOOKUP($B$2,'BASE DE EXCEL'!$C:$C,'BASE DE EXCEL'!H:H,"NO HAY REFERENCIA") -> 46086 | CO8: =_xlfn.XLOOKUP($B$2,'BASE DE EXCEL'!$C:$C,'BASE DE EXCEL'!I:I,"NO HAY REFERENCIA") -> 4 | CP8: =_xlfn.XLOOKUP($B$2,'BASE DE EXCEL'!$C:$C,'BASE DE EXCEL'!J:J,"NO HAY REFERENCIA") -> 4 a 5 días | CQ8: =_xlfn.XLOOKUP($B$2,'BASE DE EXCEL'!$C:$C,'BASE DE EXCEL'!K:K,"NO HAY REFERENCIA") -> 46087 | CR8: =_xlfn.XLOOKUP($B$2,'BASE DE EXCEL'!$C:$C,'BASE DE EXCEL'!L:L,"NO HAY REFERENCIA") -> 5 | CS8: =_xlfn.XLOOKUP($B$2,'BASE DE EXCEL'!$C:$C,'BASE DE EXCEL'!M:M,"NO HAY REFERENCIA") -> 6 | CT8: =_xlfn.XLOOKUP($B$2,'BASE DE EXCEL'!$C:$C,'BASE DE EXCEL'!N:N,"NO HAY REFERENCIA") -> 6 a 10 días | CU8: =_xlfn.XLOOKUP($B$2,'BASE DE EXCEL'!$C:$C,'BASE DE EXCEL'!O:O,"NO HAY REFERENCIA") -> On Time | CV8: =_xlfn.XLOOKUP(B8,'BASE DE EXCEL'!$C:$C,'BASE DE EXCEL'!P:P,"NO HAY REFERENCIA") -> 4 a 5 días | CW8: =_xlfn.XLOOKUP(B8,'BASE DE EXCEL'!$C:$C,'BASE DE EXCEL'!Q:Q,"NO HAY REFERENCIA") -> 46031 | CX8: =_xlfn.XLOOKUP(B8,'BASE DE EXCEL'!$C:$C,'BASE DE EXCEL'!R:R,"NO HAY REFERENCIA") -> 5 | CY8: =_xlfn.XLOOKUP(B8,'BASE DE EXCEL'!$C:$C,'BASE DE EXCEL'!S:S,"NO HAY REFERENCIA") -> 4 a 5 días | CZ8: =_xlfn.XLOOKUP(B8,'BASE DE EXCEL'!$C:$C,'BASE DE EXCEL'!T:T,"NO HAY REFERENCIA") -> On Time | DA8: =_xlfn.XLOOKUP(B8,'BASE DE EXCEL'!$C:$C,'BASE DE EXCEL'!U:U,"NO HAY REFERENCIA") -> 6 | DB8: =_xlfn.XLOOKUP(B8,'BASE DE EXCEL'!$C:$C,'BASE DE EXCEL'!V:V,"NO HAY REFERENCIA") -> 4 a 5 días | DC8: =_xlfn.XLOOKUP(B8,'BASE DE EXCEL'!$C:$C,'BASE DE EXCEL'!W:W,"NO HAY REFERENCIA") -> 9 | DD8: =_xlfn.XLOOKUP(B8,'BASE DE EXCEL'!$C:$C,'BASE DE EXCEL'!X:X,"NO HAY REFERENCIA") -> 6 a 10 días | DE8: =_xlfn.XLOOKUP(B8,'BASE DE EXCEL'!$C:$C,'BASE DE EXCEL'!Y:Y,"NO HAY REFERENCIA") -> 1 | DF8: =_xlfn.XLOOKUP(B8,'BASE DE EXCEL'!$C:$C,'BASE DE EXCEL'!Z:Z,"NO HAY REFERENCIA") -> 1 día o menos | DG8: =_xlfn.XLOOKUP(B8,'BASE DE EXCEL'!$C:$C,'BASE DE EXCEL'!AA:AA,"NO HAY REFERENCIA") -> 4 | DH8: =_xlfn.XLOOKUP(B8,'BASE DE EXCEL'!$C:$C,'BASE DE EXCEL'!AB:AB,"NO HAY REFERENCIA") -> 1 | DI8: =_xlfn.XLOOKUP(B8,'BASE DE EXCEL'!$C:$C,'BASE DE EXCEL'!AC:AC,"NO HAY REFERENCIA") -> 1 día o menos | DJ8: =_xlfn.XLOOKUP(B8,'BASE DE EXCEL'!$C:$C,'BASE DE EXCEL'!AD:AD,"NO HAY REFERENCIA") -> 46038 | DK8: =_xlfn.XLOOKUP(B8,'BASE DE EXCEL'!$C:$C,'BASE DE EXCEL'!AE:AE,"NO HAY REFERENCIA") -> 7 | DL8: =_xlfn.XLOOKUP(B8,'BASE DE EXCEL'!$C:$C,'BASE DE EXCEL'!AF:AF,"NO HAY REFERENCIA") -> 5 | DM8: =_xlfn.XLOOKUP(B8,'BASE DE EXCEL'!$C:$C,'BASE DE EXCEL'!AG:AG,"NO HAY REFERENCIA") -> 46038 | DN8: =_xlfn.XLOOKUP(B8,'BASE DE EXCEL'!$C:$C,'BASE DE EXCEL'!AH:AH,"NO HAY REFERENCIA") -> 46038 | DO8: =_xlfn.XLOOKUP(B8,'BASE DE EXCEL'!$C:$C,'BASE DE EXCEL'!AI:AI,"NO HAY REFERENCIA") -> 0 | DP8: =_xlfn.XLOOKUP(B8,'BASE DE EXCEL'!$C:$C,'BASE DE EXCEL'!AJ:AJ,"NO HAY REFERENCIA") -> 6 a 10 días | DQ8: =_xlfn.XLOOKUP(B8,'BASE DE EXCEL'!$C:$C,'BASE DE EXCEL'!AK:AK,"NO HAY REFERENCIA") -> 46038 | DR8: =_xlfn.XLOOKUP(B8,'BASE DE EXCEL'!$C:$C,'BASE DE EXCEL'!AL:AL,"NO HAY REFERENCIA") -> 6 | DS8: =_xlfn.XLOOKUP(B8,'BASE DE EXCEL'!$C:$C,'BASE DE EXCEL'!AM:AM,"NO HAY REFERENCIA") -> 6 a 10 días | DT8: =_xlfn.XLOOKUP(B8,'BASE DE EXCEL'!$C:$C,'BASE DE EXCEL'!AN:AN,"NO HAY REFERENCIA") -> On Time | DU8: =_xlfn.XLOOKUP(B8,'BASE DE EXCEL'!$C:$C,'BASE DE EXCEL'!AO:AO,"NO HAY REFERENCIA") -> 1 | DV8: =_xlfn.XLOOKUP(B8,'BASE DE EXCEL'!$C:$C,'BASE DE EXCEL'!AP:AP,"NO HAY REFERENCIA") -> Es anterior | DW8: =_xlfn.XLOOKUP(B8,'BASE DE EXCEL'!$C:$C,'BASE DE EXCEL'!AQ:AQ,"NO HAY REFERENCIA") -> A1 | DX8: =_xlfn.XLOOKUP(B8,'BASE DE EXCEL'!$C:$C,'BASE DE EXCEL'!AR:AR,"NO HAY REFERENCIA") -> ZULEIMA PEREZ RUIZ | DY8: =_xlfn.XLOOKUP(B8,'BASE DE EXCEL'!$C:$C,'BASE DE EXCEL'!AS:AS,"NO HAY REFERENCIA") -> HLCUANR251131095 | DZ8: =_xlfn.XLOOKUP(B8,'BASE DE EXCEL'!$C:$C,'BASE DE EXCEL'!AT:AT,"NO HAY REFERENCIA") -> NULL | EA8: =_xlfn.XLOOKUP(B8,'BASE DE EXCEL'!$C:$C,'BASE DE EXCEL'!AU:AU,"NO HAY REFERENCIA") -> 6000072 | EB8: =_xlfn.XLOOKUP(B8,'BASE DE EXCEL'!$C:$C,'BASE DE EXCEL'!AV:AV,"NO HAY REFERENCIA") -> Importación | EC8: =_xlfn.XLOOKUP(B8,'BASE DE EXCEL'!$C:$C,'BASE DE EXCEL'!AW:AW,"NO HAY REFERENCIA") -> CEFA SAFE (MEDICAMENTO DOSIFICADO DE USO VETERINARIO) | ED8: =_xlfn.XLOOKUP(B8,'BASE DE EXCEL'!$C:$C,'BASE DE EXCEL'!AX:AX,"NO HAY REFERENCIA") -> SIN CLASIFICACION | EE8: =_xlfn.XLOOKUP(B8,'BASE DE EXCEL'!$C:$C,'BASE DE EXCEL'!AY:AY,"NO HAY REFERENCIA") -> 0 | EF8: =_xlfn.XLOOKUP(B8,'BASE DE EXCEL'!$C:$C,'BASE DE EXCEL'!AZ:AZ,"NO HAY REFERENCIA") -> Cargas de Importación | EG8: =_xlfn.XLOOKUP(B8,'BASE DE EXCEL'!$C:$C,'BASE DE EXCEL'!BA:BA,"NO HAY REFERENCIA") -> INTERVET MEXICO SA DE CV | EH8: =_xlfn.XLOOKUP(B8,'BASE DE EXCEL'!$C:$C,'BASE DE EXCEL'!BB:BB,"NO HAY REFERENCIA") -> 0 | EI8: =_xlfn.XLOOKUP(B8,'BASE DE EXCEL'!$C:$C,'BASE DE EXCEL'!BC:BC,"NO HAY REFERENCIA") -> NINGUNO | EJ8: =_xlfn.XLOOKUP(B8,'BASE DE EXCEL'!$C:$C,'BASE DE EXCEL'!BD:BD,"NO HAY REFERENCIA") -> 0 | EK8: =_xlfn.XLOOKUP(B8,'BASE DE EXCEL'!$C:$C,'BASE DE EXCEL'!BE:BE,"NO HAY REFERENCIA") -> NINGUNO | EL8: =_xlfn.XLOOKUP(B8,'BASE DE EXCEL'!$C:$C,'BASE DE EXCEL'!BF:BF,"NO HAY REFERENCIA") -> PRODUCTO TERMINADO | EM8: =_xlfn.XLOOKUP(B8,'BASE DE EXCEL'!$C:$C,'BASE DE EXCEL'!BG:BG,"NO HAY REFERENCIA") -> Verde | EN8: =_xlfn.XLOOKUP(B8,'BASE DE EXCEL'!$C:$C,'BASE DE EXCEL'!BH:BH,"NO HAY REFERENCIA") -> SUPER EXPRESS DE CARGA FEDERAL S.A. DE C.V. | EO8: =_xlfn.XLOOKUP(B8,'BASE DE EXCEL'!$C:$C,'BASE DE EXCEL'!BI:BI,"NO HAY REFERENCIA") -> 0 | EP8: =_xlfn.XLOOKUP(B8,'BASE DE EXCEL'!$C:$C,'BASE DE EXCEL'!BJ:BJ,"NO HAY REFERENCIA") -> IME-T006 | EQ8: =_xlfn.XLOOKUP(B8,'BASE DE EXCEL'!$C:$C,'BASE DE EXCEL'!BK:BK,"NO HAY REFERENCIA") -> IME850329RH2 | ER8: =_xlfn.XLOOKUP(B8,'BASE DE EXCEL'!$C:$C,'BASE DE EXCEL'!BL:BL,"NO HAY REFERENCIA") -> 0 | ES8: =_xlfn.XLOOKUP(B8,'BASE DE EXCEL'!$C:$C,'BASE DE EXCEL'!BM:BM,"NO HAY REFERENCIA") -> 00,99 | ET8: =_xlfn.XLOOKUP(B8,'BASE DE EXCEL'!$C:$C,'BASE DE EXCEL'!BN:BN,"NO HAY REFERENCIA") -> LOTE: A217A05,LOTE: A219A02,LOTE: A219A01,LOTE: A217A03,LOTE: H107A01,LOTES: J550A01, J607A01,LOTE: 5677101,LOTE: A217A04 | EU8: =_xlfn.XLOOKUP(B8,'BASE DE EXCEL'!$C:$C,'BASE DE EXCEL'!BO:BO,"NO HAY REFERENCIA") -> 90 | EV8: =_xlfn.XLOOKUP(B8,'BASE DE EXCEL'!$C:$C,'BASE DE EXCEL'!BP:BP,"NO HAY REFERENCIA") -> 952448.23, 2181141.30, 863532.00 | EW8: =_xlfn.XLOOKUP(B8,'BASE DE EXCEL'!$C:$C,'BASE DE EXCEL'!BQ:BQ,"NO HAY REFERENCIA") -> KILO,KILO,KILO,KILO,KILO,KILO,KILO,KILO | EX8: =_xlfn.XLOOKUP(B8,'BASE DE EXCEL'!$C:$C,'BASE DE EXCEL'!BR:BR,"NO HAY REFERENCIA") -> 0 | EY8: =_xlfn.XLOOKUP(B8,'BASE DE EXCEL'!$C:$C,'BASE DE EXCEL'!BS:BS,"NO HAY REFERENCIA") -> ALEMANIA (REPUBLICA FEDERAL DE),PAISES BAJOS (REINO DE LOS) (HOLANDA) | EZ8: =_xlfn.XLOOKUP(B8,'BASE DE EXCEL'!$C:$C,'BASE DE EXCEL'!BT:BT,"NO HAY REFERENCIA") -> PAISES BAJOS (REINO DE LOS) (HOLANDA) | FA8: =_xlfn.XLOOKUP(B8,'BASE DE EXCEL'!$C:$C,'BASE DE EXCEL'!BU:BU,"NO HAY REFERENCIA") -> DEU,ZYA | FB8: =_xlfn.XLOOKUP(B8,'BASE DE EXCEL'!$C:$C,'BASE DE EXCEL'!BV:BV,"NO HAY REFERENCIA") -> ZYA | FC8: =_xlfn.XLOOKUP(B8,QUERY!$C:$C,QUERY!D:D) -> 430 | FD8: =_xlfn.XLOOKUP(B8,QUERY!$C:$C,QUERY!E:E) -> 46029 | FE8: =_xlfn.XLOOKUP(B8,QUERY!$C:$C,QUERY!F:F) -> 1 | FF8: =_xlfn.XLOOKUP(B8,QUERY!$C:$C,QUERY!G:G) -> 46025 | FG8: =_xlfn.XLOOKUP(B8,QUERY!$C:$C,QUERY!H:H) -> 46029 | FH8: =_xlfn.XLOOKUP(B8,QUERY!$C:$C,QUERY!I:I) -> 2 | FI8: =_xlfn.XLOOKUP(B8,QUERY!$C:$C,QUERY!J:J) -> 2 a 3 días | FJ8: =_xlfn.XLOOKUP(B8,QUERY!$C:$C,QUERY!K:K) -> 46030 | FK8: =_xlfn.XLOOKUP(B8,QUERY!$C:$C,QUERY!L:L) -> 3 | FL8: =_xlfn.XLOOKUP(B8,QUERY!$C:$C,QUERY!M:M) -> 2 a 3 días | FM8: =_xlfn.XLOOKUP(B8,QUERY!$C:$C,QUERY!N:N) -> 1 | FN8: =_xlfn.XLOOKUP(B8,QUERY!$C:$C,QUERY!O:O) -> 1 día o menos | FO8: =_xlfn.XLOOKUP(B8,QUERY!$C:$C,QUERY!P:P) -> 1 | FP8: =_xlfn.XLOOKUP(B8,QUERY!$C:$C,QUERY!Q:Q) -> 1 | FQ8: =_xlfn.XLOOKUP(B8,QUERY!$C:$C,QUERY!R:R) -> 1 día o menos | FR8: =_xlfn.XLOOKUP(B8,QUERY!$C:$C,QUERY!S:S) -> 46031 | FS8: =_xlfn.XLOOKUP(B8,QUERY!$C:$C,QUERY!T:T) -> 4 | FT8: =_xlfn.XLOOKUP(B8,QUERY!$C:$C,QUERY!U:U) -> 4 a 5 días | FU8: =_xlfn.XLOOKUP(B8,QUERY!$C:$C,QUERY!V:V) -> 9 | FV8: =_xlfn.XLOOKUP(B8,QUERY!$C:$C,QUERY!W:W) -> 6 a 10 días | FW8: =_xlfn.XLOOKUP(B8,QUERY!$C:$C,QUERY!X:X) -> 46038 | FX8: =_xlfn.XLOOKUP(B8,QUERY!$C:$C,QUERY!Y:Y) -> 5 | FY8: =_xlfn.XLOOKUP(B8,QUERY!$C:$C,QUERY!Z:Z) -> 5 | FZ8: =_xlfn.XLOOKUP(B8,QUERY!$C:$C,QUERY!AA:AA) -> 6 a 10 días | GA8: =_xlfn.XLOOKUP(B8,QUERY!$C:$C,QUERY!AB:AB) -> 46038 | GB8: =_xlfn.XLOOKUP(B8,QUERY!$C:$C,QUERY!AC:AC) -> 46038 | GC8: =_xlfn.XLOOKUP(B8,QUERY!$C:$C,QUERY!AD:AD) -> 0 | GD8: =_xlfn.XLOOKUP(B8,QUERY!$C:$C,QUERY!AE:AE) -> 46038 | GE8: =_xlfn.XLOOKUP(B8,QUERY!$C:$C,QUERY!AF:AF) -> 1 | GF8: =_xlfn.XLOOKUP(B8,QUERY!$C:$C,QUERY!AG:AG) -> Es anterior | GG8: =_xlfn.XLOOKUP(B8,QUERY!$C:$C,QUERY!AH:AH) -> A1 | GH8: =_xlfn.XLOOKUP(B8,QUERY!$C:$C,QUERY!AI:AI) -> ZULEIMA PEREZ RUIZ | GI8: =_xlfn.XLOOKUP(B8,QUERY!$C:$C,QUERY!AJ:AJ) -> HLCUANR251131095 | GJ8: =_xlfn.XLOOKUP(B8,QUERY!$C:$C,QUERY!AK:AK) -> NULL | GK8: =_xlfn.XLOOKUP(B8,QUERY!$C:$C,QUERY!AL:AL) -> 6000072 | GL8: =_xlfn.XLOOKUP(B8,QUERY!$C:$C,QUERY!AM:AM) -> Importación | GM8: =_xlfn.XLOOKUP(B8,QUERY!$C:$C,QUERY!AN:AN) -> CEFA SAFE (MEDICAMENTO DOSIFICADO DE USO VETERINARIO) | GN8: =_xlfn.XLOOKUP(B8,QUERY!$C:$C,QUERY!AO:AO) -> SIN CLASIFICACION | GO8: =_xlfn.XLOOKUP(B8,QUERY!$C:$C,QUERY!AP:AP) -> 0 | GP8: =_xlfn.XLOOKUP(B8,QUERY!$C:$C,QUERY!AQ:AQ) -> Cargas de Importación | GQ8: =_xlfn.XLOOKUP(B8,QUERY!$C:$C,QUERY!AR:AR) -> INTERVET MEXICO SA DE CV | GR8: =_xlfn.XLOOKUP(B8,QUERY!$C:$C,QUERY!AS:AS) -> 0 | GS8: =_xlfn.XLOOKUP(B8,QUERY!$C:$C,QUERY!AT:AT) -> NINGUNO | GT8: =_xlfn.XLOOKUP(B8,QUERY!$C:$C,QUERY!AU:AU) -> 0 | GU8: =_xlfn.XLOOKUP(B8,QUERY!$C:$C,QUERY!AV:AV) -> NINGUNO | GV8: =_xlfn.XLOOKUP(B8,QUERY!$C:$C,QUERY!AW:AW) -> PRODUCTO TERMINADO | GW8: =_xlfn.XLOOKUP(B8,QUERY!$C:$C,QUERY!AX:AX) -> Verde | GX8: =_xlfn.XLOOKUP(B8,QUERY!$C:$C,QUERY!AY:AY) -> SUPER EXPRESS DE CARGA FEDERAL S.A. DE C.V. | GY8: =_xlfn.XLOOKUP(B8,QUERY!$C:$C,QUERY!AZ:AZ) -> 0 | GZ8: =_xlfn.XLOOKUP(B8,QUERY!$C:$C,QUERY!BA:BA) -> IME-T006 | HA8: =_xlfn.XLOOKUP(B8,QUERY!$C:$C,QUERY!BB:BB) -> IME850329RH2 | HB8: =_xlfn.XLOOKUP(B8,QUERY!$C:$C,QUERY!BC:BC) -> 0 | HC8: =_xlfn.XLOOKUP(B8,QUERY!$C:$C,QUERY!BD:BD) -> 0.99 | HD8: =_xlfn.XLOOKUP(B8,QUERY!$C:$C,QUERY!BE:BE) -> LOTE: A217A05,LOTE: A219A02,LOTE: A219A01,LOTE: A217A04,LOTE: A217A03,LOTE: H107A01,LOTES: J550A01, J607A01,LOTE: 5677101 | HE8: =_xlfn.XLOOKUP(B8,QUERY!$C:$C,QUERY!BF:BF) -> 90 | HF8: =_xlfn.XLOOKUP(B8,QUERY!$C:$C,QUERY!BG:BG) -> 952448.23, 2181141.30, 863532.00 | HG8: =_xlfn.XLOOKUP(B8,QUERY!$C:$C,QUERY!BH:BH) -> KILO,KILO,KILO,KILO,KILO,KILO,KILO,KILO | HH8: =_xlfn.XLOOKUP(B8,QUERY!$C:$C,QUERY!BI:BI) -> 0 | HI8: =_xlfn.XLOOKUP(B8,QUERY!$C:$C,QUERY!BJ:BJ) -> ALEMANIA (REPUBLICA FEDERAL DE),PAISES BAJOS (REINO DE LOS) (HOLANDA) | HJ8: =_xlfn.XLOOKUP(B8,QUERY!$C:$C,QUERY!BK:BK) -> PAISES BAJOS (REINO DE LOS) (HOLANDA) | HK8: =_xlfn.XLOOKUP(B8,QUERY!$C:$C,QUERY!BL:BL) -> DEU,ZYA | HL8: =_xlfn.XLOOKUP(B8,QUERY!$C:$C,QUERY!BM:BM) -> ZYA | HM8: =_xlfn.XLOOKUP(B8,QUERY!$C:$C,QUERY!BN:BN) -> 3997122 | HN8: =_xlfn.XLOOKUP(B8,QUERY!$C:$C,QUERY!BO:BO) -> 462.00 | HO8: =_xlfn.XLOOKUP(B8,QUERY!$C:$C,QUERY!BP:BP) -> NULL | HP8: =_xlfn.XLOOKUP(B8,QUERY!$C:$C,QUERY!BQ:BQ) -> NULL | HQ8: =_xlfn.XLOOKUP(B8,QUERY!$C:$C,QUERY!BR:BR) -> 139939.61 | HR8: =_xlfn.XLOOKUP(B8,QUERY!$C:$C,QUERY!BS:BS) -> 0 | HS8: =_xlfn.XLOOKUP(B8,QUERY!$C:$C,QUERY!BT:BT) -> 0 | HT8: =_xlfn.XLOOKUP(B8,QUERY!$C:$C,QUERY!A:A) -> VERACRUZ | HU8: =_xlfn.XLOOKUP(B8,QUERY!$C:$C,QUERY!B:B) -> MARÍTIMO VERACRUZ
A9: INTERVET MEXICO SA DE CV | B9: VER-25-1248 | C9: 3942 | D9: 6000072 | F9: Importación | G9: A1 | H9: 0 | I9: 0 | J9: 0 | K9: 0 | L9: 0 | M9: 0 | N9: 0 | O9: 0 | P9: 0 | Q9: 0 | R9: 430 | S9: CAAU4072651 | T9: 0 | U9: 0 | V9: 0 | W9: 0 | X9: 0 | Y9: 0 | Z9: 0 | AA9: CEFA SAFE (MEDICAMENTO DOSIFICADO DE USO VETERINARIO) | AC9: 370535 | AD9: 2486.8121 | AE9: 0 | AF9: 0 | AG9: 0 | AH9: 0 | AI9: 0 | AJ9: 0 | AK9: 0 | AL9: 0 | AM9: 0 | AN9: 0 | AP9: INTERVET INTERNATIONAL BV | AQ9: 210358509 | AR9: CIP | AS9: MXP | AT9: 0 | AU9: 0 | AV9: 0 | AW9: 30042099 | AX9: 0 | AY9: 149 | AZ9: 149 | BA9: CAJA | BC9: ZYA | BD9: ZYA | BK9: COVE267WH9PS7 | BL9: 0 | BM9: 0 | BN9: 0 | BO9: 0 | BP9: 0 | BQ9: 0 | BR9: 0 | BS9: 0 | BT9: 0 | BU9: 0 | BV9: 0 | BW9: 0 | BX9: 0 | BY9: 0 | BZ9: 0 | CA9: 0 | CB9: 0 | CC9: 0 | CD9: 0 | CE9: PAGADO | CF9: 0 | CG9: 0 | CH9: 0 | CI9: ZULEIMA PEREZ RUIZ | CJ9: ZULEIMA PEREZ RUIZ | CK9: =_xlfn.XLOOKUP($B$2,'BASE DE EXCEL'!C:C,'BASE DE EXCEL'!D:D,"NO HAY REFERENCIA") -> 470 | CL9: =_xlfn.XLOOKUP($B$2,'BASE DE EXCEL'!$C:$C,'BASE DE EXCEL'!F:F,"NO HAY REFERENCIA") -> 3 | CM9: =_xlfn.XLOOKUP($B$2,'BASE DE EXCEL'!$C:$C,'BASE DE EXCEL'!G:G,"NO HAY REFERENCIA") -> 46080 | CN9: =_xlfn.XLOOKUP($B$2,'BASE DE EXCEL'!$C:$C,'BASE DE EXCEL'!H:H,"NO HAY REFERENCIA") -> 46086 | CO9: =_xlfn.XLOOKUP($B$2,'BASE DE EXCEL'!$C:$C,'BASE DE EXCEL'!I:I,"NO HAY REFERENCIA") -> 4 | CP9: =_xlfn.XLOOKUP($B$2,'BASE DE EXCEL'!$C:$C,'BASE DE EXCEL'!J:J,"NO HAY REFERENCIA") -> 4 a 5 días | CQ9: =_xlfn.XLOOKUP($B$2,'BASE DE EXCEL'!$C:$C,'BASE DE EXCEL'!K:K,"NO HAY REFERENCIA") -> 46087 | CR9: =_xlfn.XLOOKUP($B$2,'BASE DE EXCEL'!$C:$C,'BASE DE EXCEL'!L:L,"NO HAY REFERENCIA") -> 5 | CS9: =_xlfn.XLOOKUP($B$2,'BASE DE EXCEL'!$C:$C,'BASE DE EXCEL'!M:M,"NO HAY REFERENCIA") -> 6 | CT9: =_xlfn.XLOOKUP($B$2,'BASE DE EXCEL'!$C:$C,'BASE DE EXCEL'!N:N,"NO HAY REFERENCIA") -> 6 a 10 días | CU9: =_xlfn.XLOOKUP($B$2,'BASE DE EXCEL'!$C:$C,'BASE DE EXCEL'!O:O,"NO HAY REFERENCIA") -> On Time | CV9: =_xlfn.XLOOKUP(B9,'BASE DE EXCEL'!$C:$C,'BASE DE EXCEL'!P:P,"NO HAY REFERENCIA") -> 4 a 5 días | CW9: =_xlfn.XLOOKUP(B9,'BASE DE EXCEL'!$C:$C,'BASE DE EXCEL'!Q:Q,"NO HAY REFERENCIA") -> 46031 | CX9: =_xlfn.XLOOKUP(B9,'BASE DE EXCEL'!$C:$C,'BASE DE EXCEL'!R:R,"NO HAY REFERENCIA") -> 5 | CY9: =_xlfn.XLOOKUP(B9,'BASE DE EXCEL'!$C:$C,'BASE DE EXCEL'!S:S,"NO HAY REFERENCIA") -> 4 a 5 días | CZ9: =_xlfn.XLOOKUP(B9,'BASE DE EXCEL'!$C:$C,'BASE DE EXCEL'!T:T,"NO HAY REFERENCIA") -> On Time | DA9: =_xlfn.XLOOKUP(B9,'BASE DE EXCEL'!$C:$C,'BASE DE EXCEL'!U:U,"NO HAY REFERENCIA") -> 6 | DB9: =_xlfn.XLOOKUP(B9,'BASE DE EXCEL'!$C:$C,'BASE DE EXCEL'!V:V,"NO HAY REFERENCIA") -> 4 a 5 días | DC9: =_xlfn.XLOOKUP(B9,'BASE DE EXCEL'!$C:$C,'BASE DE EXCEL'!W:W,"NO HAY REFERENCIA") -> 9 | DD9: =_xlfn.XLOOKUP(B9,'BASE DE EXCEL'!$C:$C,'BASE DE EXCEL'!X:X,"NO HAY REFERENCIA") -> 6 a 10 días | DE9: =_xlfn.XLOOKUP(B9,'BASE DE EXCEL'!$C:$C,'BASE DE EXCEL'!Y:Y,"NO HAY REFERENCIA") -> 1 | DF9: =_xlfn.XLOOKUP(B9,'BASE DE EXCEL'!$C:$C,'BASE DE EXCEL'!Z:Z,"NO HAY REFERENCIA") -> 1 día o menos | DG9: =_xlfn.XLOOKUP(B9,'BASE DE EXCEL'!$C:$C,'BASE DE EXCEL'!AA:AA,"NO HAY REFERENCIA") -> 4 | DH9: =_xlfn.XLOOKUP(B9,'BASE DE EXCEL'!$C:$C,'BASE DE EXCEL'!AB:AB,"NO HAY REFERENCIA") -> 1 | DI9: =_xlfn.XLOOKUP(B9,'BASE DE EXCEL'!$C:$C,'BASE DE EXCEL'!AC:AC,"NO HAY REFERENCIA") -> 1 día o menos | DJ9: =_xlfn.XLOOKUP(B9,'BASE DE EXCEL'!$C:$C,'BASE DE EXCEL'!AD:AD,"NO HAY REFERENCIA") -> 46038 | DK9: =_xlfn.XLOOKUP(B9,'BASE DE EXCEL'!$C:$C,'BASE DE EXCEL'!AE:AE,"NO HAY REFERENCIA") -> 7 | DL9: =_xlfn.XLOOKUP(B9,'BASE DE EXCEL'!$C:$C,'BASE DE EXCEL'!AF:AF,"NO HAY REFERENCIA") -> 5 | DM9: =_xlfn.XLOOKUP(B9,'BASE DE EXCEL'!$C:$C,'BASE DE EXCEL'!AG:AG,"NO HAY REFERENCIA") -> 46038 | DN9: =_xlfn.XLOOKUP(B9,'BASE DE EXCEL'!$C:$C,'BASE DE EXCEL'!AH:AH,"NO HAY REFERENCIA") -> 46038 | DO9: =_xlfn.XLOOKUP(B9,'BASE DE EXCEL'!$C:$C,'BASE DE EXCEL'!AI:AI,"NO HAY REFERENCIA") -> 0 | DP9: =_xlfn.XLOOKUP(B9,'BASE DE EXCEL'!$C:$C,'BASE DE EXCEL'!AJ:AJ,"NO HAY REFERENCIA") -> 6 a 10 días | DQ9: =_xlfn.XLOOKUP(B9,'BASE DE EXCEL'!$C:$C,'BASE DE EXCEL'!AK:AK,"NO HAY REFERENCIA") -> 46038 | DR9: =_xlfn.XLOOKUP(B9,'BASE DE EXCEL'!$C:$C,'BASE DE EXCEL'!AL:AL,"NO HAY REFERENCIA") -> 6 | DS9: =_xlfn.XLOOKUP(B9,'BASE DE EXCEL'!$C:$C,'BASE DE EXCEL'!AM:AM,"NO HAY REFERENCIA") -> 6 a 10 días | DT9: =_xlfn.XLOOKUP(B9,'BASE DE EXCEL'!$C:$C,'BASE DE EXCEL'!AN:AN,"NO HAY REFERENCIA") -> On Time | DU9: =_xlfn.XLOOKUP(B9,'BASE DE EXCEL'!$C:$C,'BASE DE EXCEL'!AO:AO,"NO HAY REFERENCIA") -> 1 | DV9: =_xlfn.XLOOKUP(B9,'BASE DE EXCEL'!$C:$C,'BASE DE EXCEL'!AP:AP,"NO HAY REFERENCIA") -> Es anterior | DW9: =_xlfn.XLOOKUP(B9,'BASE DE EXCEL'!$C:$C,'BASE DE EXCEL'!AQ:AQ,"NO HAY REFERENCIA") -> A1 | DX9: =_xlfn.XLOOKUP(B9,'BASE DE EXCEL'!$C:$C,'BASE DE EXCEL'!AR:AR,"NO HAY REFERENCIA") -> ZULEIMA PEREZ RUIZ | DY9: =_xlfn.XLOOKUP(B9,'BASE DE EXCEL'!$C:$C,'BASE DE EXCEL'!AS:AS,"NO HAY REFERENCIA") -> HLCUANR251131095 | DZ9: =_xlfn.XLOOKUP(B9,'BASE DE EXCEL'!$C:$C,'BASE DE EXCEL'!AT:AT,"NO HAY REFERENCIA") -> NULL | EA9: =_xlfn.XLOOKUP(B9,'BASE DE EXCEL'!$C:$C,'BASE DE EXCEL'!AU:AU,"NO HAY REFERENCIA") -> 6000072 | EB9: =_xlfn.XLOOKUP(B9,'BASE DE EXCEL'!$C:$C,'BASE DE EXCEL'!AV:AV,"NO HAY REFERENCIA") -> Importación | EC9: =_xlfn.XLOOKUP(B9,'BASE DE EXCEL'!$C:$C,'BASE DE EXCEL'!AW:AW,"NO HAY REFERENCIA") -> CEFA SAFE (MEDICAMENTO DOSIFICADO DE USO VETERINARIO) | ED9: =_xlfn.XLOOKUP(B9,'BASE DE EXCEL'!$C:$C,'BASE DE EXCEL'!AX:AX,"NO HAY REFERENCIA") -> SIN CLASIFICACION | EE9: =_xlfn.XLOOKUP(B9,'BASE DE EXCEL'!$C:$C,'BASE DE EXCEL'!AY:AY,"NO HAY REFERENCIA") -> 0 | EF9: =_xlfn.XLOOKUP(B9,'BASE DE EXCEL'!$C:$C,'BASE DE EXCEL'!AZ:AZ,"NO HAY REFERENCIA") -> Cargas de Importación | EG9: =_xlfn.XLOOKUP(B9,'BASE DE EXCEL'!$C:$C,'BASE DE EXCEL'!BA:BA,"NO HAY REFERENCIA") -> INTERVET MEXICO SA DE CV | EH9: =_xlfn.XLOOKUP(B9,'BASE DE EXCEL'!$C:$C,'BASE DE EXCEL'!BB:BB,"NO HAY REFERENCIA") -> 0 | EI9: =_xlfn.XLOOKUP(B9,'BASE DE EXCEL'!$C:$C,'BASE DE EXCEL'!BC:BC,"NO HAY REFERENCIA") -> NINGUNO | EJ9: =_xlfn.XLOOKUP(B9,'BASE DE EXCEL'!$C:$C,'BASE DE EXCEL'!BD:BD,"NO HAY REFERENCIA") -> 0 | EK9: =_xlfn.XLOOKUP(B9,'BASE DE EXCEL'!$C:$C,'BASE DE EXCEL'!BE:BE,"NO HAY REFERENCIA") -> NINGUNO | EL9: =_xlfn.XLOOKUP(B9,'BASE DE EXCEL'!$C:$C,'BASE DE EXCEL'!BF:BF,"NO HAY REFERENCIA") -> PRODUCTO TERMINADO | EM9: =_xlfn.XLOOKUP(B9,'BASE DE EXCEL'!$C:$C,'BASE DE EXCEL'!BG:BG,"NO HAY REFERENCIA") -> Verde | EN9: =_xlfn.XLOOKUP(B9,'BASE DE EXCEL'!$C:$C,'BASE DE EXCEL'!BH:BH,"NO HAY REFERENCIA") -> SUPER EXPRESS DE CARGA FEDERAL S.A. DE C.V. | EO9: =_xlfn.XLOOKUP(B9,'BASE DE EXCEL'!$C:$C,'BASE DE EXCEL'!BI:BI,"NO HAY REFERENCIA") -> 0 | EP9: =_xlfn.XLOOKUP(B9,'BASE DE EXCEL'!$C:$C,'BASE DE EXCEL'!BJ:BJ,"NO HAY REFERENCIA") -> IME-T006 | EQ9: =_xlfn.XLOOKUP(B9,'BASE DE EXCEL'!$C:$C,'BASE DE EXCEL'!BK:BK,"NO HAY REFERENCIA") -> IME850329RH2 | ER9: =_xlfn.XLOOKUP(B9,'BASE DE EXCEL'!$C:$C,'BASE DE EXCEL'!BL:BL,"NO HAY REFERENCIA") -> 0 | ES9: =_xlfn.XLOOKUP(B9,'BASE DE EXCEL'!$C:$C,'BASE DE EXCEL'!BM:BM,"NO HAY REFERENCIA") -> 00,99 | ET9: =_xlfn.XLOOKUP(B9,'BASE DE EXCEL'!$C:$C,'BASE DE EXCEL'!BN:BN,"NO HAY REFERENCIA") -> LOTE: A217A05,LOTE: A219A02,LOTE: A219A01,LOTE: A217A03,LOTE: H107A01,LOTES: J550A01, J607A01,LOTE: 5677101,LOTE: A217A04 | EU9: =_xlfn.XLOOKUP(B9,'BASE DE EXCEL'!$C:$C,'BASE DE EXCEL'!BO:BO,"NO HAY REFERENCIA") -> 90 | EV9: =_xlfn.XLOOKUP(B9,'BASE DE EXCEL'!$C:$C,'BASE DE EXCEL'!BP:BP,"NO HAY REFERENCIA") -> 952448.23, 2181141.30, 863532.00 | EW9: =_xlfn.XLOOKUP(B9,'BASE DE EXCEL'!$C:$C,'BASE DE EXCEL'!BQ:BQ,"NO HAY REFERENCIA") -> KILO,KILO,KILO,KILO,KILO,KILO,KILO,KILO | EX9: =_xlfn.XLOOKUP(B9,'BASE DE EXCEL'!$C:$C,'BASE DE EXCEL'!BR:BR,"NO HAY REFERENCIA") -> 0 | EY9: =_xlfn.XLOOKUP(B9,'BASE DE EXCEL'!$C:$C,'BASE DE EXCEL'!BS:BS,"NO HAY REFERENCIA") -> ALEMANIA (REPUBLICA FEDERAL DE),PAISES BAJOS (REINO DE LOS) (HOLANDA) | EZ9: =_xlfn.XLOOKUP(B9,'BASE DE EXCEL'!$C:$C,'BASE DE EXCEL'!BT:BT,"NO HAY REFERENCIA") -> PAISES BAJOS (REINO DE LOS) (HOLANDA) | FA9: =_xlfn.XLOOKUP(B9,'BASE DE EXCEL'!$C:$C,'BASE DE EXCEL'!BU:BU,"NO HAY REFERENCIA") -> DEU,ZYA | FB9: =_xlfn.XLOOKUP(B9,'BASE DE EXCEL'!$C:$C,'BASE DE EXCEL'!BV:BV,"NO HAY REFERENCIA") -> ZYA | FC9: =_xlfn.XLOOKUP(B9,QUERY!$C:$C,QUERY!D:D) -> 430 | FD9: =_xlfn.XLOOKUP(B9,QUERY!$C:$C,QUERY!E:E) -> 46029 | FE9: =_xlfn.XLOOKUP(B9,QUERY!$C:$C,QUERY!F:F) -> 1 | FF9: =_xlfn.XLOOKUP(B9,QUERY!$C:$C,QUERY!G:G) -> 46025 | FG9: =_xlfn.XLOOKUP(B9,QUERY!$C:$C,QUERY!H:H) -> 46029 | FH9: =_xlfn.XLOOKUP(B9,QUERY!$C:$C,QUERY!I:I) -> 2 | FI9: =_xlfn.XLOOKUP(B9,QUERY!$C:$C,QUERY!J:J) -> 2 a 3 días | FJ9: =_xlfn.XLOOKUP(B9,QUERY!$C:$C,QUERY!K:K) -> 46030 | FK9: =_xlfn.XLOOKUP(B9,QUERY!$C:$C,QUERY!L:L) -> 3 | FL9: =_xlfn.XLOOKUP(B9,QUERY!$C:$C,QUERY!M:M) -> 2 a 3 días | FM9: =_xlfn.XLOOKUP(B9,QUERY!$C:$C,QUERY!N:N) -> 1 | FN9: =_xlfn.XLOOKUP(B9,QUERY!$C:$C,QUERY!O:O) -> 1 día o menos | FO9: =_xlfn.XLOOKUP(B9,QUERY!$C:$C,QUERY!P:P) -> 1 | FP9: =_xlfn.XLOOKUP(B9,QUERY!$C:$C,QUERY!Q:Q) -> 1 | FQ9: =_xlfn.XLOOKUP(B9,QUERY!$C:$C,QUERY!R:R) -> 1 día o menos | FR9: =_xlfn.XLOOKUP(B9,QUERY!$C:$C,QUERY!S:S) -> 46031 | FS9: =_xlfn.XLOOKUP(B9,QUERY!$C:$C,QUERY!T:T) -> 4 | FT9: =_xlfn.XLOOKUP(B9,QUERY!$C:$C,QUERY!U:U) -> 4 a 5 días | FU9: =_xlfn.XLOOKUP(B9,QUERY!$C:$C,QUERY!V:V) -> 9 | FV9: =_xlfn.XLOOKUP(B9,QUERY!$C:$C,QUERY!W:W) -> 6 a 10 días | FW9: =_xlfn.XLOOKUP(B9,QUERY!$C:$C,QUERY!X:X) -> 46038 | FX9: =_xlfn.XLOOKUP(B9,QUERY!$C:$C,QUERY!Y:Y) -> 5 | FY9: =_xlfn.XLOOKUP(B9,QUERY!$C:$C,QUERY!Z:Z) -> 5 | FZ9: =_xlfn.XLOOKUP(B9,QUERY!$C:$C,QUERY!AA:AA) -> 6 a 10 días | GA9: =_xlfn.XLOOKUP(B9,QUERY!$C:$C,QUERY!AB:AB) -> 46038 | GB9: =_xlfn.XLOOKUP(B9,QUERY!$C:$C,QUERY!AC:AC) -> 46038 | GC9: =_xlfn.XLOOKUP(B9,QUERY!$C:$C,QUERY!AD:AD) -> 0 | GD9: =_xlfn.XLOOKUP(B9,QUERY!$C:$C,QUERY!AE:AE) -> 46038 | GE9: =_xlfn.XLOOKUP(B9,QUERY!$C:$C,QUERY!AF:AF) -> 1 | GF9: =_xlfn.XLOOKUP(B9,QUERY!$C:$C,QUERY!AG:AG) -> Es anterior | GG9: =_xlfn.XLOOKUP(B9,QUERY!$C:$C,QUERY!AH:AH) -> A1 | GH9: =_xlfn.XLOOKUP(B9,QUERY!$C:$C,QUERY!AI:AI) -> ZULEIMA PEREZ RUIZ | GI9: =_xlfn.XLOOKUP(B9,QUERY!$C:$C,QUERY!AJ:AJ) -> HLCUANR251131095 | GJ9: =_xlfn.XLOOKUP(B9,QUERY!$C:$C,QUERY!AK:AK) -> NULL | GK9: =_xlfn.XLOOKUP(B9,QUERY!$C:$C,QUERY!AL:AL) -> 6000072 | GL9: =_xlfn.XLOOKUP(B9,QUERY!$C:$C,QUERY!AM:AM) -> Importación | GM9: =_xlfn.XLOOKUP(B9,QUERY!$C:$C,QUERY!AN:AN) -> CEFA SAFE (MEDICAMENTO DOSIFICADO DE USO VETERINARIO) | GN9: =_xlfn.XLOOKUP(B9,QUERY!$C:$C,QUERY!AO:AO) -> SIN CLASIFICACION | GO9: =_xlfn.XLOOKUP(B9,QUERY!$C:$C,QUERY!AP:AP) -> 0 | GP9: =_xlfn.XLOOKUP(B9,QUERY!$C:$C,QUERY!AQ:AQ) -> Cargas de Importación | GQ9: =_xlfn.XLOOKUP(B9,QUERY!$C:$C,QUERY!AR:AR) -> INTERVET MEXICO SA DE CV | GR9: =_xlfn.XLOOKUP(B9,QUERY!$C:$C,QUERY!AS:AS) -> 0 | GS9: =_xlfn.XLOOKUP(B9,QUERY!$C:$C,QUERY!AT:AT) -> NINGUNO | GT9: =_xlfn.XLOOKUP(B9,QUERY!$C:$C,QUERY!AU:AU) -> 0 | GU9: =_xlfn.XLOOKUP(B9,QUERY!$C:$C,QUERY!AV:AV) -> NINGUNO | GV9: =_xlfn.XLOOKUP(B9,QUERY!$C:$C,QUERY!AW:AW) -> PRODUCTO TERMINADO | GW9: =_xlfn.XLOOKUP(B9,QUERY!$C:$C,QUERY!AX:AX) -> Verde | GX9: =_xlfn.XLOOKUP(B9,QUERY!$C:$C,QUERY!AY:AY) -> SUPER EXPRESS DE CARGA FEDERAL S.A. DE C.V. | GY9: =_xlfn.XLOOKUP(B9,QUERY!$C:$C,QUERY!AZ:AZ) -> 0 | GZ9: =_xlfn.XLOOKUP(B9,QUERY!$C:$C,QUERY!BA:BA) -> IME-T006 | HA9: =_xlfn.XLOOKUP(B9,QUERY!$C:$C,QUERY!BB:BB) -> IME850329RH2 | HB9: =_xlfn.XLOOKUP(B9,QUERY!$C:$C,QUERY!BC:BC) -> 0 | HC9: =_xlfn.XLOOKUP(B9,QUERY!$C:$C,QUERY!BD:BD) -> 0.99 | HD9: =_xlfn.XLOOKUP(B9,QUERY!$C:$C,QUERY!BE:BE) -> LOTE: A217A05,LOTE: A219A02,LOTE: A219A01,LOTE: A217A04,LOTE: A217A03,LOTE: H107A01,LOTES: J550A01, J607A01,LOTE: 5677101 | HE9: =_xlfn.XLOOKUP(B9,QUERY!$C:$C,QUERY!BF:BF) -> 90 | HF9: =_xlfn.XLOOKUP(B9,QUERY!$C:$C,QUERY!BG:BG) -> 952448.23, 2181141.30, 863532.00 | HG9: =_xlfn.XLOOKUP(B9,QUERY!$C:$C,QUERY!BH:BH) -> KILO,KILO,KILO,KILO,KILO,KILO,KILO,KILO | HH9: =_xlfn.XLOOKUP(B9,QUERY!$C:$C,QUERY!BI:BI) -> 0 | HI9: =_xlfn.XLOOKUP(B9,QUERY!$C:$C,QUERY!BJ:BJ) -> ALEMANIA (REPUBLICA FEDERAL DE),PAISES BAJOS (REINO DE LOS) (HOLANDA) | HJ9: =_xlfn.XLOOKUP(B9,QUERY!$C:$C,QUERY!BK:BK) -> PAISES BAJOS (REINO DE LOS) (HOLANDA) | HK9: =_xlfn.XLOOKUP(B9,QUERY!$C:$C,QUERY!BL:BL) -> DEU,ZYA | HL9: =_xlfn.XLOOKUP(B9,QUERY!$C:$C,QUERY!BM:BM) -> ZYA | HM9: =_xlfn.XLOOKUP(B9,QUERY!$C:$C,QUERY!BN:BN) -> 3997122 | HN9: =_xlfn.XLOOKUP(B9,QUERY!$C:$C,QUERY!BO:BO) -> 462.00 | HO9: =_xlfn.XLOOKUP(B9,QUERY!$C:$C,QUERY!BP:BP) -> NULL | HP9: =_xlfn.XLOOKUP(B9,QUERY!$C:$C,QUERY!BQ:BQ) -> NULL | HQ9: =_xlfn.XLOOKUP(B9,QUERY!$C:$C,QUERY!BR:BR) -> 139939.61 | HR9: =_xlfn.XLOOKUP(B9,QUERY!$C:$C,QUERY!BS:BS) -> 0 | HS9: =_xlfn.XLOOKUP(B9,QUERY!$C:$C,QUERY!BT:BT) -> 0 | HT9: =_xlfn.XLOOKUP(B9,QUERY!$C:$C,QUERY!A:A) -> VERACRUZ | HU9: =_xlfn.XLOOKUP(B9,QUERY!$C:$C,QUERY!B:B) -> MARÍTIMO VERACRUZ
A10: INTERVET MEXICO SA DE CV | B10: VER-25-1248 | C10: 3942 | D10: 6000072 | F10: Importación | G10: A1 | H10: 0 | I10: 0 | J10: 0 | K10: 0 | L10: 0 | M10: 0 | N10: 0 | O10: 0 | P10: 0 | Q10: 0 | R10: 430 | S10: CAAU4072651 | T10: 0 | U10: 0 | V10: 0 | W10: 0 | X10: 0 | Y10: 0 | Z10: 0 | AA10: DILUVAC FORTE (MEDICAMENTO DOSIFICADO DE USO VETERINARIO) | AC10: 1425144 | AD10: 748.5 | AE10: 0 | AF10: 0 | AG10: 0 | AH10: 0 | AI10: 0 | AJ10: 0 | AK10: 0 | AL10: 0 | AM10: 0 | AN10: 0 | AP10: INTERVET INTERNATIONAL BV | AQ10: 210358509 | AR10: CIP | AS10: MXP | AT10: 0 | AU10: 0 | AV10: 0 | AW10: 30049099 | AX10: 99 | AY10: 1904 | AZ10: 1904 | BA10: CAJA | BC10: ZYA | BD10: ZYA | BK10: COVE267WH9PS7 | BL10: 0 | BM10: 0 | BN10: 0 | BO10: 0 | BP10: 0 | BQ10: 0 | BR10: 0 | BS10: 0 | BT10: 0 | BU10: 0 | BV10: 0 | BW10: 0 | BX10: 0 | BY10: 0 | BZ10: 0 | CA10: 0 | CB10: 0 | CC10: 0 | CD10: 0 | CE10: PAGADO | CF10: 0 | CG10: 0 | CH10: 0 | CI10: ZULEIMA PEREZ RUIZ | CJ10: ZULEIMA PEREZ RUIZ | CK10: =_xlfn.XLOOKUP($B$2,'BASE DE EXCEL'!C:C,'BASE DE EXCEL'!D:D,"NO HAY REFERENCIA") -> 470 | CL10: =_xlfn.XLOOKUP($B$2,'BASE DE EXCEL'!$C:$C,'BASE DE EXCEL'!F:F,"NO HAY REFERENCIA") -> 3 | CM10: =_xlfn.XLOOKUP($B$2,'BASE DE EXCEL'!$C:$C,'BASE DE EXCEL'!G:G,"NO HAY REFERENCIA") -> 46080 | CN10: =_xlfn.XLOOKUP($B$2,'BASE DE EXCEL'!$C:$C,'BASE DE EXCEL'!H:H,"NO HAY REFERENCIA") -> 46086 | CO10: =_xlfn.XLOOKUP($B$2,'BASE DE EXCEL'!$C:$C,'BASE DE EXCEL'!I:I,"NO HAY REFERENCIA") -> 4 | CP10: =_xlfn.XLOOKUP($B$2,'BASE DE EXCEL'!$C:$C,'BASE DE EXCEL'!J:J,"NO HAY REFERENCIA") -> 4 a 5 días | CQ10: =_xlfn.XLOOKUP($B$2,'BASE DE EXCEL'!$C:$C,'BASE DE EXCEL'!K:K,"NO HAY REFERENCIA") -> 46087 | CR10: =_xlfn.XLOOKUP($B$2,'BASE DE EXCEL'!$C:$C,'BASE DE EXCEL'!L:L,"NO HAY REFERENCIA") -> 5 | CS10: =_xlfn.XLOOKUP($B$2,'BASE DE EXCEL'!$C:$C,'BASE DE EXCEL'!M:M,"NO HAY REFERENCIA") -> 6 | CT10: =_xlfn.XLOOKUP($B$2,'BASE DE EXCEL'!$C:$C,'BASE DE EXCEL'!N:N,"NO HAY REFERENCIA") -> 6 a 10 días | CU10: =_xlfn.XLOOKUP($B$2,'BASE DE EXCEL'!$C:$C,'BASE DE EXCEL'!O:O,"NO HAY REFERENCIA") -> On Time | CV10: =_xlfn.XLOOKUP(B10,'BASE DE EXCEL'!$C:$C,'BASE DE EXCEL'!P:P,"NO HAY REFERENCIA") -> 4 a 5 días | CW10: =_xlfn.XLOOKUP(B10,'BASE DE EXCEL'!$C:$C,'BASE DE EXCEL'!Q:Q,"NO HAY REFERENCIA") -> 46031 | CX10: =_xlfn.XLOOKUP(B10,'BASE DE EXCEL'!$C:$C,'BASE DE EXCEL'!R:R,"NO HAY REFERENCIA") -> 5 | CY10: =_xlfn.XLOOKUP(B10,'BASE DE EXCEL'!$C:$C,'BASE DE EXCEL'!S:S,"NO HAY REFERENCIA") -> 4 a 5 días | CZ10: =_xlfn.XLOOKUP(B10,'BASE DE EXCEL'!$C:$C,'BASE DE EXCEL'!T:T,"NO HAY REFERENCIA") -> On Time | DA10: =_xlfn.XLOOKUP(B10,'BASE DE EXCEL'!$C:$C,'BASE DE EXCEL'!U:U,"NO HAY REFERENCIA") -> 6 | DB10: =_xlfn.XLOOKUP(B10,'BASE DE EXCEL'!$C:$C,'BASE DE EXCEL'!V:V,"NO HAY REFERENCIA") -> 4 a 5 días | DC10: =_xlfn.XLOOKUP(B10,'BASE DE EXCEL'!$C:$C,'BASE DE EXCEL'!W:W,"NO HAY REFERENCIA") -> 9 | DD10: =_xlfn.XLOOKUP(B10,'BASE DE EXCEL'!$C:$C,'BASE DE EXCEL'!X:X,"NO HAY REFERENCIA") -> 6 a 10 días | DE10: =_xlfn.XLOOKUP(B10,'BASE DE EXCEL'!$C:$C,'BASE DE EXCEL'!Y:Y,"NO HAY REFERENCIA") -> 1 | DF10: =_xlfn.XLOOKUP(B10,'BASE DE EXCEL'!$C:$C,'BASE DE EXCEL'!Z:Z,"NO HAY REFERENCIA") -> 1 día o menos | DG10: =_xlfn.XLOOKUP(B10,'BASE DE EXCEL'!$C:$C,'BASE DE EXCEL'!AA:AA,"NO HAY REFERENCIA") -> 4 | DH10: =_xlfn.XLOOKUP(B10,'BASE DE EXCEL'!$C:$C,'BASE DE EXCEL'!AB:AB,"NO HAY REFERENCIA") -> 1 | DI10: =_xlfn.XLOOKUP(B10,'BASE DE EXCEL'!$C:$C,'BASE DE EXCEL'!AC:AC,"NO HAY REFERENCIA") -> 1 día o menos | DJ10: =_xlfn.XLOOKUP(B10,'BASE DE EXCEL'!$C:$C,'BASE DE EXCEL'!AD:AD,"NO HAY REFERENCIA") -> 46038 | DK10: =_xlfn.XLOOKUP(B10,'BASE DE EXCEL'!$C:$C,'BASE DE EXCEL'!AE:AE,"NO HAY REFERENCIA") -> 7 | DL10: =_xlfn.XLOOKUP(B10,'BASE DE EXCEL'!$C:$C,'BASE DE EXCEL'!AF:AF,"NO HAY REFERENCIA") -> 5 | DM10: =_xlfn.XLOOKUP(B10,'BASE DE EXCEL'!$C:$C,'BASE DE EXCEL'!AG:AG,"NO HAY REFERENCIA") -> 46038 | DN10: =_xlfn.XLOOKUP(B10,'BASE DE EXCEL'!$C:$C,'BASE DE EXCEL'!AH:AH,"NO HAY REFERENCIA") -> 46038 | DO10: =_xlfn.XLOOKUP(B10,'BASE DE EXCEL'!$C:$C,'BASE DE EXCEL'!AI:AI,"NO HAY REFERENCIA") -> 0 | DP10: =_xlfn.XLOOKUP(B10,'BASE DE EXCEL'!$C:$C,'BASE DE EXCEL'!AJ:AJ,"NO HAY REFERENCIA") -> 6 a 10 días | DQ10: =_xlfn.XLOOKUP(B10,'BASE DE EXCEL'!$C:$C,'BASE DE EXCEL'!AK:AK,"NO HAY REFERENCIA") -> 46038 | DR10: =_xlfn.XLOOKUP(B10,'BASE DE EXCEL'!$C:$C,'BASE DE EXCEL'!AL:AL,"NO HAY REFERENCIA") -> 6 | DS10: =_xlfn.XLOOKUP(B10,'BASE DE EXCEL'!$C:$C,'BASE DE EXCEL'!AM:AM,"NO HAY REFERENCIA") -> 6 a 10 días | DT10: =_xlfn.XLOOKUP(B10,'BASE DE EXCEL'!$C:$C,'BASE DE EXCEL'!AN:AN,"NO HAY REFERENCIA") -> On Time | DU10: =_xlfn.XLOOKUP(B10,'BASE DE EXCEL'!$C:$C,'BASE DE EXCEL'!AO:AO,"NO HAY REFERENCIA") -> 1 | DV10: =_xlfn.XLOOKUP(B10,'BASE DE EXCEL'!$C:$C,'BASE DE EXCEL'!AP:AP,"NO HAY REFERENCIA") -> Es anterior | DW10: =_xlfn.XLOOKUP(B10,'BASE DE EXCEL'!$C:$C,'BASE DE EXCEL'!AQ:AQ,"NO HAY REFERENCIA") -> A1 | DX10: =_xlfn.XLOOKUP(B10,'BASE DE EXCEL'!$C:$C,'BASE DE EXCEL'!AR:AR,"NO HAY REFERENCIA") -> ZULEIMA PEREZ RUIZ | DY10: =_xlfn.XLOOKUP(B10,'BASE DE EXCEL'!$C:$C,'BASE DE EXCEL'!AS:AS,"NO HAY REFERENCIA") -> HLCUANR251131095 | DZ10: =_xlfn.XLOOKUP(B10,'BASE DE EXCEL'!$C:$C,'BASE DE EXCEL'!AT:AT,"NO HAY REFERENCIA") -> NULL | EA10: =_xlfn.XLOOKUP(B10,'BASE DE EXCEL'!$C:$C,'BASE DE EXCEL'!AU:AU,"NO HAY REFERENCIA") -> 6000072 | EB10: =_xlfn.XLOOKUP(B10,'BASE DE EXCEL'!$C:$C,'BASE DE EXCEL'!AV:AV,"NO HAY REFERENCIA") -> Importación | EC10: =_xlfn.XLOOKUP(B10,'BASE DE EXCEL'!$C:$C,'BASE DE EXCEL'!AW:AW,"NO HAY REFERENCIA") -> CEFA SAFE (MEDICAMENTO DOSIFICADO DE USO VETERINARIO) | ED10: =_xlfn.XLOOKUP(B10,'BASE DE EXCEL'!$C:$C,'BASE DE EXCEL'!AX:AX,"NO HAY REFERENCIA") -> SIN CLASIFICACION | EE10: =_xlfn.XLOOKUP(B10,'BASE DE EXCEL'!$C:$C,'BASE DE EXCEL'!AY:AY,"NO HAY REFERENCIA") -> 0 | EF10: =_xlfn.XLOOKUP(B10,'BASE DE EXCEL'!$C:$C,'BASE DE EXCEL'!AZ:AZ,"NO HAY REFERENCIA") -> Cargas de Importación | EG10: =_xlfn.XLOOKUP(B10,'BASE DE EXCEL'!$C:$C,'BASE DE EXCEL'!BA:BA,"NO HAY REFERENCIA") -> INTERVET MEXICO SA DE CV | EH10: =_xlfn.XLOOKUP(B10,'BASE DE EXCEL'!$C:$C,'BASE DE EXCEL'!BB:BB,"NO HAY REFERENCIA") -> 0 | EI10: =_xlfn.XLOOKUP(B10,'BASE DE EXCEL'!$C:$C,'BASE DE EXCEL'!BC:BC,"NO HAY REFERENCIA") -> NINGUNO | EJ10: =_xlfn.XLOOKUP(B10,'BASE DE EXCEL'!$C:$C,'BASE DE EXCEL'!BD:BD,"NO HAY REFERENCIA") -> 0 | EK10: =_xlfn.XLOOKUP(B10,'BASE DE EXCEL'!$C:$C,'BASE DE EXCEL'!BE:BE,"NO HAY REFERENCIA") -> NINGUNO | EL10: =_xlfn.XLOOKUP(B10,'BASE DE EXCEL'!$C:$C,'BASE DE EXCEL'!BF:BF,"NO HAY REFERENCIA") -> PRODUCTO TERMINADO | EM10: =_xlfn.XLOOKUP(B10,'BASE DE EXCEL'!$C:$C,'BASE DE EXCEL'!BG:BG,"NO HAY REFERENCIA") -> Verde | EN10: =_xlfn.XLOOKUP(B10,'BASE DE EXCEL'!$C:$C,'BASE DE EXCEL'!BH:BH,"NO HAY REFERENCIA") -> SUPER EXPRESS DE CARGA FEDERAL S.A. DE C.V. | EO10: =_xlfn.XLOOKUP(B10,'BASE DE EXCEL'!$C:$C,'BASE DE EXCEL'!BI:BI,"NO HAY REFERENCIA") -> 0 | EP10: =_xlfn.XLOOKUP(B10,'BASE DE EXCEL'!$C:$C,'BASE DE EXCEL'!BJ:BJ,"NO HAY REFERENCIA") -> IME-T006 | EQ10: =_xlfn.XLOOKUP(B10,'BASE DE EXCEL'!$C:$C,'BASE DE EXCEL'!BK:BK,"NO HAY REFERENCIA") -> IME850329RH2 | ER10: =_xlfn.XLOOKUP(B10,'BASE DE EXCEL'!$C:$C,'BASE DE EXCEL'!BL:BL,"NO HAY REFERENCIA") -> 0 | ES10: =_xlfn.XLOOKUP(B10,'BASE DE EXCEL'!$C:$C,'BASE DE EXCEL'!BM:BM,"NO HAY REFERENCIA") -> 00,99 | ET10: =_xlfn.XLOOKUP(B10,'BASE DE EXCEL'!$C:$C,'BASE DE EXCEL'!BN:BN,"NO HAY REFERENCIA") -> LOTE: A217A05,LOTE: A219A02,LOTE: A219A01,LOTE: A217A03,LOTE: H107A01,LOTES: J550A01, J607A01,LOTE: 5677101,LOTE: A217A04 | EU10: =_xlfn.XLOOKUP(B10,'BASE DE EXCEL'!$C:$C,'BASE DE EXCEL'!BO:BO,"NO HAY REFERENCIA") -> 90 | EV10: =_xlfn.XLOOKUP(B10,'BASE DE EXCEL'!$C:$C,'BASE DE EXCEL'!BP:BP,"NO HAY REFERENCIA") -> 952448.23, 2181141.30, 863532.00 | EW10: =_xlfn.XLOOKUP(B10,'BASE DE EXCEL'!$C:$C,'BASE DE EXCEL'!BQ:BQ,"NO HAY REFERENCIA") -> KILO,KILO,KILO,KILO,KILO,KILO,KILO,KILO | EX10: =_xlfn.XLOOKUP(B10,'BASE DE EXCEL'!$C:$C,'BASE DE EXCEL'!BR:BR,"NO HAY REFERENCIA") -> 0 | EY10: =_xlfn.XLOOKUP(B10,'BASE DE EXCEL'!$C:$C,'BASE DE EXCEL'!BS:BS,"NO HAY REFERENCIA") -> ALEMANIA (REPUBLICA FEDERAL DE),PAISES BAJOS (REINO DE LOS) (HOLANDA) | EZ10: =_xlfn.XLOOKUP(B10,'BASE DE EXCEL'!$C:$C,'BASE DE EXCEL'!BT:BT,"NO HAY REFERENCIA") -> PAISES BAJOS (REINO DE LOS) (HOLANDA) | FA10: =_xlfn.XLOOKUP(B10,'BASE DE EXCEL'!$C:$C,'BASE DE EXCEL'!BU:BU,"NO HAY REFERENCIA") -> DEU,ZYA | FB10: =_xlfn.XLOOKUP(B10,'BASE DE EXCEL'!$C:$C,'BASE DE EXCEL'!BV:BV,"NO HAY REFERENCIA") -> ZYA | FC10: =_xlfn.XLOOKUP(B10,QUERY!$C:$C,QUERY!D:D) -> 430 | FD10: =_xlfn.XLOOKUP(B10,QUERY!$C:$C,QUERY!E:E) -> 46029 | FE10: =_xlfn.XLOOKUP(B10,QUERY!$C:$C,QUERY!F:F) -> 1 | FF10: =_xlfn.XLOOKUP(B10,QUERY!$C:$C,QUERY!G:G) -> 46025 | FG10: =_xlfn.XLOOKUP(B10,QUERY!$C:$C,QUERY!H:H) -> 46029 | FH10: =_xlfn.XLOOKUP(B10,QUERY!$C:$C,QUERY!I:I) -> 2 | FI10: =_xlfn.XLOOKUP(B10,QUERY!$C:$C,QUERY!J:J) -> 2 a 3 días | FJ10: =_xlfn.XLOOKUP(B10,QUERY!$C:$C,QUERY!K:K) -> 46030 | FK10: =_xlfn.XLOOKUP(B10,QUERY!$C:$C,QUERY!L:L) -> 3 | FL10: =_xlfn.XLOOKUP(B10,QUERY!$C:$C,QUERY!M:M) -> 2 a 3 días | FM10: =_xlfn.XLOOKUP(B10,QUERY!$C:$C,QUERY!N:N) -> 1 | FN10: =_xlfn.XLOOKUP(B10,QUERY!$C:$C,QUERY!O:O) -> 1 día o menos | FO10: =_xlfn.XLOOKUP(B10,QUERY!$C:$C,QUERY!P:P) -> 1 | FP10: =_xlfn.XLOOKUP(B10,QUERY!$C:$C,QUERY!Q:Q) -> 1 | FQ10: =_xlfn.XLOOKUP(B10,QUERY!$C:$C,QUERY!R:R) -> 1 día o menos | FR10: =_xlfn.XLOOKUP(B10,QUERY!$C:$C,QUERY!S:S) -> 46031 | FS10: =_xlfn.XLOOKUP(B10,QUERY!$C:$C,QUERY!T:T) -> 4 | FT10: =_xlfn.XLOOKUP(B10,QUERY!$C:$C,QUERY!U:U) -> 4 a 5 días | FU10: =_xlfn.XLOOKUP(B10,QUERY!$C:$C,QUERY!V:V) -> 9 | FV10: =_xlfn.XLOOKUP(B10,QUERY!$C:$C,QUERY!W:W) -> 6 a 10 días | FW10: =_xlfn.XLOOKUP(B10,QUERY!$C:$C,QUERY!X:X) -> 46038 | FX10: =_xlfn.XLOOKUP(B10,QUERY!$C:$C,QUERY!Y:Y) -> 5 | FY10: =_xlfn.XLOOKUP(B10,QUERY!$C:$C,QUERY!Z:Z) -> 5 | FZ10: =_xlfn.XLOOKUP(B10,QUERY!$C:$C,QUERY!AA:AA) -> 6 a 10 días | GA10: =_xlfn.XLOOKUP(B10,QUERY!$C:$C,QUERY!AB:AB) -> 46038 | GB10: =_xlfn.XLOOKUP(B10,QUERY!$C:$C,QUERY!AC:AC) -> 46038 | GC10: =_xlfn.XLOOKUP(B10,QUERY!$C:$C,QUERY!AD:AD) -> 0 | GD10: =_xlfn.XLOOKUP(B10,QUERY!$C:$C,QUERY!AE:AE) -> 46038 | GE10: =_xlfn.XLOOKUP(B10,QUERY!$C:$C,QUERY!AF:AF) -> 1 | GF10: =_xlfn.XLOOKUP(B10,QUERY!$C:$C,QUERY!AG:AG) -> Es anterior | GG10: =_xlfn.XLOOKUP(B10,QUERY!$C:$C,QUERY!AH:AH) -> A1 | GH10: =_xlfn.XLOOKUP(B10,QUERY!$C:$C,QUERY!AI:AI) -> ZULEIMA PEREZ RUIZ | GI10: =_xlfn.XLOOKUP(B10,QUERY!$C:$C,QUERY!AJ:AJ) -> HLCUANR251131095 | GJ10: =_xlfn.XLOOKUP(B10,QUERY!$C:$C,QUERY!AK:AK) -> NULL | GK10: =_xlfn.XLOOKUP(B10,QUERY!$C:$C,QUERY!AL:AL) -> 6000072 | GL10: =_xlfn.XLOOKUP(B10,QUERY!$C:$C,QUERY!AM:AM) -> Importación | GM10: =_xlfn.XLOOKUP(B10,QUERY!$C:$C,QUERY!AN:AN) -> CEFA SAFE (MEDICAMENTO DOSIFICADO DE USO VETERINARIO) | GN10: =_xlfn.XLOOKUP(B10,QUERY!$C:$C,QUERY!AO:AO) -> SIN CLASIFICACION | GO10: =_xlfn.XLOOKUP(B10,QUERY!$C:$C,QUERY!AP:AP) -> 0 | GP10: =_xlfn.XLOOKUP(B10,QUERY!$C:$C,QUERY!AQ:AQ) -> Cargas de Importación | GQ10: =_xlfn.XLOOKUP(B10,QUERY!$C:$C,QUERY!AR:AR) -> INTERVET MEXICO SA DE CV | GR10: =_xlfn.XLOOKUP(B10,QUERY!$C:$C,QUERY!AS:AS) -> 0 | GS10: =_xlfn.XLOOKUP(B10,QUERY!$C:$C,QUERY!AT:AT) -> NINGUNO | GT10: =_xlfn.XLOOKUP(B10,QUERY!$C:$C,QUERY!AU:AU) -> 0 | GU10: =_xlfn.XLOOKUP(B10,QUERY!$C:$C,QUERY!AV:AV) -> NINGUNO | GV10: =_xlfn.XLOOKUP(B10,QUERY!$C:$C,QUERY!AW:AW) -> PRODUCTO TERMINADO | GW10: =_xlfn.XLOOKUP(B10,QUERY!$C:$C,QUERY!AX:AX) -> Verde | GX10: =_xlfn.XLOOKUP(B10,QUERY!$C:$C,QUERY!AY:AY) -> SUPER EXPRESS DE CARGA FEDERAL S.A. DE C.V. | GY10: =_xlfn.XLOOKUP(B10,QUERY!$C:$C,QUERY!AZ:AZ) -> 0 | GZ10: =_xlfn.XLOOKUP(B10,QUERY!$C:$C,QUERY!BA:BA) -> IME-T006 | HA10: =_xlfn.XLOOKUP(B10,QUERY!$C:$C,QUERY!BB:BB) -> IME850329RH2 | HB10: =_xlfn.XLOOKUP(B10,QUERY!$C:$C,QUERY!BC:BC) -> 0 | HC10: =_xlfn.XLOOKUP(B10,QUERY!$C:$C,QUERY!BD:BD) -> 0.99 | HD10: =_xlfn.XLOOKUP(B10,QUERY!$C:$C,QUERY!BE:BE) -> LOTE: A217A05,LOTE: A219A02,LOTE: A219A01,LOTE: A217A04,LOTE: A217A03,LOTE: H107A01,LOTES: J550A01, J607A01,LOTE: 5677101 | HE10: =_xlfn.XLOOKUP(B10,QUERY!$C:$C,QUERY!BF:BF) -> 90 | HF10: =_xlfn.XLOOKUP(B10,QUERY!$C:$C,QUERY!BG:BG) -> 952448.23, 2181141.30, 863532.00 | HG10: =_xlfn.XLOOKUP(B10,QUERY!$C:$C,QUERY!BH:BH) -> KILO,KILO,KILO,KILO,KILO,KILO,KILO,KILO | HH10: =_xlfn.XLOOKUP(B10,QUERY!$C:$C,QUERY!BI:BI) -> 0 | HI10: =_xlfn.XLOOKUP(B10,QUERY!$C:$C,QUERY!BJ:BJ) -> ALEMANIA (REPUBLICA FEDERAL DE),PAISES BAJOS (REINO DE LOS) (HOLANDA) | HJ10: =_xlfn.XLOOKUP(B10,QUERY!$C:$C,QUERY!BK:BK) -> PAISES BAJOS (REINO DE LOS) (HOLANDA) | HK10: =_xlfn.XLOOKUP(B10,QUERY!$C:$C,QUERY!BL:BL) -> DEU,ZYA | HL10: =_xlfn.XLOOKUP(B10,QUERY!$C:$C,QUERY!BM:BM) -> ZYA | HM10: =_xlfn.XLOOKUP(B10,QUERY!$C:$C,QUERY!BN:BN) -> 3997122 | HN10: =_xlfn.XLOOKUP(B10,QUERY!$C:$C,QUERY!BO:BO) -> 462.00 | HO10: =_xlfn.XLOOKUP(B10,QUERY!$C:$C,QUERY!BP:BP) -> NULL | HP10: =_xlfn.XLOOKUP(B10,QUERY!$C:$C,QUERY!BQ:BQ) -> NULL | HQ10: =_xlfn.XLOOKUP(B10,QUERY!$C:$C,QUERY!BR:BR) -> 139939.61 | HR10: =_xlfn.XLOOKUP(B10,QUERY!$C:$C,QUERY!BS:BS) -> 0 | HS10: =_xlfn.XLOOKUP(B10,QUERY!$C:$C,QUERY!BT:BT) -> 0 | HT10: =_xlfn.XLOOKUP(B10,QUERY!$C:$C,QUERY!A:A) -> VERACRUZ | HU10: =_xlfn.XLOOKUP(B10,QUERY!$C:$C,QUERY!B:B) -> MARÍTIMO VERACRUZ
A11: INTERVET MEXICO SA DE CV | B11: VER-25-1248 | C11: 3942 | D11: 6000072 | F11: Importación | G11: A1 | H11: 0 | I11: 0 | J11: 0 | K11: 0 | L11: 0 | M11: 0 | N11: 0 | O11: 0 | P11: 0 | Q11: 0 | R11: 430 | S11: CAAU4072651 | T11: 0 | U11: 0 | V11: 0 | W11: 0 | X11: 0 | Y11: 0 | Z11: 0 | AA11: SOLVENS OCULO NASAL (MEDICAMENTO DOSIFICADO DE USO VETERINARIO) | AC11: 203925 | AD11: 325.23923 | AE11: 0 | AF11: 0 | AG11: 0 | AH11: 0 | AI11: 0 | AJ11: 0 | AK11: 0 | AL11: 0 | AM11: 0 | AN11: 0 | AP11: INTERVET INTERNATIONAL BV | AQ11: 210358509 | AR11: CIP | AS11: MXP | AT11: 0 | AU11: 0 | AV11: 0 | AW11: 30049099 | AX11: 99 | AY11: 627 | AZ11: 627 | BA11: CAJA | BC11: ZYA | BD11: ZYA | BK11: COVE267WH9PS7 | BL11: 0 | BM11: 0 | BN11: 0 | BO11: 0 | BP11: 0 | BQ11: 0 | BR11: 0 | BS11: 0 | BT11: 0 | BU11: 0 | BV11: 0 | BW11: 0 | BX11: 0 | BY11: 0 | BZ11: 0 | CA11: 0 | CB11: 0 | CC11: 0 | CD11: 0 | CE11: PAGADO | CF11: 0 | CG11: 0 | CH11: 0 | CI11: ZULEIMA PEREZ RUIZ | CJ11: ZULEIMA PEREZ RUIZ | CK11: =_xlfn.XLOOKUP($B$2,'BASE DE EXCEL'!C:C,'BASE DE EXCEL'!D:D,"NO HAY REFERENCIA") -> 470 | CL11: =_xlfn.XLOOKUP($B$2,'BASE DE EXCEL'!$C:$C,'BASE DE EXCEL'!F:F,"NO HAY REFERENCIA") -> 3 | CM11: =_xlfn.XLOOKUP($B$2,'BASE DE EXCEL'!$C:$C,'BASE DE EXCEL'!G:G,"NO HAY REFERENCIA") -> 46080 | CN11: =_xlfn.XLOOKUP($B$2,'BASE DE EXCEL'!$C:$C,'BASE DE EXCEL'!H:H,"NO HAY REFERENCIA") -> 46086 | CO11: =_xlfn.XLOOKUP($B$2,'BASE DE EXCEL'!$C:$C,'BASE DE EXCEL'!I:I,"NO HAY REFERENCIA") -> 4 | CP11: =_xlfn.XLOOKUP($B$2,'BASE DE EXCEL'!$C:$C,'BASE DE EXCEL'!J:J,"NO HAY REFERENCIA") -> 4 a 5 días | CQ11: =_xlfn.XLOOKUP($B$2,'BASE DE EXCEL'!$C:$C,'BASE DE EXCEL'!K:K,"NO HAY REFERENCIA") -> 46087 | CR11: =_xlfn.XLOOKUP($B$2,'BASE DE EXCEL'!$C:$C,'BASE DE EXCEL'!L:L,"NO HAY REFERENCIA") -> 5 | CS11: =_xlfn.XLOOKUP($B$2,'BASE DE EXCEL'!$C:$C,'BASE DE EXCEL'!M:M,"NO HAY REFERENCIA") -> 6 | CT11: =_xlfn.XLOOKUP($B$2,'BASE DE EXCEL'!$C:$C,'BASE DE EXCEL'!N:N,"NO HAY REFERENCIA") -> 6 a 10 días | CU11: =_xlfn.XLOOKUP($B$2,'BASE DE EXCEL'!$C:$C,'BASE DE EXCEL'!O:O,"NO HAY REFERENCIA") -> On Time | CV11: =_xlfn.XLOOKUP(B11,'BASE DE EXCEL'!$C:$C,'BASE DE EXCEL'!P:P,"NO HAY REFERENCIA") -> 4 a 5 días | CW11: =_xlfn.XLOOKUP(B11,'BASE DE EXCEL'!$C:$C,'BASE DE EXCEL'!Q:Q,"NO HAY REFERENCIA") -> 46031 | CX11: =_xlfn.XLOOKUP(B11,'BASE DE EXCEL'!$C:$C,'BASE DE EXCEL'!R:R,"NO HAY REFERENCIA") -> 5 | CY11: =_xlfn.XLOOKUP(B11,'BASE DE EXCEL'!$C:$C,'BASE DE EXCEL'!S:S,"NO HAY REFERENCIA") -> 4 a 5 días | CZ11: =_xlfn.XLOOKUP(B11,'BASE DE EXCEL'!$C:$C,'BASE DE EXCEL'!T:T,"NO HAY REFERENCIA") -> On Time | DA11: =_xlfn.XLOOKUP(B11,'BASE DE EXCEL'!$C:$C,'BASE DE EXCEL'!U:U,"NO HAY REFERENCIA") -> 6 | DB11: =_xlfn.XLOOKUP(B11,'BASE DE EXCEL'!$C:$C,'BASE DE EXCEL'!V:V,"NO HAY REFERENCIA") -> 4 a 5 días | DC11: =_xlfn.XLOOKUP(B11,'BASE DE EXCEL'!$C:$C,'BASE DE EXCEL'!W:W,"NO HAY REFERENCIA") -> 9 | DD11: =_xlfn.XLOOKUP(B11,'BASE DE EXCEL'!$C:$C,'BASE DE EXCEL'!X:X,"NO HAY REFERENCIA") -> 6 a 10 días | DE11: =_xlfn.XLOOKUP(B11,'BASE DE EXCEL'!$C:$C,'BASE DE EXCEL'!Y:Y,"NO HAY REFERENCIA") -> 1 | DF11: =_xlfn.XLOOKUP(B11,'BASE DE EXCEL'!$C:$C,'BASE DE EXCEL'!Z:Z,"NO HAY REFERENCIA") -> 1 día o menos | DG11: =_xlfn.XLOOKUP(B11,'BASE DE EXCEL'!$C:$C,'BASE DE EXCEL'!AA:AA,"NO HAY REFERENCIA") -> 4 | DH11: =_xlfn.XLOOKUP(B11,'BASE DE EXCEL'!$C:$C,'BASE DE EXCEL'!AB:AB,"NO HAY REFERENCIA") -> 1 | DI11: =_xlfn.XLOOKUP(B11,'BASE DE EXCEL'!$C:$C,'BASE DE EXCEL'!AC:AC,"NO HAY REFERENCIA") -> 1 día o menos | DJ11: =_xlfn.XLOOKUP(B11,'BASE DE EXCEL'!$C:$C,'BASE DE EXCEL'!AD:AD,"NO HAY REFERENCIA") -> 46038 | DK11: =_xlfn.XLOOKUP(B11,'BASE DE EXCEL'!$C:$C,'BASE DE EXCEL'!AE:AE,"NO HAY REFERENCIA") -> 7 | DL11: =_xlfn.XLOOKUP(B11,'BASE DE EXCEL'!$C:$C,'BASE DE EXCEL'!AF:AF,"NO HAY REFERENCIA") -> 5 | DM11: =_xlfn.XLOOKUP(B11,'BASE DE EXCEL'!$C:$C,'BASE DE EXCEL'!AG:AG,"NO HAY REFERENCIA") -> 46038 | DN11: =_xlfn.XLOOKUP(B11,'BASE DE EXCEL'!$C:$C,'BASE DE EXCEL'!AH:AH,"NO HAY REFERENCIA") -> 46038 | DO11: =_xlfn.XLOOKUP(B11,'BASE DE EXCEL'!$C:$C,'BASE DE EXCEL'!AI:AI,"NO HAY REFERENCIA") -> 0 | DP11: =_xlfn.XLOOKUP(B11,'BASE DE EXCEL'!$C:$C,'BASE DE EXCEL'!AJ:AJ,"NO HAY REFERENCIA") -> 6 a 10 días | DQ11: =_xlfn.XLOOKUP(B11,'BASE DE EXCEL'!$C:$C,'BASE DE EXCEL'!AK:AK,"NO HAY REFERENCIA") -> 46038 | DR11: =_xlfn.XLOOKUP(B11,'BASE DE EXCEL'!$C:$C,'BASE DE EXCEL'!AL:AL,"NO HAY REFERENCIA") -> 6 | DS11: =_xlfn.XLOOKUP(B11,'BASE DE EXCEL'!$C:$C,'BASE DE EXCEL'!AM:AM,"NO HAY REFERENCIA") -> 6 a 10 días | DT11: =_xlfn.XLOOKUP(B11,'BASE DE EXCEL'!$C:$C,'BASE DE EXCEL'!AN:AN,"NO HAY REFERENCIA") -> On Time | DU11: =_xlfn.XLOOKUP(B11,'BASE DE EXCEL'!$C:$C,'BASE DE EXCEL'!AO:AO,"NO HAY REFERENCIA") -> 1 | DV11: =_xlfn.XLOOKUP(B11,'BASE DE EXCEL'!$C:$C,'BASE DE EXCEL'!AP:AP,"NO HAY REFERENCIA") -> Es anterior | DW11: =_xlfn.XLOOKUP(B11,'BASE DE EXCEL'!$C:$C,'BASE DE EXCEL'!AQ:AQ,"NO HAY REFERENCIA") -> A1 | DX11: =_xlfn.XLOOKUP(B11,'BASE DE EXCEL'!$C:$C,'BASE DE EXCEL'!AR:AR,"NO HAY REFERENCIA") -> ZULEIMA PEREZ RUIZ | DY11: =_xlfn.XLOOKUP(B11,'BASE DE EXCEL'!$C:$C,'BASE DE EXCEL'!AS:AS,"NO HAY REFERENCIA") -> HLCUANR251131095 | DZ11: =_xlfn.XLOOKUP(B11,'BASE DE EXCEL'!$C:$C,'BASE DE EXCEL'!AT:AT,"NO HAY REFERENCIA") -> NULL | EA11: =_xlfn.XLOOKUP(B11,'BASE DE EXCEL'!$C:$C,'BASE DE EXCEL'!AU:AU,"NO HAY REFERENCIA") -> 6000072 | EB11: =_xlfn.XLOOKUP(B11,'BASE DE EXCEL'!$C:$C,'BASE DE EXCEL'!AV:AV,"NO HAY REFERENCIA") -> Importación | EC11: =_xlfn.XLOOKUP(B11,'BASE DE EXCEL'!$C:$C,'BASE DE EXCEL'!AW:AW,"NO HAY REFERENCIA") -> CEFA SAFE (MEDICAMENTO DOSIFICADO DE USO VETERINARIO) | ED11: =_xlfn.XLOOKUP(B11,'BASE DE EXCEL'!$C:$C,'BASE DE EXCEL'!AX:AX,"NO HAY REFERENCIA") -> SIN CLASIFICACION | EE11: =_xlfn.XLOOKUP(B11,'BASE DE EXCEL'!$C:$C,'BASE DE EXCEL'!AY:AY,"NO HAY REFERENCIA") -> 0 | EF11: =_xlfn.XLOOKUP(B11,'BASE DE EXCEL'!$C:$C,'BASE DE EXCEL'!AZ:AZ,"NO HAY REFERENCIA") -> Cargas de Importación | EG11: =_xlfn.XLOOKUP(B11,'BASE DE EXCEL'!$C:$C,'BASE DE EXCEL'!BA:BA,"NO HAY REFERENCIA") -> INTERVET MEXICO SA DE CV | EH11: =_xlfn.XLOOKUP(B11,'BASE DE EXCEL'!$C:$C,'BASE DE EXCEL'!BB:BB,"NO HAY REFERENCIA") -> 0 | EI11: =_xlfn.XLOOKUP(B11,'BASE DE EXCEL'!$C:$C,'BASE DE EXCEL'!BC:BC,"NO HAY REFERENCIA") -> NINGUNO | EJ11: =_xlfn.XLOOKUP(B11,'BASE DE EXCEL'!$C:$C,'BASE DE EXCEL'!BD:BD,"NO HAY REFERENCIA") -> 0 | EK11: =_xlfn.XLOOKUP(B11,'BASE DE EXCEL'!$C:$C,'BASE DE EXCEL'!BE:BE,"NO HAY REFERENCIA") -> NINGUNO | EL11: =_xlfn.XLOOKUP(B11,'BASE DE EXCEL'!$C:$C,'BASE DE EXCEL'!BF:BF,"NO HAY REFERENCIA") -> PRODUCTO TERMINADO | EM11: =_xlfn.XLOOKUP(B11,'BASE DE EXCEL'!$C:$C,'BASE DE EXCEL'!BG:BG,"NO HAY REFERENCIA") -> Verde | EN11: =_xlfn.XLOOKUP(B11,'BASE DE EXCEL'!$C:$C,'BASE DE EXCEL'!BH:BH,"NO HAY REFERENCIA") -> SUPER EXPRESS DE CARGA FEDERAL S.A. DE C.V. | EO11: =_xlfn.XLOOKUP(B11,'BASE DE EXCEL'!$C:$C,'BASE DE EXCEL'!BI:BI,"NO HAY REFERENCIA") -> 0 | EP11: =_xlfn.XLOOKUP(B11,'BASE DE EXCEL'!$C:$C,'BASE DE EXCEL'!BJ:BJ,"NO HAY REFERENCIA") -> IME-T006 | EQ11: =_xlfn.XLOOKUP(B11,'BASE DE EXCEL'!$C:$C,'BASE DE EXCEL'!BK:BK,"NO HAY REFERENCIA") -> IME850329RH2 | ER11: =_xlfn.XLOOKUP(B11,'BASE DE EXCEL'!$C:$C,'BASE DE EXCEL'!BL:BL,"NO HAY REFERENCIA") -> 0 | ES11: =_xlfn.XLOOKUP(B11,'BASE DE EXCEL'!$C:$C,'BASE DE EXCEL'!BM:BM,"NO HAY REFERENCIA") -> 00,99 | ET11: =_xlfn.XLOOKUP(B11,'BASE DE EXCEL'!$C:$C,'BASE DE EXCEL'!BN:BN,"NO HAY REFERENCIA") -> LOTE: A217A05,LOTE: A219A02,LOTE: A219A01,LOTE: A217A03,LOTE: H107A01,LOTES: J550A01, J607A01,LOTE: 5677101,LOTE: A217A04 | EU11: =_xlfn.XLOOKUP(B11,'BASE DE EXCEL'!$C:$C,'BASE DE EXCEL'!BO:BO,"NO HAY REFERENCIA") -> 90 | EV11: =_xlfn.XLOOKUP(B11,'BASE DE EXCEL'!$C:$C,'BASE DE EXCEL'!BP:BP,"NO HAY REFERENCIA") -> 952448.23, 2181141.30, 863532.00 | EW11: =_xlfn.XLOOKUP(B11,'BASE DE EXCEL'!$C:$C,'BASE DE EXCEL'!BQ:BQ,"NO HAY REFERENCIA") -> KILO,KILO,KILO,KILO,KILO,KILO,KILO,KILO | EX11: =_xlfn.XLOOKUP(B11,'BASE DE EXCEL'!$C:$C,'BASE DE EXCEL'!BR:BR,"NO HAY REFERENCIA") -> 0 | EY11: =_xlfn.XLOOKUP(B11,'BASE DE EXCEL'!$C:$C,'BASE DE EXCEL'!BS:BS,"NO HAY REFERENCIA") -> ALEMANIA (REPUBLICA FEDERAL DE),PAISES BAJOS (REINO DE LOS) (HOLANDA) | EZ11: =_xlfn.XLOOKUP(B11,'BASE DE EXCEL'!$C:$C,'BASE DE EXCEL'!BT:BT,"NO HAY REFERENCIA") -> PAISES BAJOS (REINO DE LOS) (HOLANDA) | FA11: =_xlfn.XLOOKUP(B11,'BASE DE EXCEL'!$C:$C,'BASE DE EXCEL'!BU:BU,"NO HAY REFERENCIA") -> DEU,ZYA | FB11: =_xlfn.XLOOKUP(B11,'BASE DE EXCEL'!$C:$C,'BASE DE EXCEL'!BV:BV,"NO HAY REFERENCIA") -> ZYA | FC11: =_xlfn.XLOOKUP(B11,QUERY!$C:$C,QUERY!D:D) -> 430 | FD11: =_xlfn.XLOOKUP(B11,QUERY!$C:$C,QUERY!E:E) -> 46029 | FE11: =_xlfn.XLOOKUP(B11,QUERY!$C:$C,QUERY!F:F) -> 1 | FF11: =_xlfn.XLOOKUP(B11,QUERY!$C:$C,QUERY!G:G) -> 46025 | FG11: =_xlfn.XLOOKUP(B11,QUERY!$C:$C,QUERY!H:H) -> 46029 | FH11: =_xlfn.XLOOKUP(B11,QUERY!$C:$C,QUERY!I:I) -> 2 | FI11: =_xlfn.XLOOKUP(B11,QUERY!$C:$C,QUERY!J:J) -> 2 a 3 días | FJ11: =_xlfn.XLOOKUP(B11,QUERY!$C:$C,QUERY!K:K) -> 46030 | FK11: =_xlfn.XLOOKUP(B11,QUERY!$C:$C,QUERY!L:L) -> 3 | FL11: =_xlfn.XLOOKUP(B11,QUERY!$C:$C,QUERY!M:M) -> 2 a 3 días | FM11: =_xlfn.XLOOKUP(B11,QUERY!$C:$C,QUERY!N:N) -> 1 | FN11: =_xlfn.XLOOKUP(B11,QUERY!$C:$C,QUERY!O:O) -> 1 día o menos | FO11: =_xlfn.XLOOKUP(B11,QUERY!$C:$C,QUERY!P:P) -> 1 | FP11: =_xlfn.XLOOKUP(B11,QUERY!$C:$C,QUERY!Q:Q) -> 1 | FQ11: =_xlfn.XLOOKUP(B11,QUERY!$C:$C,QUERY!R:R) -> 1 día o menos | FR11: =_xlfn.XLOOKUP(B11,QUERY!$C:$C,QUERY!S:S) -> 46031 | FS11: =_xlfn.XLOOKUP(B11,QUERY!$C:$C,QUERY!T:T) -> 4 | FT11: =_xlfn.XLOOKUP(B11,QUERY!$C:$C,QUERY!U:U) -> 4 a 5 días | FU11: =_xlfn.XLOOKUP(B11,QUERY!$C:$C,QUERY!V:V) -> 9 | FV11: =_xlfn.XLOOKUP(B11,QUERY!$C:$C,QUERY!W:W) -> 6 a 10 días | FW11: =_xlfn.XLOOKUP(B11,QUERY!$C:$C,QUERY!X:X) -> 46038 | FX11: =_xlfn.XLOOKUP(B11,QUERY!$C:$C,QUERY!Y:Y) -> 5 | FY11: =_xlfn.XLOOKUP(B11,QUERY!$C:$C,QUERY!Z:Z) -> 5 | FZ11: =_xlfn.XLOOKUP(B11,QUERY!$C:$C,QUERY!AA:AA) -> 6 a 10 días | GA11: =_xlfn.XLOOKUP(B11,QUERY!$C:$C,QUERY!AB:AB) -> 46038 | GB11: =_xlfn.XLOOKUP(B11,QUERY!$C:$C,QUERY!AC:AC) -> 46038 | GC11: =_xlfn.XLOOKUP(B11,QUERY!$C:$C,QUERY!AD:AD) -> 0 | GD11: =_xlfn.XLOOKUP(B11,QUERY!$C:$C,QUERY!AE:AE) -> 46038 | GE11: =_xlfn.XLOOKUP(B11,QUERY!$C:$C,QUERY!AF:AF) -> 1 | GF11: =_xlfn.XLOOKUP(B11,QUERY!$C:$C,QUERY!AG:AG) -> Es anterior | GG11: =_xlfn.XLOOKUP(B11,QUERY!$C:$C,QUERY!AH:AH) -> A1 | GH11: =_xlfn.XLOOKUP(B11,QUERY!$C:$C,QUERY!AI:AI) -> ZULEIMA PEREZ RUIZ | GI11: =_xlfn.XLOOKUP(B11,QUERY!$C:$C,QUERY!AJ:AJ) -> HLCUANR251131095 | GJ11: =_xlfn.XLOOKUP(B11,QUERY!$C:$C,QUERY!AK:AK) -> NULL | GK11: =_xlfn.XLOOKUP(B11,QUERY!$C:$C,QUERY!AL:AL) -> 6000072 | GL11: =_xlfn.XLOOKUP(B11,QUERY!$C:$C,QUERY!AM:AM) -> Importación | GM11: =_xlfn.XLOOKUP(B11,QUERY!$C:$C,QUERY!AN:AN) -> CEFA SAFE (MEDICAMENTO DOSIFICADO DE USO VETERINARIO) | GN11: =_xlfn.XLOOKUP(B11,QUERY!$C:$C,QUERY!AO:AO) -> SIN CLASIFICACION | GO11: =_xlfn.XLOOKUP(B11,QUERY!$C:$C,QUERY!AP:AP) -> 0 | GP11: =_xlfn.XLOOKUP(B11,QUERY!$C:$C,QUERY!AQ:AQ) -> Cargas de Importación | GQ11: =_xlfn.XLOOKUP(B11,QUERY!$C:$C,QUERY!AR:AR) -> INTERVET MEXICO SA DE CV | GR11: =_xlfn.XLOOKUP(B11,QUERY!$C:$C,QUERY!AS:AS) -> 0 | GS11: =_xlfn.XLOOKUP(B11,QUERY!$C:$C,QUERY!AT:AT) -> NINGUNO | GT11: =_xlfn.XLOOKUP(B11,QUERY!$C:$C,QUERY!AU:AU) -> 0 | GU11: =_xlfn.XLOOKUP(B11,QUERY!$C:$C,QUERY!AV:AV) -> NINGUNO | GV11: =_xlfn.XLOOKUP(B11,QUERY!$C:$C,QUERY!AW:AW) -> PRODUCTO TERMINADO | GW11: =_xlfn.XLOOKUP(B11,QUERY!$C:$C,QUERY!AX:AX) -> Verde | GX11: =_xlfn.XLOOKUP(B11,QUERY!$C:$C,QUERY!AY:AY) -> SUPER EXPRESS DE CARGA FEDERAL S.A. DE C.V. | GY11: =_xlfn.XLOOKUP(B11,QUERY!$C:$C,QUERY!AZ:AZ) -> 0 | GZ11: =_xlfn.XLOOKUP(B11,QUERY!$C:$C,QUERY!BA:BA) -> IME-T006 | HA11: =_xlfn.XLOOKUP(B11,QUERY!$C:$C,QUERY!BB:BB) -> IME850329RH2 | HB11: =_xlfn.XLOOKUP(B11,QUERY!$C:$C,QUERY!BC:BC) -> 0 | HC11: =_xlfn.XLOOKUP(B11,QUERY!$C:$C,QUERY!BD:BD) -> 0.99 | HD11: =_xlfn.XLOOKUP(B11,QUERY!$C:$C,QUERY!BE:BE) -> LOTE: A217A05,LOTE: A219A02,LOTE: A219A01,LOTE: A217A04,LOTE: A217A03,LOTE: H107A01,LOTES: J550A01, J607A01,LOTE: 5677101 | HE11: =_xlfn.XLOOKUP(B11,QUERY!$C:$C,QUERY!BF:BF) -> 90 | HF11: =_xlfn.XLOOKUP(B11,QUERY!$C:$C,QUERY!BG:BG) -> 952448.23, 2181141.30, 863532.00 | HG11: =_xlfn.XLOOKUP(B11,QUERY!$C:$C,QUERY!BH:BH) -> KILO,KILO,KILO,KILO,KILO,KILO,KILO,KILO | HH11: =_xlfn.XLOOKUP(B11,QUERY!$C:$C,QUERY!BI:BI) -> 0 | HI11: =_xlfn.XLOOKUP(B11,QUERY!$C:$C,QUERY!BJ:BJ) -> ALEMANIA (REPUBLICA FEDERAL DE),PAISES BAJOS (REINO DE LOS) (HOLANDA) | HJ11: =_xlfn.XLOOKUP(B11,QUERY!$C:$C,QUERY!BK:BK) -> PAISES BAJOS (REINO DE LOS) (HOLANDA) | HK11: =_xlfn.XLOOKUP(B11,QUERY!$C:$C,QUERY!BL:BL) -> DEU,ZYA | HL11: =_xlfn.XLOOKUP(B11,QUERY!$C:$C,QUERY!BM:BM) -> ZYA | HM11: =_xlfn.XLOOKUP(B11,QUERY!$C:$C,QUERY!BN:BN) -> 3997122 | HN11: =_xlfn.XLOOKUP(B11,QUERY!$C:$C,QUERY!BO:BO) -> 462.00 | HO11: =_xlfn.XLOOKUP(B11,QUERY!$C:$C,QUERY!BP:BP) -> NULL | HP11: =_xlfn.XLOOKUP(B11,QUERY!$C:$C,QUERY!BQ:BQ) -> NULL | HQ11: =_xlfn.XLOOKUP(B11,QUERY!$C:$C,QUERY!BR:BR) -> 139939.61 | HR11: =_xlfn.XLOOKUP(B11,QUERY!$C:$C,QUERY!BS:BS) -> 0 | HS11: =_xlfn.XLOOKUP(B11,QUERY!$C:$C,QUERY!BT:BT) -> 0 | HT11: =_xlfn.XLOOKUP(B11,QUERY!$C:$C,QUERY!A:A) -> VERACRUZ | HU11: =_xlfn.XLOOKUP(B11,QUERY!$C:$C,QUERY!B:B) -> MARÍTIMO VERACRUZ
A12: INTERVET MEXICO SA DE CV | B12: VER-25-1248 | C12: 3942 | D12: 6000072 | F12: Importación | G12: A1 | H12: 0 | I12: 0 | J12: 0 | K12: 0 | L12: 0 | M12: 0 | N12: 0 | O12: 0 | P12: 0 | Q12: 0 | R12: 430 | S12: CAAU4072651 | T12: 0 | U12: 0 | V12: 0 | W12: 0 | X12: 0 | Y12: 0 | Z12: 0 | AA12: CELOSIL (MEDICAMENTO DOSIFICADO DE USO VETERINARIO) | AC12: 863532 | AD12: 479.74 | AE12: 0 | AF12: 0 | AG12: 0 | AH12: 0 | AI12: 0 | AJ12: 0 | AK12: 0 | AL12: 0 | AM12: 0 | AN12: 0 | AP12: INTERVET INTERNATIONAL BV | AQ12: 210358711 | AR12: CIP | AS12: MXP | AT12: 0 | AU12: 0 | AV12: 0 | AW12: 30043999 | AX12: 99 | AY12: 1800 | AZ12: 1800 | BA12: PIEZA | BC12: DEU | BD12: ZYA | BK12: COVE267WG87C4 | BL12: 0 | BM12: 0 | BN12: 0 | BO12: 0 | BP12: 0 | BQ12: 0 | BR12: 0 | BS12: 0 | BT12: 0 | BU12: 0 | BV12: 0 | BW12: 0 | BX12: 0 | BY12: 0 | BZ12: 0 | CA12: 0 | CB12: 0 | CC12: 0 | CD12: 0 | CE12: PAGADO | CF12: 0 | CG12: 0 | CH12: 0 | CI12: ZULEIMA PEREZ RUIZ | CJ12: ZULEIMA PEREZ RUIZ | CK12: =_xlfn.XLOOKUP($B$2,'BASE DE EXCEL'!C:C,'BASE DE EXCEL'!D:D,"NO HAY REFERENCIA") -> 470 | CL12: =_xlfn.XLOOKUP($B$2,'BASE DE EXCEL'!$C:$C,'BASE DE EXCEL'!F:F,"NO HAY REFERENCIA") -> 3 | CM12: =_xlfn.XLOOKUP($B$2,'BASE DE EXCEL'!$C:$C,'BASE DE EXCEL'!G:G,"NO HAY REFERENCIA") -> 46080 | CN12: =_xlfn.XLOOKUP($B$2,'BASE DE EXCEL'!$C:$C,'BASE DE EXCEL'!H:H,"NO HAY REFERENCIA") -> 46086 | CO12: =_xlfn.XLOOKUP($B$2,'BASE DE EXCEL'!$C:$C,'BASE DE EXCEL'!I:I,"NO HAY REFERENCIA") -> 4 | CP12: =_xlfn.XLOOKUP($B$2,'BASE DE EXCEL'!$C:$C,'BASE DE EXCEL'!J:J,"NO HAY REFERENCIA") -> 4 a 5 días | CQ12: =_xlfn.XLOOKUP($B$2,'BASE DE EXCEL'!$C:$C,'BASE DE EXCEL'!K:K,"NO HAY REFERENCIA") -> 46087 | CR12: =_xlfn.XLOOKUP($B$2,'BASE DE EXCEL'!$C:$C,'BASE DE EXCEL'!L:L,"NO HAY REFERENCIA") -> 5 | CS12: =_xlfn.XLOOKUP($B$2,'BASE DE EXCEL'!$C:$C,'BASE DE EXCEL'!M:M,"NO HAY REFERENCIA") -> 6 | CT12: =_xlfn.XLOOKUP($B$2,'BASE DE EXCEL'!$C:$C,'BASE DE EXCEL'!N:N,"NO HAY REFERENCIA") -> 6 a 10 días | CU12: =_xlfn.XLOOKUP($B$2,'BASE DE EXCEL'!$C:$C,'BASE DE EXCEL'!O:O,"NO HAY REFERENCIA") -> On Time | CV12: =_xlfn.XLOOKUP(B12,'BASE DE EXCEL'!$C:$C,'BASE DE EXCEL'!P:P,"NO HAY REFERENCIA") -> 4 a 5 días | CW12: =_xlfn.XLOOKUP(B12,'BASE DE EXCEL'!$C:$C,'BASE DE EXCEL'!Q:Q,"NO HAY REFERENCIA") -> 46031 | CX12: =_xlfn.XLOOKUP(B12,'BASE DE EXCEL'!$C:$C,'BASE DE EXCEL'!R:R,"NO HAY REFERENCIA") -> 5 | CY12: =_xlfn.XLOOKUP(B12,'BASE DE EXCEL'!$C:$C,'BASE DE EXCEL'!S:S,"NO HAY REFERENCIA") -> 4 a 5 días | CZ12: =_xlfn.XLOOKUP(B12,'BASE DE EXCEL'!$C:$C,'BASE DE EXCEL'!T:T,"NO HAY REFERENCIA") -> On Time | DA12: =_xlfn.XLOOKUP(B12,'BASE DE EXCEL'!$C:$C,'BASE DE EXCEL'!U:U,"NO HAY REFERENCIA") -> 6 | DB12: =_xlfn.XLOOKUP(B12,'BASE DE EXCEL'!$C:$C,'BASE DE EXCEL'!V:V,"NO HAY REFERENCIA") -> 4 a 5 días | DC12: =_xlfn.XLOOKUP(B12,'BASE DE EXCEL'!$C:$C,'BASE DE EXCEL'!W:W,"NO HAY REFERENCIA") -> 9 | DD12: =_xlfn.XLOOKUP(B12,'BASE DE EXCEL'!$C:$C,'BASE DE EXCEL'!X:X,"NO HAY REFERENCIA") -> 6 a 10 días | DE12: =_xlfn.XLOOKUP(B12,'BASE DE EXCEL'!$C:$C,'BASE DE EXCEL'!Y:Y,"NO HAY REFERENCIA") -> 1 | DF12: =_xlfn.XLOOKUP(B12,'BASE DE EXCEL'!$C:$C,'BASE DE EXCEL'!Z:Z,"NO HAY REFERENCIA") -> 1 día o menos | DG12: =_xlfn.XLOOKUP(B12,'BASE DE EXCEL'!$C:$C,'BASE DE EXCEL'!AA:AA,"NO HAY REFERENCIA") -> 4 | DH12: =_xlfn.XLOOKUP(B12,'BASE DE EXCEL'!$C:$C,'BASE DE EXCEL'!AB:AB,"NO HAY REFERENCIA") -> 1 | DI12: =_xlfn.XLOOKUP(B12,'BASE DE EXCEL'!$C:$C,'BASE DE EXCEL'!AC:AC,"NO HAY REFERENCIA") -> 1 día o menos | DJ12: =_xlfn.XLOOKUP(B12,'BASE DE EXCEL'!$C:$C,'BASE DE EXCEL'!AD:AD,"NO HAY REFERENCIA") -> 46038 | DK12: =_xlfn.XLOOKUP(B12,'BASE DE EXCEL'!$C:$C,'BASE DE EXCEL'!AE:AE,"NO HAY REFERENCIA") -> 7 | DL12: =_xlfn.XLOOKUP(B12,'BASE DE EXCEL'!$C:$C,'BASE DE EXCEL'!AF:AF,"NO HAY REFERENCIA") -> 5 | DM12: =_xlfn.XLOOKUP(B12,'BASE DE EXCEL'!$C:$C,'BASE DE EXCEL'!AG:AG,"NO HAY REFERENCIA") -> 46038 | DN12: =_xlfn.XLOOKUP(B12,'BASE DE EXCEL'!$C:$C,'BASE DE EXCEL'!AH:AH,"NO HAY REFERENCIA") -> 46038 | DO12: =_xlfn.XLOOKUP(B12,'BASE DE EXCEL'!$C:$C,'BASE DE EXCEL'!AI:AI,"NO HAY REFERENCIA") -> 0 | DP12: =_xlfn.XLOOKUP(B12,'BASE DE EXCEL'!$C:$C,'BASE DE EXCEL'!AJ:AJ,"NO HAY REFERENCIA") -> 6 a 10 días | DQ12: =_xlfn.XLOOKUP(B12,'BASE DE EXCEL'!$C:$C,'BASE DE EXCEL'!AK:AK,"NO HAY REFERENCIA") -> 46038 | DR12: =_xlfn.XLOOKUP(B12,'BASE DE EXCEL'!$C:$C,'BASE DE EXCEL'!AL:AL,"NO HAY REFERENCIA") -> 6 | DS12: =_xlfn.XLOOKUP(B12,'BASE DE EXCEL'!$C:$C,'BASE DE EXCEL'!AM:AM,"NO HAY REFERENCIA") -> 6 a 10 días | DT12: =_xlfn.XLOOKUP(B12,'BASE DE EXCEL'!$C:$C,'BASE DE EXCEL'!AN:AN,"NO HAY REFERENCIA") -> On Time | DU12: =_xlfn.XLOOKUP(B12,'BASE DE EXCEL'!$C:$C,'BASE DE EXCEL'!AO:AO,"NO HAY REFERENCIA") -> 1 | DV12: =_xlfn.XLOOKUP(B12,'BASE DE EXCEL'!$C:$C,'BASE DE EXCEL'!AP:AP,"NO HAY REFERENCIA") -> Es anterior | DW12: =_xlfn.XLOOKUP(B12,'BASE DE EXCEL'!$C:$C,'BASE DE EXCEL'!AQ:AQ,"NO HAY REFERENCIA") -> A1 | DX12: =_xlfn.XLOOKUP(B12,'BASE DE EXCEL'!$C:$C,'BASE DE EXCEL'!AR:AR,"NO HAY REFERENCIA") -> ZULEIMA PEREZ RUIZ | DY12: =_xlfn.XLOOKUP(B12,'BASE DE EXCEL'!$C:$C,'BASE DE EXCEL'!AS:AS,"NO HAY REFERENCIA") -> HLCUANR251131095 | DZ12: =_xlfn.XLOOKUP(B12,'BASE DE EXCEL'!$C:$C,'BASE DE EXCEL'!AT:AT,"NO HAY REFERENCIA") -> NULL | EA12: =_xlfn.XLOOKUP(B12,'BASE DE EXCEL'!$C:$C,'BASE DE EXCEL'!AU:AU,"NO HAY REFERENCIA") -> 6000072 | EB12: =_xlfn.XLOOKUP(B12,'BASE DE EXCEL'!$C:$C,'BASE DE EXCEL'!AV:AV,"NO HAY REFERENCIA") -> Importación | EC12: =_xlfn.XLOOKUP(B12,'BASE DE EXCEL'!$C:$C,'BASE DE EXCEL'!AW:AW,"NO HAY REFERENCIA") -> CEFA SAFE (MEDICAMENTO DOSIFICADO DE USO VETERINARIO) | ED12: =_xlfn.XLOOKUP(B12,'BASE DE EXCEL'!$C:$C,'BASE DE EXCEL'!AX:AX,"NO HAY REFERENCIA") -> SIN CLASIFICACION | EE12: =_xlfn.XLOOKUP(B12,'BASE DE EXCEL'!$C:$C,'BASE DE EXCEL'!AY:AY,"NO HAY REFERENCIA") -> 0 | EF12: =_xlfn.XLOOKUP(B12,'BASE DE EXCEL'!$C:$C,'BASE DE EXCEL'!AZ:AZ,"NO HAY REFERENCIA") -> Cargas de Importación | EG12: =_xlfn.XLOOKUP(B12,'BASE DE EXCEL'!$C:$C,'BASE DE EXCEL'!BA:BA,"NO HAY REFERENCIA") -> INTERVET MEXICO SA DE CV | EH12: =_xlfn.XLOOKUP(B12,'BASE DE EXCEL'!$C:$C,'BASE DE EXCEL'!BB:BB,"NO HAY REFERENCIA") -> 0 | EI12: =_xlfn.XLOOKUP(B12,'BASE DE EXCEL'!$C:$C,'BASE DE EXCEL'!BC:BC,"NO HAY REFERENCIA") -> NINGUNO | EJ12: =_xlfn.XLOOKUP(B12,'BASE DE EXCEL'!$C:$C,'BASE DE EXCEL'!BD:BD,"NO HAY REFERENCIA") -> 0 | EK12: =_xlfn.XLOOKUP(B12,'BASE DE EXCEL'!$C:$C,'BASE DE EXCEL'!BE:BE,"NO HAY REFERENCIA") -> NINGUNO | EL12: =_xlfn.XLOOKUP(B12,'BASE DE EXCEL'!$C:$C,'BASE DE EXCEL'!BF:BF,"NO HAY REFERENCIA") -> PRODUCTO TERMINADO | EM12: =_xlfn.XLOOKUP(B12,'BASE DE EXCEL'!$C:$C,'BASE DE EXCEL'!BG:BG,"NO HAY REFERENCIA") -> Verde | EN12: =_xlfn.XLOOKUP(B12,'BASE DE EXCEL'!$C:$C,'BASE DE EXCEL'!BH:BH,"NO HAY REFERENCIA") -> SUPER EXPRESS DE CARGA FEDERAL S.A. DE C.V. | EO12: =_xlfn.XLOOKUP(B12,'BASE DE EXCEL'!$C:$C,'BASE DE EXCEL'!BI:BI,"NO HAY REFERENCIA") -> 0 | EP12: =_xlfn.XLOOKUP(B12,'BASE DE EXCEL'!$C:$C,'BASE DE EXCEL'!BJ:BJ,"NO HAY REFERENCIA") -> IME-T006 | EQ12: =_xlfn.XLOOKUP(B12,'BASE DE EXCEL'!$C:$C,'BASE DE EXCEL'!BK:BK,"NO HAY REFERENCIA") -> IME850329RH2 | ER12: =_xlfn.XLOOKUP(B12,'BASE DE EXCEL'!$C:$C,'BASE DE EXCEL'!BL:BL,"NO HAY REFERENCIA") -> 0 | ES12: =_xlfn.XLOOKUP(B12,'BASE DE EXCEL'!$C:$C,'BASE DE EXCEL'!BM:BM,"NO HAY REFERENCIA") -> 00,99 | ET12: =_xlfn.XLOOKUP(B12,'BASE DE EXCEL'!$C:$C,'BASE DE EXCEL'!BN:BN,"NO HAY REFERENCIA") -> LOTE: A217A05,LOTE: A219A02,LOTE: A219A01,LOTE: A217A03,LOTE: H107A01,LOTES: J550A01, J607A01,LOTE: 5677101,LOTE: A217A04 | EU12: =_xlfn.XLOOKUP(B12,'BASE DE EXCEL'!$C:$C,'BASE DE EXCEL'!BO:BO,"NO HAY REFERENCIA") -> 90 | EV12: =_xlfn.XLOOKUP(B12,'BASE DE EXCEL'!$C:$C,'BASE DE EXCEL'!BP:BP,"NO HAY REFERENCIA") -> 952448.23, 2181141.30, 863532.00 | EW12: =_xlfn.XLOOKUP(B12,'BASE DE EXCEL'!$C:$C,'BASE DE EXCEL'!BQ:BQ,"NO HAY REFERENCIA") -> KILO,KILO,KILO,KILO,KILO,KILO,KILO,KILO | EX12: =_xlfn.XLOOKUP(B12,'BASE DE EXCEL'!$C:$C,'BASE DE EXCEL'!BR:BR,"NO HAY REFERENCIA") -> 0 | EY12: =_xlfn.XLOOKUP(B12,'BASE DE EXCEL'!$C:$C,'BASE DE EXCEL'!BS:BS,"NO HAY REFERENCIA") -> ALEMANIA (REPUBLICA FEDERAL DE),PAISES BAJOS (REINO DE LOS) (HOLANDA) | EZ12: =_xlfn.XLOOKUP(B12,'BASE DE EXCEL'!$C:$C,'BASE DE EXCEL'!BT:BT,"NO HAY REFERENCIA") -> PAISES BAJOS (REINO DE LOS) (HOLANDA) | FA12: =_xlfn.XLOOKUP(B12,'BASE DE EXCEL'!$C:$C,'BASE DE EXCEL'!BU:BU,"NO HAY REFERENCIA") -> DEU,ZYA | FB12: =_xlfn.XLOOKUP(B12,'BASE DE EXCEL'!$C:$C,'BASE DE EXCEL'!BV:BV,"NO HAY REFERENCIA") -> ZYA | FC12: =_xlfn.XLOOKUP(B12,QUERY!$C:$C,QUERY!D:D) -> 430 | FD12: =_xlfn.XLOOKUP(B12,QUERY!$C:$C,QUERY!E:E) -> 46029 | FE12: =_xlfn.XLOOKUP(B12,QUERY!$C:$C,QUERY!F:F) -> 1 | FF12: =_xlfn.XLOOKUP(B12,QUERY!$C:$C,QUERY!G:G) -> 46025 | FG12: =_xlfn.XLOOKUP(B12,QUERY!$C:$C,QUERY!H:H) -> 46029 | FH12: =_xlfn.XLOOKUP(B12,QUERY!$C:$C,QUERY!I:I) -> 2 | FI12: =_xlfn.XLOOKUP(B12,QUERY!$C:$C,QUERY!J:J) -> 2 a 3 días | FJ12: =_xlfn.XLOOKUP(B12,QUERY!$C:$C,QUERY!K:K) -> 46030 | FK12: =_xlfn.XLOOKUP(B12,QUERY!$C:$C,QUERY!L:L) -> 3 | FL12: =_xlfn.XLOOKUP(B12,QUERY!$C:$C,QUERY!M:M) -> 2 a 3 días | FM12: =_xlfn.XLOOKUP(B12,QUERY!$C:$C,QUERY!N:N) -> 1 | FN12: =_xlfn.XLOOKUP(B12,QUERY!$C:$C,QUERY!O:O) -> 1 día o menos | FO12: =_xlfn.XLOOKUP(B12,QUERY!$C:$C,QUERY!P:P) -> 1 | FP12: =_xlfn.XLOOKUP(B12,QUERY!$C:$C,QUERY!Q:Q) -> 1 | FQ12: =_xlfn.XLOOKUP(B12,QUERY!$C:$C,QUERY!R:R) -> 1 día o menos | FR12: =_xlfn.XLOOKUP(B12,QUERY!$C:$C,QUERY!S:S) -> 46031 | FS12: =_xlfn.XLOOKUP(B12,QUERY!$C:$C,QUERY!T:T) -> 4 | FT12: =_xlfn.XLOOKUP(B12,QUERY!$C:$C,QUERY!U:U) -> 4 a 5 días | FU12: =_xlfn.XLOOKUP(B12,QUERY!$C:$C,QUERY!V:V) -> 9 | FV12: =_xlfn.XLOOKUP(B12,QUERY!$C:$C,QUERY!W:W) -> 6 a 10 días | FW12: =_xlfn.XLOOKUP(B12,QUERY!$C:$C,QUERY!X:X) -> 46038 | FX12: =_xlfn.XLOOKUP(B12,QUERY!$C:$C,QUERY!Y:Y) -> 5 | FY12: =_xlfn.XLOOKUP(B12,QUERY!$C:$C,QUERY!Z:Z) -> 5 | FZ12: =_xlfn.XLOOKUP(B12,QUERY!$C:$C,QUERY!AA:AA) -> 6 a 10 días | GA12: =_xlfn.XLOOKUP(B12,QUERY!$C:$C,QUERY!AB:AB) -> 46038 | GB12: =_xlfn.XLOOKUP(B12,QUERY!$C:$C,QUERY!AC:AC) -> 46038 | GC12: =_xlfn.XLOOKUP(B12,QUERY!$C:$C,QUERY!AD:AD) -> 0 | GD12: =_xlfn.XLOOKUP(B12,QUERY!$C:$C,QUERY!AE:AE) -> 46038 | GE12: =_xlfn.XLOOKUP(B12,QUERY!$C:$C,QUERY!AF:AF) -> 1 | GF12: =_xlfn.XLOOKUP(B12,QUERY!$C:$C,QUERY!AG:AG) -> Es anterior | GG12: =_xlfn.XLOOKUP(B12,QUERY!$C:$C,QUERY!AH:AH) -> A1 | GH12: =_xlfn.XLOOKUP(B12,QUERY!$C:$C,QUERY!AI:AI) -> ZULEIMA PEREZ RUIZ | GI12: =_xlfn.XLOOKUP(B12,QUERY!$C:$C,QUERY!AJ:AJ) -> HLCUANR251131095 | GJ12: =_xlfn.XLOOKUP(B12,QUERY!$C:$C,QUERY!AK:AK) -> NULL | GK12: =_xlfn.XLOOKUP(B12,QUERY!$C:$C,QUERY!AL:AL) -> 6000072 | GL12: =_xlfn.XLOOKUP(B12,QUERY!$C:$C,QUERY!AM:AM) -> Importación | GM12: =_xlfn.XLOOKUP(B12,QUERY!$C:$C,QUERY!AN:AN) -> CEFA SAFE (MEDICAMENTO DOSIFICADO DE USO VETERINARIO) | GN12: =_xlfn.XLOOKUP(B12,QUERY!$C:$C,QUERY!AO:AO) -> SIN CLASIFICACION | GO12: =_xlfn.XLOOKUP(B12,QUERY!$C:$C,QUERY!AP:AP) -> 0 | GP12: =_xlfn.XLOOKUP(B12,QUERY!$C:$C,QUERY!AQ:AQ) -> Cargas de Importación | GQ12: =_xlfn.XLOOKUP(B12,QUERY!$C:$C,QUERY!AR:AR) -> INTERVET MEXICO SA DE CV | GR12: =_xlfn.XLOOKUP(B12,QUERY!$C:$C,QUERY!AS:AS) -> 0 | GS12: =_xlfn.XLOOKUP(B12,QUERY!$C:$C,QUERY!AT:AT) -> NINGUNO | GT12: =_xlfn.XLOOKUP(B12,QUERY!$C:$C,QUERY!AU:AU) -> 0 | GU12: =_xlfn.XLOOKUP(B12,QUERY!$C:$C,QUERY!AV:AV) -> NINGUNO | GV12: =_xlfn.XLOOKUP(B12,QUERY!$C:$C,QUERY!AW:AW) -> PRODUCTO TERMINADO | GW12: =_xlfn.XLOOKUP(B12,QUERY!$C:$C,QUERY!AX:AX) -> Verde | GX12: =_xlfn.XLOOKUP(B12,QUERY!$C:$C,QUERY!AY:AY) -> SUPER EXPRESS DE CARGA FEDERAL S.A. DE C.V. | GY12: =_xlfn.XLOOKUP(B12,QUERY!$C:$C,QUERY!AZ:AZ) -> 0 | GZ12: =_xlfn.XLOOKUP(B12,QUERY!$C:$C,QUERY!BA:BA) -> IME-T006 | HA12: =_xlfn.XLOOKUP(B12,QUERY!$C:$C,QUERY!BB:BB) -> IME850329RH2 | HB12: =_xlfn.XLOOKUP(B12,QUERY!$C:$C,QUERY!BC:BC) -> 0 | HC12: =_xlfn.XLOOKUP(B12,QUERY!$C:$C,QUERY!BD:BD) -> 0.99 | HD12: =_xlfn.XLOOKUP(B12,QUERY!$C:$C,QUERY!BE:BE) -> LOTE: A217A05,LOTE: A219A02,LOTE: A219A01,LOTE: A217A04,LOTE: A217A03,LOTE: H107A01,LOTES: J550A01, J607A01,LOTE: 5677101 | HE12: =_xlfn.XLOOKUP(B12,QUERY!$C:$C,QUERY!BF:BF) -> 90 | HF12: =_xlfn.XLOOKUP(B12,QUERY!$C:$C,QUERY!BG:BG) -> 952448.23, 2181141.30, 863532.00 | HG12: =_xlfn.XLOOKUP(B12,QUERY!$C:$C,QUERY!BH:BH) -> KILO,KILO,KILO,KILO,KILO,KILO,KILO,KILO | HH12: =_xlfn.XLOOKUP(B12,QUERY!$C:$C,QUERY!BI:BI) -> 0 | HI12: =_xlfn.XLOOKUP(B12,QUERY!$C:$C,QUERY!BJ:BJ) -> ALEMANIA (REPUBLICA FEDERAL DE),PAISES BAJOS (REINO DE LOS) (HOLANDA) | HJ12: =_xlfn.XLOOKUP(B12,QUERY!$C:$C,QUERY!BK:BK) -> PAISES BAJOS (REINO DE LOS) (HOLANDA) | HK12: =_xlfn.XLOOKUP(B12,QUERY!$C:$C,QUERY!BL:BL) -> DEU,ZYA | HL12: =_xlfn.XLOOKUP(B12,QUERY!$C:$C,QUERY!BM:BM) -> ZYA | HM12: =_xlfn.XLOOKUP(B12,QUERY!$C:$C,QUERY!BN:BN) -> 3997122 | HN12: =_xlfn.XLOOKUP(B12,QUERY!$C:$C,QUERY!BO:BO) -> 462.00 | HO12: =_xlfn.XLOOKUP(B12,QUERY!$C:$C,QUERY!BP:BP) -> NULL | HP12: =_xlfn.XLOOKUP(B12,QUERY!$C:$C,QUERY!BQ:BQ) -> NULL | HQ12: =_xlfn.XLOOKUP(B12,QUERY!$C:$C,QUERY!BR:BR) -> 139939.61 | HR12: =_xlfn.XLOOKUP(B12,QUERY!$C:$C,QUERY!BS:BS) -> 0 | HS12: =_xlfn.XLOOKUP(B12,QUERY!$C:$C,QUERY!BT:BT) -> 0 | HT12: =_xlfn.XLOOKUP(B12,QUERY!$C:$C,QUERY!A:A) -> VERACRUZ | HU12: =_xlfn.XLOOKUP(B12,QUERY!$C:$C,QUERY!B:B) -> MARÍTIMO VERACRUZ
A13: INTERVET MEXICO SA DE CV | B13: VER-25-1250 | C13: 3942 | D13: 6000083 | F13: Importación | G13: A1 | H13: 0 | I13: 0 | J13: 0 | K13: 0 | L13: 0 | M13: 0 | N13: 0 | O13: 0 | P13: 18.2085 | Q13: 9260.96 | R13: 430 | S13: HLBU6070355 | T13: 1 CONTENEDOR DE 40' RH | U13: 12581182 | V13: 12581182 | W13: 0 | X13: 0 | Y13: 0 | Z13: 0 | AA13: ZILMAX (PROMOTOR DEL RENDIMIENTO) | AC13: 12581182 | AD13: 14836.3 | AE13: 354 | AF13: 0 | AG13: 0 | AH13: 0 | AI13: 53 | AJ13: 100649 | AK13: 0 | AL13: 0 | AM13: 330 | AN13: 101032 | AO13: Cliente | AP13: INTERVET INTERNATIONAL BV | AQ13: 210358461 | AR13: CIP | AS13: MXP | AT13: HLCULE1251059620 | AV13: TEC | AW13: 23099099 | AX13: 99 | AY13: 848 | AZ13: 848 | BA13: PIEZA | BC13: FRA | BD13: ZYA | BE13: DESADUANAMIENTO LIBRE | BF13: FALTA RRNA | BG13: 4.3064022e+16 | BH13: A1 | BJ13: DE CONFORMIDAD CON EL ART. 36- | BK13: COVE267WBI7G5 | BL13: 41521 | BM13: 0 | BN13: 0 | BO13: 0 | BP13: 0 | BQ13: 0 | BR13: 0 | BS13: 0 | BT13: 0 | BU13: 0 | BV13: 0 | BW13: 0 | BX13: 20545.92 | BY13: 0 | BZ13: 0 | CA13: 120130.3 | CB13: 18000 | CC13: 3323.2 | CD13: 375823.69 | CE13: PAGADO | CF13: 375823.69 | CG13: 375823.69 | CH13: 0 | CI13: ZULEIMA PEREZ RUIZ | CJ13: ZULEIMA PEREZ RUIZ | CK13: =_xlfn.XLOOKUP($B$2,'BASE DE EXCEL'!C:C,'BASE DE EXCEL'!D:D,"NO HAY REFERENCIA") -> 470 | CL13: =_xlfn.XLOOKUP($B$2,'BASE DE EXCEL'!$C:$C,'BASE DE EXCEL'!F:F,"NO HAY REFERENCIA") -> 3 | CM13: =_xlfn.XLOOKUP($B$2,'BASE DE EXCEL'!$C:$C,'BASE DE EXCEL'!G:G,"NO HAY REFERENCIA") -> 46080 | CN13: =_xlfn.XLOOKUP($B$2,'BASE DE EXCEL'!$C:$C,'BASE DE EXCEL'!H:H,"NO HAY REFERENCIA") -> 46086 | CO13: =_xlfn.XLOOKUP($B$2,'BASE DE EXCEL'!$C:$C,'BASE DE EXCEL'!I:I,"NO HAY REFERENCIA") -> 4 | CP13: =_xlfn.XLOOKUP($B$2,'BASE DE EXCEL'!$C:$C,'BASE DE EXCEL'!J:J,"NO HAY REFERENCIA") -> 4 a 5 días | CQ13: =_xlfn.XLOOKUP($B$2,'BASE DE EXCEL'!$C:$C,'BASE DE EXCEL'!K:K,"NO HAY REFERENCIA") -> 46087 | CR13: =_xlfn.XLOOKUP($B$2,'BASE DE EXCEL'!$C:$C,'BASE DE EXCEL'!L:L,"NO HAY REFERENCIA") -> 5 | CS13: =_xlfn.XLOOKUP($B$2,'BASE DE EXCEL'!$C:$C,'BASE DE EXCEL'!M:M,"NO HAY REFERENCIA") -> 6 | CT13: =_xlfn.XLOOKUP($B$2,'BASE DE EXCEL'!$C:$C,'BASE DE EXCEL'!N:N,"NO HAY REFERENCIA") -> 6 a 10 días | CU13: =_xlfn.XLOOKUP($B$2,'BASE DE EXCEL'!$C:$C,'BASE DE EXCEL'!O:O,"NO HAY REFERENCIA") -> On Time | CV13: =_xlfn.XLOOKUP(B13,'BASE DE EXCEL'!$C:$C,'BASE DE EXCEL'!P:P,"NO HAY REFERENCIA") -> 16 o más días | CW13: =_xlfn.XLOOKUP(B13,'BASE DE EXCEL'!$C:$C,'BASE DE EXCEL'!Q:Q,"NO HAY REFERENCIA") -> 46029 | CX13: =_xlfn.XLOOKUP(B13,'BASE DE EXCEL'!$C:$C,'BASE DE EXCEL'!R:R,"NO HAY REFERENCIA") -> 17 | CY13: =_xlfn.XLOOKUP(B13,'BASE DE EXCEL'!$C:$C,'BASE DE EXCEL'!S:S,"NO HAY REFERENCIA") -> más de 16 días | CZ13: =_xlfn.XLOOKUP(B13,'BASE DE EXCEL'!$C:$C,'BASE DE EXCEL'!T:T,"NO HAY REFERENCIA") -> Delayed | DA13: =_xlfn.XLOOKUP(B13,'BASE DE EXCEL'!$C:$C,'BASE DE EXCEL'!U:U,"NO HAY REFERENCIA") -> 23 | DB13: =_xlfn.XLOOKUP(B13,'BASE DE EXCEL'!$C:$C,'BASE DE EXCEL'!V:V,"NO HAY REFERENCIA") -> mas de 16 dias | DC13: =_xlfn.XLOOKUP(B13,'BASE DE EXCEL'!$C:$C,'BASE DE EXCEL'!W:W,"NO HAY REFERENCIA") -> 21 | DD13: =_xlfn.XLOOKUP(B13,'BASE DE EXCEL'!$C:$C,'BASE DE EXCEL'!X:X,"NO HAY REFERENCIA") -> más de 16 días | DE13: =_xlfn.XLOOKUP(B13,'BASE DE EXCEL'!$C:$C,'BASE DE EXCEL'!Y:Y,"NO HAY REFERENCIA") -> 1 | DF13: =_xlfn.XLOOKUP(B13,'BASE DE EXCEL'!$C:$C,'BASE DE EXCEL'!Z:Z,"NO HAY REFERENCIA") -> 1 día o menos | DG13: =_xlfn.XLOOKUP(B13,'BASE DE EXCEL'!$C:$C,'BASE DE EXCEL'!AA:AA,"NO HAY REFERENCIA") -> 21 | DH13: =_xlfn.XLOOKUP(B13,'BASE DE EXCEL'!$C:$C,'BASE DE EXCEL'!AB:AB,"NO HAY REFERENCIA") -> 1 | DI13: =_xlfn.XLOOKUP(B13,'BASE DE EXCEL'!$C:$C,'BASE DE EXCEL'!AC:AC,"NO HAY REFERENCIA") -> 1 día o menos | DJ13: =_xlfn.XLOOKUP(B13,'BASE DE EXCEL'!$C:$C,'BASE DE EXCEL'!AD:AD,"NO HAY REFERENCIA") -> 46035 | DK13: =_xlfn.XLOOKUP(B13,'BASE DE EXCEL'!$C:$C,'BASE DE EXCEL'!AE:AE,"NO HAY REFERENCIA") -> 6 | DL13: =_xlfn.XLOOKUP(B13,'BASE DE EXCEL'!$C:$C,'BASE DE EXCEL'!AF:AF,"NO HAY REFERENCIA") -> 4 | DM13: =_xlfn.XLOOKUP(B13,'BASE DE EXCEL'!$C:$C,'BASE DE EXCEL'!AG:AG,"NO HAY REFERENCIA") -> 46035 | DN13: =_xlfn.XLOOKUP(B13,'BASE DE EXCEL'!$C:$C,'BASE DE EXCEL'!AH:AH,"NO HAY REFERENCIA") -> 46035 | DO13: =_xlfn.XLOOKUP(B13,'BASE DE EXCEL'!$C:$C,'BASE DE EXCEL'!AI:AI,"NO HAY REFERENCIA") -> 0 | DP13: =_xlfn.XLOOKUP(B13,'BASE DE EXCEL'!$C:$C,'BASE DE EXCEL'!AJ:AJ,"NO HAY REFERENCIA") -> 6 a 10 días | DQ13: =_xlfn.XLOOKUP(B13,'BASE DE EXCEL'!$C:$C,'BASE DE EXCEL'!AK:AK,"NO HAY REFERENCIA") -> 46035 | DR13: =_xlfn.XLOOKUP(B13,'BASE DE EXCEL'!$C:$C,'BASE DE EXCEL'!AL:AL,"NO HAY REFERENCIA") -> 5 | DS13: =_xlfn.XLOOKUP(B13,'BASE DE EXCEL'!$C:$C,'BASE DE EXCEL'!AM:AM,"NO HAY REFERENCIA") -> 4 a 5 días | DT13: =_xlfn.XLOOKUP(B13,'BASE DE EXCEL'!$C:$C,'BASE DE EXCEL'!AN:AN,"NO HAY REFERENCIA") -> On Time | DU13: =_xlfn.XLOOKUP(B13,'BASE DE EXCEL'!$C:$C,'BASE DE EXCEL'!AO:AO,"NO HAY REFERENCIA") -> 1 | DV13: =_xlfn.XLOOKUP(B13,'BASE DE EXCEL'!$C:$C,'BASE DE EXCEL'!AP:AP,"NO HAY REFERENCIA") -> Es anterior | DW13: =_xlfn.XLOOKUP(B13,'BASE DE EXCEL'!$C:$C,'BASE DE EXCEL'!AQ:AQ,"NO HAY REFERENCIA") -> A1 | DX13: =_xlfn.XLOOKUP(B13,'BASE DE EXCEL'!$C:$C,'BASE DE EXCEL'!AR:AR,"NO HAY REFERENCIA") -> ZULEIMA PEREZ RUIZ | DY13: =_xlfn.XLOOKUP(B13,'BASE DE EXCEL'!$C:$C,'BASE DE EXCEL'!AS:AS,"NO HAY REFERENCIA") -> HLCULE1251059620 | DZ13: =_xlfn.XLOOKUP(B13,'BASE DE EXCEL'!$C:$C,'BASE DE EXCEL'!AT:AT,"NO HAY REFERENCIA") -> NULL | EA13: =_xlfn.XLOOKUP(B13,'BASE DE EXCEL'!$C:$C,'BASE DE EXCEL'!AU:AU,"NO HAY REFERENCIA") -> 6000083 | EB13: =_xlfn.XLOOKUP(B13,'BASE DE EXCEL'!$C:$C,'BASE DE EXCEL'!AV:AV,"NO HAY REFERENCIA") -> Importación | EC13: =_xlfn.XLOOKUP(B13,'BASE DE EXCEL'!$C:$C,'BASE DE EXCEL'!AW:AW,"NO HAY REFERENCIA") -> ZILMAX (PROMOTOR DEL RENDIMIENTO) | ED13: =_xlfn.XLOOKUP(B13,'BASE DE EXCEL'!$C:$C,'BASE DE EXCEL'!AX:AX,"NO HAY REFERENCIA") -> SIN CLASIFICACION | EE13: =_xlfn.XLOOKUP(B13,'BASE DE EXCEL'!$C:$C,'BASE DE EXCEL'!AY:AY,"NO HAY REFERENCIA") -> 0 | EF13: =_xlfn.XLOOKUP(B13,'BASE DE EXCEL'!$C:$C,'BASE DE EXCEL'!AZ:AZ,"NO HAY REFERENCIA") -> Cargas de Importación | EG13: =_xlfn.XLOOKUP(B13,'BASE DE EXCEL'!$C:$C,'BASE DE EXCEL'!BA:BA,"NO HAY REFERENCIA") -> INTERVET MEXICO SA DE CV | EH13: =_xlfn.XLOOKUP(B13,'BASE DE EXCEL'!$C:$C,'BASE DE EXCEL'!BB:BB,"NO HAY REFERENCIA") -> 0 | EI13: =_xlfn.XLOOKUP(B13,'BASE DE EXCEL'!$C:$C,'BASE DE EXCEL'!BC:BC,"NO HAY REFERENCIA") -> FALTA RRNA | EJ13: =_xlfn.XLOOKUP(B13,'BASE DE EXCEL'!$C:$C,'BASE DE EXCEL'!BD:BD,"NO HAY REFERENCIA") -> 0 | EK13: =_xlfn.XLOOKUP(B13,'BASE DE EXCEL'!$C:$C,'BASE DE EXCEL'!BE:BE,"NO HAY REFERENCIA") -> FALTA RRNA | EL13: =_xlfn.XLOOKUP(B13,'BASE DE EXCEL'!$C:$C,'BASE DE EXCEL'!BF:BF,"NO HAY REFERENCIA") -> PRODUCTO TERMINADO | EM13: =_xlfn.XLOOKUP(B13,'BASE DE EXCEL'!$C:$C,'BASE DE EXCEL'!BG:BG,"NO HAY REFERENCIA") -> Verde | EN13: =_xlfn.XLOOKUP(B13,'BASE DE EXCEL'!$C:$C,'BASE DE EXCEL'!BH:BH,"NO HAY REFERENCIA") -> SUPER EXPRESS DE CARGA FEDERAL S.A. DE C.V. | EO13: =_xlfn.XLOOKUP(B13,'BASE DE EXCEL'!$C:$C,'BASE DE EXCEL'!BI:BI,"NO HAY REFERENCIA") -> 0 | EP13: =_xlfn.XLOOKUP(B13,'BASE DE EXCEL'!$C:$C,'BASE DE EXCEL'!BJ:BJ,"NO HAY REFERENCIA") -> IME-T001 | EQ13: =_xlfn.XLOOKUP(B13,'BASE DE EXCEL'!$C:$C,'BASE DE EXCEL'!BK:BK,"NO HAY REFERENCIA") -> IME850329RH2 | ER13: =_xlfn.XLOOKUP(B13,'BASE DE EXCEL'!$C:$C,'BASE DE EXCEL'!BL:BL,"NO HAY REFERENCIA") -> 0 | ES13: =_xlfn.XLOOKUP(B13,'BASE DE EXCEL'!$C:$C,'BASE DE EXCEL'!BM:BM,"NO HAY REFERENCIA") -> 99 | ET13: =_xlfn.XLOOKUP(B13,'BASE DE EXCEL'!$C:$C,'BASE DE EXCEL'!BN:BN,"NO HAY REFERENCIA") -> LOTES: M084A01, M085A01,LOTES: M086A01, M087A01,LOTES: M156A01, M157A01,,LOTES: M158A01, M159A01,LOTES: M160A01, M161A01,LOTES: M162A01, M163A01,LOTES: M164A01, M165A01,LOTES: M180A01, M179A01,LOTES: M178A01, M177A01 | EU13: =_xlfn.XLOOKUP(B13,'BASE DE EXCEL'!$C:$C,'BASE DE EXCEL'!BO:BO,"NO HAY REFERENCIA") -> 90 | EV13: =_xlfn.XLOOKUP(B13,'BASE DE EXCEL'!$C:$C,'BASE DE EXCEL'!BP:BP,"NO HAY REFERENCIA") -> 12581182 | EW13: =_xlfn.XLOOKUP(B13,'BASE DE EXCEL'!$C:$C,'BASE DE EXCEL'!BQ:BQ,"NO HAY REFERENCIA") -> KILO | EX13: =_xlfn.XLOOKUP(B13,'BASE DE EXCEL'!$C:$C,'BASE DE EXCEL'!BR:BR,"NO HAY REFERENCIA") -> 0 | EY13: =_xlfn.XLOOKUP(B13,'BASE DE EXCEL'!$C:$C,'BASE DE EXCEL'!BS:BS,"NO HAY REFERENCIA") -> FRANCIA (REPUBLICA FRANCESA) | EZ13: =_xlfn.XLOOKUP(B13,'BASE DE EXCEL'!$C:$C,'BASE DE EXCEL'!BT:BT,"NO HAY REFERENCIA") -> PAISES BAJOS (REINO DE LOS) (HOLANDA) | FA13: =_xlfn.XLOOKUP(B13,'BASE DE EXCEL'!$C:$C,'BASE DE EXCEL'!BU:BU,"NO HAY REFERENCIA") -> FRA | FB13: =_xlfn.XLOOKUP(B13,'BASE DE EXCEL'!$C:$C,'BASE DE EXCEL'!BV:BV,"NO HAY REFERENCIA") -> ZYA | FC13: =_xlfn.XLOOKUP(B13,QUERY!$C:$C,QUERY!D:D) -> 430 | FD13: =_xlfn.XLOOKUP(B13,QUERY!$C:$C,QUERY!E:E) -> 46027 | FE13: =_xlfn.XLOOKUP(B13,QUERY!$C:$C,QUERY!F:F) -> 1 | FF13: =_xlfn.XLOOKUP(B13,QUERY!$C:$C,QUERY!G:G) -> 46006 | FG13: =_xlfn.XLOOKUP(B13,QUERY!$C:$C,QUERY!H:H) -> 46027 | FH13: =_xlfn.XLOOKUP(B13,QUERY!$C:$C,QUERY!I:I) -> 15 | FI13: =_xlfn.XLOOKUP(B13,QUERY!$C:$C,QUERY!J:J) -> 11 a 15 días | FJ13: =_xlfn.XLOOKUP(B13,QUERY!$C:$C,QUERY!K:K) -> 46028 | FK13: =_xlfn.XLOOKUP(B13,QUERY!$C:$C,QUERY!L:L) -> 16 | FL13: =_xlfn.XLOOKUP(B13,QUERY!$C:$C,QUERY!M:M) -> 16 o más días | FM13: =_xlfn.XLOOKUP(B13,QUERY!$C:$C,QUERY!N:N) -> 1 | FN13: =_xlfn.XLOOKUP(B13,QUERY!$C:$C,QUERY!O:O) -> 1 día o menos | FO13: =_xlfn.XLOOKUP(B13,QUERY!$C:$C,QUERY!P:P) -> 1 | FP13: =_xlfn.XLOOKUP(B13,QUERY!$C:$C,QUERY!Q:Q) -> 1 | FQ13: =_xlfn.XLOOKUP(B13,QUERY!$C:$C,QUERY!R:R) -> 1 día o menos | FR13: =_xlfn.XLOOKUP(B13,QUERY!$C:$C,QUERY!S:S) -> 46029 | FS13: =_xlfn.XLOOKUP(B13,QUERY!$C:$C,QUERY!T:T) -> 17 | FT13: =_xlfn.XLOOKUP(B13,QUERY!$C:$C,QUERY!U:U) -> mas de 16 dias | FU13: =_xlfn.XLOOKUP(B13,QUERY!$C:$C,QUERY!V:V) -> 21 | FV13: =_xlfn.XLOOKUP(B13,QUERY!$C:$C,QUERY!W:W) -> más de 16 días | FW13: =_xlfn.XLOOKUP(B13,QUERY!$C:$C,QUERY!X:X) -> 46035 | FX13: =_xlfn.XLOOKUP(B13,QUERY!$C:$C,QUERY!Y:Y) -> 4 | FY13: =_xlfn.XLOOKUP(B13,QUERY!$C:$C,QUERY!Z:Z) -> 4 | FZ13: =_xlfn.XLOOKUP(B13,QUERY!$C:$C,QUERY!AA:AA) -> 6 a 10 días | GA13: =_xlfn.XLOOKUP(B13,QUERY!$C:$C,QUERY!AB:AB) -> 46035 | GB13: =_xlfn.XLOOKUP(B13,QUERY!$C:$C,QUERY!AC:AC) -> 46035 | GC13: =_xlfn.XLOOKUP(B13,QUERY!$C:$C,QUERY!AD:AD) -> 0 | GD13: =_xlfn.XLOOKUP(B13,QUERY!$C:$C,QUERY!AE:AE) -> 46035 | GE13: =_xlfn.XLOOKUP(B13,QUERY!$C:$C,QUERY!AF:AF) -> 1 | GF13: =_xlfn.XLOOKUP(B13,QUERY!$C:$C,QUERY!AG:AG) -> Es anterior | GG13: =_xlfn.XLOOKUP(B13,QUERY!$C:$C,QUERY!AH:AH) -> A1 | GH13: =_xlfn.XLOOKUP(B13,QUERY!$C:$C,QUERY!AI:AI) -> ZULEIMA PEREZ RUIZ | GI13: =_xlfn.XLOOKUP(B13,QUERY!$C:$C,QUERY!AJ:AJ) -> HLCULE1251059620 | GJ13: =_xlfn.XLOOKUP(B13,QUERY!$C:$C,QUERY!AK:AK) -> NULL | GK13: =_xlfn.XLOOKUP(B13,QUERY!$C:$C,QUERY!AL:AL) -> 6000083 | GL13: =_xlfn.XLOOKUP(B13,QUERY!$C:$C,QUERY!AM:AM) -> Importación | GM13: =_xlfn.XLOOKUP(B13,QUERY!$C:$C,QUERY!AN:AN) -> ZILMAX (PROMOTOR DEL RENDIMIENTO) | GN13: =_xlfn.XLOOKUP(B13,QUERY!$C:$C,QUERY!AO:AO) -> SIN CLASIFICACION | GO13: =_xlfn.XLOOKUP(B13,QUERY!$C:$C,QUERY!AP:AP) -> 0 | GP13: =_xlfn.XLOOKUP(B13,QUERY!$C:$C,QUERY!AQ:AQ) -> Cargas de Importación | GQ13: =_xlfn.XLOOKUP(B13,QUERY!$C:$C,QUERY!AR:AR) -> INTERVET MEXICO SA DE CV | GR13: =_xlfn.XLOOKUP(B13,QUERY!$C:$C,QUERY!AS:AS) -> 0 | GS13: =_xlfn.XLOOKUP(B13,QUERY!$C:$C,QUERY!AT:AT) -> FALTA RRNA | GT13: =_xlfn.XLOOKUP(B13,QUERY!$C:$C,QUERY!AU:AU) -> 0 | GU13: =_xlfn.XLOOKUP(B13,QUERY!$C:$C,QUERY!AV:AV) -> FALTA RRNA | GV13: =_xlfn.XLOOKUP(B13,QUERY!$C:$C,QUERY!AW:AW) -> PRODUCTO TERMINADO | GW13: =_xlfn.XLOOKUP(B13,QUERY!$C:$C,QUERY!AX:AX) -> Verde | GX13: =_xlfn.XLOOKUP(B13,QUERY!$C:$C,QUERY!AY:AY) -> SUPER EXPRESS DE CARGA FEDERAL S.A. DE C.V. | GY13: =_xlfn.XLOOKUP(B13,QUERY!$C:$C,QUERY!AZ:AZ) -> 0 | GZ13: =_xlfn.XLOOKUP(B13,QUERY!$C:$C,QUERY!BA:BA) -> IME-T001 | HA13: =_xlfn.XLOOKUP(B13,QUERY!$C:$C,QUERY!BB:BB) -> IME850329RH2 | HB13: =_xlfn.XLOOKUP(B13,QUERY!$C:$C,QUERY!BC:BC) -> 0 | HC13: =_xlfn.XLOOKUP(B13,QUERY!$C:$C,QUERY!BD:BD) -> 99 | HD13: =_xlfn.XLOOKUP(B13,QUERY!$C:$C,QUERY!BE:BE) -> LOTES: M084A01, M085A01,LOTES: M086A01, M087A01,LOTES: M156A01, M157A01,,LOTES: M158A01, M159A01,LOTES: M160A01, M161A01,LOTES: M162A01, M163A01,LOTES: M164A01, M165A01,LOTES: M180A01, M179A01,LOTES: M178A01, M177A01 | HE13: =_xlfn.XLOOKUP(B13,QUERY!$C:$C,QUERY!BF:BF) -> 90 | HF13: =_xlfn.XLOOKUP(B13,QUERY!$C:$C,QUERY!BG:BG) -> 12581182.40 | HG13: =_xlfn.XLOOKUP(B13,QUERY!$C:$C,QUERY!BH:BH) -> KILO | HH13: =_xlfn.XLOOKUP(B13,QUERY!$C:$C,QUERY!BI:BI) -> 0 | HI13: =_xlfn.XLOOKUP(B13,QUERY!$C:$C,QUERY!BJ:BJ) -> FRANCIA (REPUBLICA FRANCESA) | HJ13: =_xlfn.XLOOKUP(B13,QUERY!$C:$C,QUERY!BK:BK) -> PAISES BAJOS (REINO DE LOS) (HOLANDA) | HK13: =_xlfn.XLOOKUP(B13,QUERY!$C:$C,QUERY!BL:BL) -> FRA | HL13: =_xlfn.XLOOKUP(B13,QUERY!$C:$C,QUERY!BM:BM) -> ZYA | HM13: =_xlfn.XLOOKUP(B13,QUERY!$C:$C,QUERY!BN:BN) -> 12581182 | HN13: =_xlfn.XLOOKUP(B13,QUERY!$C:$C,QUERY!BO:BO) -> 100649.00 | HO13: =_xlfn.XLOOKUP(B13,QUERY!$C:$C,QUERY!BP:BP) -> NULL | HP13: =_xlfn.XLOOKUP(B13,QUERY!$C:$C,QUERY!BQ:BQ) -> NULL | HQ13: =_xlfn.XLOOKUP(B13,QUERY!$C:$C,QUERY!BR:BR) -> 375823.69 | HR13: =_xlfn.XLOOKUP(B13,QUERY!$C:$C,QUERY!BS:BS) -> 0 | HS13: =_xlfn.XLOOKUP(B13,QUERY!$C:$C,QUERY!BT:BT) -> 0 | HT13: =_xlfn.XLOOKUP(B13,QUERY!$C:$C,QUERY!A:A) -> VERACRUZ | HU13: =_xlfn.XLOOKUP(B13,QUERY!$C:$C,QUERY!B:B) -> MARÍTIMO VERACRUZ
A14: INTERVET MEXICO SA DE CV | B14: VER-25-1250-1 | C14: 3942 | D14: 6000299 | F14: Importación | G14: A1 | H14: 0 | I14: 0 | J14: 0 | K14: 0 | L14: 0 | M14: 0 | N14: 0 | O14: 0 | P14: 18.2085 | Q14: 546 | R14: 430 | T14: S/M Y S/N, 1 PALLETS | U14: 741815 | V14: 741815 | W14: 0 | X14: 0 | Y14: 0 | Z14: 0 | AA14: ZILMAX (PROMOTOR DEL RENDIMIENTO) | AC14: 741815 | AD14: 14836.3 | AE14: 354 | AF14: 0 | AG14: 0 | AH14: 0 | AI14: 53 | AJ14: 5935 | AK14: 0 | AL14: 0 | AM14: 330 | AN14: 6318 | AO14: Cliente | AP14: INTERVET INTERNATIONAL BV | AQ14: 210358461 | AR14: CIP | AS14: MXP | AT14: HLCULE1251059620 | AV14: TEC | AW14: 23099099 | AX14: 99 | AY14: 50 | AZ14: 50 | BA14: PIEZA | BC14: FRA | BD14: ZYA | BE14: DESADUANAMIENTO LIBRE | BF14: FALTA RRNA | BG14: 4.3064022e+16 | BH14: A1 | BJ14: DE CONFORMIDAD CON EL ART. 36- | BK14: COVE267WBI7G5 | BL14: 43356 | BM14: 0 | BN14: 0 | BO14: 0 | BP14: 0 | BQ14: 0 | BR14: 0 | BS14: 0 | BT14: 0 | BU14: 0 | BV14: 0 | BW14: 0 | BX14: 22189.59 | BY14: 0 | BZ14: 0 | CA14: 0 | CB14: 5600 | CC14: 1358.4 | CD14: 114307.79 | CE14: PEDIENTE DE PAGO | CF14: 114307.79 | CG14: 0 | CH14: 0 | CI14: ZULEIMA PEREZ RUIZ | CJ14: ZULEIMA PEREZ RUIZ | CK14: =_xlfn.XLOOKUP($B$2,'BASE DE EXCEL'!C:C,'BASE DE EXCEL'!D:D,"NO HAY REFERENCIA") -> 470 | CL14: =_xlfn.XLOOKUP($B$2,'BASE DE EXCEL'!$C:$C,'BASE DE EXCEL'!F:F,"NO HAY REFERENCIA") -> 3 | CM14: =_xlfn.XLOOKUP($B$2,'BASE DE EXCEL'!$C:$C,'BASE DE EXCEL'!G:G,"NO HAY REFERENCIA") -> 46080 | CN14: =_xlfn.XLOOKUP($B$2,'BASE DE EXCEL'!$C:$C,'BASE DE EXCEL'!H:H,"NO HAY REFERENCIA") -> 46086 | CO14: =_xlfn.XLOOKUP($B$2,'BASE DE EXCEL'!$C:$C,'BASE DE EXCEL'!I:I,"NO HAY REFERENCIA") -> 4 | CP14: =_xlfn.XLOOKUP($B$2,'BASE DE EXCEL'!$C:$C,'BASE DE EXCEL'!J:J,"NO HAY REFERENCIA") -> 4 a 5 días | CQ14: =_xlfn.XLOOKUP($B$2,'BASE DE EXCEL'!$C:$C,'BASE DE EXCEL'!K:K,"NO HAY REFERENCIA") -> 46087 | CR14: =_xlfn.XLOOKUP($B$2,'BASE DE EXCEL'!$C:$C,'BASE DE EXCEL'!L:L,"NO HAY REFERENCIA") -> 5 | CS14: =_xlfn.XLOOKUP($B$2,'BASE DE EXCEL'!$C:$C,'BASE DE EXCEL'!M:M,"NO HAY REFERENCIA") -> 6 | CT14: =_xlfn.XLOOKUP($B$2,'BASE DE EXCEL'!$C:$C,'BASE DE EXCEL'!N:N,"NO HAY REFERENCIA") -> 6 a 10 días | CU14: =_xlfn.XLOOKUP($B$2,'BASE DE EXCEL'!$C:$C,'BASE DE EXCEL'!O:O,"NO HAY REFERENCIA") -> On Time | CV14: =_xlfn.XLOOKUP(B14,'BASE DE EXCEL'!$C:$C,'BASE DE EXCEL'!P:P,"NO HAY REFERENCIA") -> 16 o más días | CW14: =_xlfn.XLOOKUP(B14,'BASE DE EXCEL'!$C:$C,'BASE DE EXCEL'!Q:Q,"NO HAY REFERENCIA") -> 46080 | CX14: =_xlfn.XLOOKUP(B14,'BASE DE EXCEL'!$C:$C,'BASE DE EXCEL'!R:R,"NO HAY REFERENCIA") -> 53 | CY14: =_xlfn.XLOOKUP(B14,'BASE DE EXCEL'!$C:$C,'BASE DE EXCEL'!S:S,"NO HAY REFERENCIA") -> más de 16 días | CZ14: =_xlfn.XLOOKUP(B14,'BASE DE EXCEL'!$C:$C,'BASE DE EXCEL'!T:T,"NO HAY REFERENCIA") -> Delayed | DA14: =_xlfn.XLOOKUP(B14,'BASE DE EXCEL'!$C:$C,'BASE DE EXCEL'!U:U,"NO HAY REFERENCIA") -> 74 | DB14: =_xlfn.XLOOKUP(B14,'BASE DE EXCEL'!$C:$C,'BASE DE EXCEL'!V:V,"NO HAY REFERENCIA") -> mas de 16 dias | DC14: =_xlfn.XLOOKUP(B14,'BASE DE EXCEL'!$C:$C,'BASE DE EXCEL'!W:W,"NO HAY REFERENCIA") -> 58 | DD14: =_xlfn.XLOOKUP(B14,'BASE DE EXCEL'!$C:$C,'BASE DE EXCEL'!X:X,"NO HAY REFERENCIA") -> más de 16 días | DE14: =_xlfn.XLOOKUP(B14,'BASE DE EXCEL'!$C:$C,'BASE DE EXCEL'!Y:Y,"NO HAY REFERENCIA") -> 1 | DF14: =_xlfn.XLOOKUP(B14,'BASE DE EXCEL'!$C:$C,'BASE DE EXCEL'!Z:Z,"NO HAY REFERENCIA") -> 1 día o menos | DG14: =_xlfn.XLOOKUP(B14,'BASE DE EXCEL'!$C:$C,'BASE DE EXCEL'!AA:AA,"NO HAY REFERENCIA") -> 72 | DH14: =_xlfn.XLOOKUP(B14,'BASE DE EXCEL'!$C:$C,'BASE DE EXCEL'!AB:AB,"NO HAY REFERENCIA") -> 1 | DI14: =_xlfn.XLOOKUP(B14,'BASE DE EXCEL'!$C:$C,'BASE DE EXCEL'!AC:AC,"NO HAY REFERENCIA") -> 1 día o menos | DJ14: =_xlfn.XLOOKUP(B14,'BASE DE EXCEL'!$C:$C,'BASE DE EXCEL'!AD:AD,"NO HAY REFERENCIA") -> 46086 | DK14: =_xlfn.XLOOKUP(B14,'BASE DE EXCEL'!$C:$C,'BASE DE EXCEL'!AE:AE,"NO HAY REFERENCIA") -> 6 | DL14: =_xlfn.XLOOKUP(B14,'BASE DE EXCEL'!$C:$C,'BASE DE EXCEL'!AF:AF,"NO HAY REFERENCIA") -> 4 | DM14: =_xlfn.XLOOKUP(B14,'BASE DE EXCEL'!$C:$C,'BASE DE EXCEL'!AG:AG,"NO HAY REFERENCIA") -> 46086 | DN14: =_xlfn.XLOOKUP(B14,'BASE DE EXCEL'!$C:$C,'BASE DE EXCEL'!AH:AH,"NO HAY REFERENCIA") -> 46086 | DO14: =_xlfn.XLOOKUP(B14,'BASE DE EXCEL'!$C:$C,'BASE DE EXCEL'!AI:AI,"NO HAY REFERENCIA") -> 0 | DP14: =_xlfn.XLOOKUP(B14,'BASE DE EXCEL'!$C:$C,'BASE DE EXCEL'!AJ:AJ,"NO HAY REFERENCIA") -> 6 a 10 días | DQ14: =_xlfn.XLOOKUP(B14,'BASE DE EXCEL'!$C:$C,'BASE DE EXCEL'!AK:AK,"NO HAY REFERENCIA") -> 46086 | DR14: =_xlfn.XLOOKUP(B14,'BASE DE EXCEL'!$C:$C,'BASE DE EXCEL'!AL:AL,"NO HAY REFERENCIA") -> 5 | DS14: =_xlfn.XLOOKUP(B14,'BASE DE EXCEL'!$C:$C,'BASE DE EXCEL'!AM:AM,"NO HAY REFERENCIA") -> 4 a 5 días | DT14: =_xlfn.XLOOKUP(B14,'BASE DE EXCEL'!$C:$C,'BASE DE EXCEL'!AN:AN,"NO HAY REFERENCIA") -> On Time | DU14: =_xlfn.XLOOKUP(B14,'BASE DE EXCEL'!$C:$C,'BASE DE EXCEL'!AO:AO,"NO HAY REFERENCIA") -> 1 | DV14: =_xlfn.XLOOKUP(B14,'BASE DE EXCEL'!$C:$C,'BASE DE EXCEL'!AP:AP,"NO HAY REFERENCIA") -> Es anterior | DW14: =_xlfn.XLOOKUP(B14,'BASE DE EXCEL'!$C:$C,'BASE DE EXCEL'!AQ:AQ,"NO HAY REFERENCIA") -> A1 | DX14: =_xlfn.XLOOKUP(B14,'BASE DE EXCEL'!$C:$C,'BASE DE EXCEL'!AR:AR,"NO HAY REFERENCIA") -> ZULEIMA PEREZ RUIZ | DY14: =_xlfn.XLOOKUP(B14,'BASE DE EXCEL'!$C:$C,'BASE DE EXCEL'!AS:AS,"NO HAY REFERENCIA") -> HLCULE1251059620 | DZ14: =_xlfn.XLOOKUP(B14,'BASE DE EXCEL'!$C:$C,'BASE DE EXCEL'!AT:AT,"NO HAY REFERENCIA") -> NULL | EA14: =_xlfn.XLOOKUP(B14,'BASE DE EXCEL'!$C:$C,'BASE DE EXCEL'!AU:AU,"NO HAY REFERENCIA") -> 6000299 | EB14: =_xlfn.XLOOKUP(B14,'BASE DE EXCEL'!$C:$C,'BASE DE EXCEL'!AV:AV,"NO HAY REFERENCIA") -> Importación | EC14: =_xlfn.XLOOKUP(B14,'BASE DE EXCEL'!$C:$C,'BASE DE EXCEL'!AW:AW,"NO HAY REFERENCIA") -> ZILMAX (PROMOTOR DEL RENDIMIENTO) | ED14: =_xlfn.XLOOKUP(B14,'BASE DE EXCEL'!$C:$C,'BASE DE EXCEL'!AX:AX,"NO HAY REFERENCIA") -> SIN CLASIFICACION | EE14: =_xlfn.XLOOKUP(B14,'BASE DE EXCEL'!$C:$C,'BASE DE EXCEL'!AY:AY,"NO HAY REFERENCIA") -> 0 | EF14: =_xlfn.XLOOKUP(B14,'BASE DE EXCEL'!$C:$C,'BASE DE EXCEL'!AZ:AZ,"NO HAY REFERENCIA") -> Cargas de Importación | EG14: =_xlfn.XLOOKUP(B14,'BASE DE EXCEL'!$C:$C,'BASE DE EXCEL'!BA:BA,"NO HAY REFERENCIA") -> INTERVET MEXICO SA DE CV | EH14: =_xlfn.XLOOKUP(B14,'BASE DE EXCEL'!$C:$C,'BASE DE EXCEL'!BB:BB,"NO HAY REFERENCIA") -> 0 | EI14: =_xlfn.XLOOKUP(B14,'BASE DE EXCEL'!$C:$C,'BASE DE EXCEL'!BC:BC,"NO HAY REFERENCIA") -> FALTA RRNA | EJ14: =_xlfn.XLOOKUP(B14,'BASE DE EXCEL'!$C:$C,'BASE DE EXCEL'!BD:BD,"NO HAY REFERENCIA") -> 0 | EK14: =_xlfn.XLOOKUP(B14,'BASE DE EXCEL'!$C:$C,'BASE DE EXCEL'!BE:BE,"NO HAY REFERENCIA") -> FALTA RRNA | EL14: =_xlfn.XLOOKUP(B14,'BASE DE EXCEL'!$C:$C,'BASE DE EXCEL'!BF:BF,"NO HAY REFERENCIA") -> PRODUCTO TERMINADO | EM14: =_xlfn.XLOOKUP(B14,'BASE DE EXCEL'!$C:$C,'BASE DE EXCEL'!BG:BG,"NO HAY REFERENCIA") -> Verde | EN14: =_xlfn.XLOOKUP(B14,'BASE DE EXCEL'!$C:$C,'BASE DE EXCEL'!BH:BH,"NO HAY REFERENCIA") -> SERVEX TRANSPORTES SA DE CV | EO14: =_xlfn.XLOOKUP(B14,'BASE DE EXCEL'!$C:$C,'BASE DE EXCEL'!BI:BI,"NO HAY REFERENCIA") -> ECONOMICO 09 | EP14: =_xlfn.XLOOKUP(B14,'BASE DE EXCEL'!$C:$C,'BASE DE EXCEL'!BJ:BJ,"NO HAY REFERENCIA") -> 0 | EQ14: =_xlfn.XLOOKUP(B14,'BASE DE EXCEL'!$C:$C,'BASE DE EXCEL'!BK:BK,"NO HAY REFERENCIA") -> IME850329RH2 | ER14: =_xlfn.XLOOKUP(B14,'BASE DE EXCEL'!$C:$C,'BASE DE EXCEL'!BL:BL,"NO HAY REFERENCIA") -> 0 | ES14: =_xlfn.XLOOKUP(B14,'BASE DE EXCEL'!$C:$C,'BASE DE EXCEL'!BM:BM,"NO HAY REFERENCIA") -> 99 | ET14: =_xlfn.XLOOKUP(B14,'BASE DE EXCEL'!$C:$C,'BASE DE EXCEL'!BN:BN,"NO HAY REFERENCIA") -> LOTES: M084A01, M085A01,LOTES: M086A01, M087A01,LOTES: M156A01, M157A01,,LOTES: M158A01, M159A01,LOTES: M160A01, M161A01,LOTES: M162A01, M163A01,LOTES: M164A01, M165A01,LOTES: M180A01, M179A01,LOTES: M178A01, M177A01 | EU14: =_xlfn.XLOOKUP(B14,'BASE DE EXCEL'!$C:$C,'BASE DE EXCEL'!BO:BO,"NO HAY REFERENCIA") -> 90 | EV14: =_xlfn.XLOOKUP(B14,'BASE DE EXCEL'!$C:$C,'BASE DE EXCEL'!BP:BP,"NO HAY REFERENCIA") -> 741815 | EW14: =_xlfn.XLOOKUP(B14,'BASE DE EXCEL'!$C:$C,'BASE DE EXCEL'!BQ:BQ,"NO HAY REFERENCIA") -> KILO | EX14: =_xlfn.XLOOKUP(B14,'BASE DE EXCEL'!$C:$C,'BASE DE EXCEL'!BR:BR,"NO HAY REFERENCIA") -> 0 | EY14: =_xlfn.XLOOKUP(B14,'BASE DE EXCEL'!$C:$C,'BASE DE EXCEL'!BS:BS,"NO HAY REFERENCIA") -> FRANCIA (REPUBLICA FRANCESA) | EZ14: =_xlfn.XLOOKUP(B14,'BASE DE EXCEL'!$C:$C,'BASE DE EXCEL'!BT:BT,"NO HAY REFERENCIA") -> PAISES BAJOS (REINO DE LOS) (HOLANDA) | FA14: =_xlfn.XLOOKUP(B14,'BASE DE EXCEL'!$C:$C,'BASE DE EXCEL'!BU:BU,"NO HAY REFERENCIA") -> FRA | FB14: =_xlfn.XLOOKUP(B14,'BASE DE EXCEL'!$C:$C,'BASE DE EXCEL'!BV:BV,"NO HAY REFERENCIA") -> ZYA | FC14: =_xlfn.XLOOKUP(B14,QUERY!$C:$C,QUERY!D:D) -> 430 | FD14: =_xlfn.XLOOKUP(B14,QUERY!$C:$C,QUERY!E:E) -> 46078 | FE14: =_xlfn.XLOOKUP(B14,QUERY!$C:$C,QUERY!F:F) -> 2 | FF14: =_xlfn.XLOOKUP(B14,QUERY!$C:$C,QUERY!G:G) -> 46006 | FG14: =_xlfn.XLOOKUP(B14,QUERY!$C:$C,QUERY!H:H) -> 46078 | FH14: =_xlfn.XLOOKUP(B14,QUERY!$C:$C,QUERY!I:I) -> 52 | FI14: =_xlfn.XLOOKUP(B14,QUERY!$C:$C,QUERY!J:J) -> 16 o más días | FJ14: =_xlfn.XLOOKUP(B14,QUERY!$C:$C,QUERY!K:K) -> 46079 | FK14: =_xlfn.XLOOKUP(B14,QUERY!$C:$C,QUERY!L:L) -> 53 | FL14: =_xlfn.XLOOKUP(B14,QUERY!$C:$C,QUERY!M:M) -> 16 o más días | FM14: =_xlfn.XLOOKUP(B14,QUERY!$C:$C,QUERY!N:N) -> 1 | FN14: =_xlfn.XLOOKUP(B14,QUERY!$C:$C,QUERY!O:O) -> 1 día o menos | FO14: =_xlfn.XLOOKUP(B14,QUERY!$C:$C,QUERY!P:P) -> 1 | FP14: =_xlfn.XLOOKUP(B14,QUERY!$C:$C,QUERY!Q:Q) -> 1 | FQ14: =_xlfn.XLOOKUP(B14,QUERY!$C:$C,QUERY!R:R) -> 1 día o menos | FR14: =_xlfn.XLOOKUP(B14,QUERY!$C:$C,QUERY!S:S) -> 46080 | FS14: =_xlfn.XLOOKUP(B14,QUERY!$C:$C,QUERY!T:T) -> 54 | FT14: =_xlfn.XLOOKUP(B14,QUERY!$C:$C,QUERY!U:U) -> mas de 16 dias | FU14: =_xlfn.XLOOKUP(B14,QUERY!$C:$C,QUERY!V:V) -> 58 | FV14: =_xlfn.XLOOKUP(B14,QUERY!$C:$C,QUERY!W:W) -> más de 16 días | FW14: =_xlfn.XLOOKUP(B14,QUERY!$C:$C,QUERY!X:X) -> 46086 | FX14: =_xlfn.XLOOKUP(B14,QUERY!$C:$C,QUERY!Y:Y) -> 4 | FY14: =_xlfn.XLOOKUP(B14,QUERY!$C:$C,QUERY!Z:Z) -> 4 | FZ14: =_xlfn.XLOOKUP(B14,QUERY!$C:$C,QUERY!AA:AA) -> 6 a 10 días | GA14: =_xlfn.XLOOKUP(B14,QUERY!$C:$C,QUERY!AB:AB) -> 46086 | GB14: =_xlfn.XLOOKUP(B14,QUERY!$C:$C,QUERY!AC:AC) -> 46086 | GC14: =_xlfn.XLOOKUP(B14,QUERY!$C:$C,QUERY!AD:AD) -> 0 | GD14: =_xlfn.XLOOKUP(B14,QUERY!$C:$C,QUERY!AE:AE) -> 46086 | GE14: =_xlfn.XLOOKUP(B14,QUERY!$C:$C,QUERY!AF:AF) -> 1 | GF14: =_xlfn.XLOOKUP(B14,QUERY!$C:$C,QUERY!AG:AG) -> Es anterior | GG14: =_xlfn.XLOOKUP(B14,QUERY!$C:$C,QUERY!AH:AH) -> A1 | GH14: =_xlfn.XLOOKUP(B14,QUERY!$C:$C,QUERY!AI:AI) -> ZULEIMA PEREZ RUIZ | GI14: =_xlfn.XLOOKUP(B14,QUERY!$C:$C,QUERY!AJ:AJ) -> HLCULE1251059620 | GJ14: =_xlfn.XLOOKUP(B14,QUERY!$C:$C,QUERY!AK:AK) -> NULL | GK14: =_xlfn.XLOOKUP(B14,QUERY!$C:$C,QUERY!AL:AL) -> 6000299 | GL14: =_xlfn.XLOOKUP(B14,QUERY!$C:$C,QUERY!AM:AM) -> Importación | GM14: =_xlfn.XLOOKUP(B14,QUERY!$C:$C,QUERY!AN:AN) -> ZILMAX (PROMOTOR DEL RENDIMIENTO) | GN14: =_xlfn.XLOOKUP(B14,QUERY!$C:$C,QUERY!AO:AO) -> SIN CLASIFICACION | GO14: =_xlfn.XLOOKUP(B14,QUERY!$C:$C,QUERY!AP:AP) -> 0 | GP14: =_xlfn.XLOOKUP(B14,QUERY!$C:$C,QUERY!AQ:AQ) -> Cargas de Importación | GQ14: =_xlfn.XLOOKUP(B14,QUERY!$C:$C,QUERY!AR:AR) -> INTERVET MEXICO SA DE CV | GR14: =_xlfn.XLOOKUP(B14,QUERY!$C:$C,QUERY!AS:AS) -> 0 | GS14: =_xlfn.XLOOKUP(B14,QUERY!$C:$C,QUERY!AT:AT) -> FALTA RRNA | GT14: =_xlfn.XLOOKUP(B14,QUERY!$C:$C,QUERY!AU:AU) -> 0 | GU14: =_xlfn.XLOOKUP(B14,QUERY!$C:$C,QUERY!AV:AV) -> FALTA RRNA | GV14: =_xlfn.XLOOKUP(B14,QUERY!$C:$C,QUERY!AW:AW) -> PRODUCTO TERMINADO | GW14: =_xlfn.XLOOKUP(B14,QUERY!$C:$C,QUERY!AX:AX) -> Verde | GX14: =_xlfn.XLOOKUP(B14,QUERY!$C:$C,QUERY!AY:AY) -> SERVEX TRANSPORTES SA DE CV | GY14: =_xlfn.XLOOKUP(B14,QUERY!$C:$C,QUERY!AZ:AZ) -> ECONOMICO 09 | GZ14: =_xlfn.XLOOKUP(B14,QUERY!$C:$C,QUERY!BA:BA) -> 0 | HA14: =_xlfn.XLOOKUP(B14,QUERY!$C:$C,QUERY!BB:BB) -> IME850329RH2 | HB14: =_xlfn.XLOOKUP(B14,QUERY!$C:$C,QUERY!BC:BC) -> 0 | HC14: =_xlfn.XLOOKUP(B14,QUERY!$C:$C,QUERY!BD:BD) -> 99 | HD14: =_xlfn.XLOOKUP(B14,QUERY!$C:$C,QUERY!BE:BE) -> LOTES: M084A01, M085A01,LOTES: M086A01, M087A01,LOTES: M156A01, M157A01,,LOTES: M158A01, M159A01,LOTES: M160A01, M161A01,LOTES: M162A01, M163A01,LOTES: M164A01, M165A01,LOTES: M180A01, M179A01,LOTES: M178A01, M177A01 | HE14: =_xlfn.XLOOKUP(B14,QUERY!$C:$C,QUERY!BF:BF) -> 90 | HF14: =_xlfn.XLOOKUP(B14,QUERY!$C:$C,QUERY!BG:BG) -> 741815.00 | HG14: =_xlfn.XLOOKUP(B14,QUERY!$C:$C,QUERY!BH:BH) -> KILO | HH14: =_xlfn.XLOOKUP(B14,QUERY!$C:$C,QUERY!BI:BI) -> 0 | HI14: =_xlfn.XLOOKUP(B14,QUERY!$C:$C,QUERY!BJ:BJ) -> FRANCIA (REPUBLICA FRANCESA) | HJ14: =_xlfn.XLOOKUP(B14,QUERY!$C:$C,QUERY!BK:BK) -> PAISES BAJOS (REINO DE LOS) (HOLANDA) | HK14: =_xlfn.XLOOKUP(B14,QUERY!$C:$C,QUERY!BL:BL) -> FRA | HL14: =_xlfn.XLOOKUP(B14,QUERY!$C:$C,QUERY!BM:BM) -> ZYA | HM14: =_xlfn.XLOOKUP(B14,QUERY!$C:$C,QUERY!BN:BN) -> 741815 | HN14: =_xlfn.XLOOKUP(B14,QUERY!$C:$C,QUERY!BO:BO) -> 5935.00 | HO14: =_xlfn.XLOOKUP(B14,QUERY!$C:$C,QUERY!BP:BP) -> NULL | HP14: =_xlfn.XLOOKUP(B14,QUERY!$C:$C,QUERY!BQ:BQ) -> NULL | HQ14: =_xlfn.XLOOKUP(B14,QUERY!$C:$C,QUERY!BR:BR) -> 114307.79 | HR14: =_xlfn.XLOOKUP(B14,QUERY!$C:$C,QUERY!BS:BS) -> 0 | HS14: =_xlfn.XLOOKUP(B14,QUERY!$C:$C,QUERY!BT:BT) -> 0 | HT14: =_xlfn.XLOOKUP(B14,QUERY!$C:$C,QUERY!A:A) -> VERACRUZ | HU14: =_xlfn.XLOOKUP(B14,QUERY!$C:$C,QUERY!B:B) -> MARÍTIMO VERACRUZ
A15: INTERVET MEXICO SA DE CV | B15: VER-25-1273-1 | C15: 3942 | D15: 6000133 | F15: Importación | G15: A1 | H15: 0 | I15: 0 | J15: 0 | K15: 0 | L15: 0 | M15: 0 | N15: 0 | O15: 0 | P15: 18.2085 | Q15: 276 | R15: 430 | T15: S/M Y S/N, 1 PALLET | U15: 4939600 | V15: 4939600 | W15: 0 | X15: 0 | Y15: 0 | Z15: 0 | AA15: ROTAVEC CORONA (VACUNA DE USO VETERINARIO) | AC15: 4939600 | AD15: 1234.9 | AE15: 808 | AF15: 0 | AG15: 0 | AH15: 0 | AI15: 53 | AJ15: 462 | AK15: 0 | AL15: 0 | AM15: 330 | AN15: 845 | AO15: Cliente | AP15: INTERVET INTERNATIONAL BV | AQ15: 210358877 | AR15: CIP | AS15: MXP | AT15: HLCURTM251142982 | AV15: REFRIGERADO | AW15: 30024201 | AX15: 99 | AY15: 4000 | AZ15: 4000 | BA15: PIEZA | BC15: ZYA | BD15: ZYA | BE15: DESADUANAMIENTO LIBRE | BF15: FALTA RRNA | BG15: 4.3064022e+16 | BH15: A1 | BJ15: DE CONFORMIDAD CON EL ART. 36- | BK15: COVE267WZ8ML2 | BL15: 41810 | BM15: 0 | BN15: 0 | BO15: 0 | BP15: 0 | BQ15: 0 | BR15: 0 | BS15: 0 | BT15: 0 | BU15: 0 | BV15: 0 | BW15: 0 | BX15: 22189.59 | BY15: 0 | BZ15: 0 | CA15: 0 | CB15: 7033.06 | CC15: 1587.69 | CD15: 94680.66 | CE15: PAGADO | CF15: 94680.66 | CG15: 94680.66 | CH15: 0 | CI15: ZULEIMA PEREZ RUIZ | CJ15: ZULEIMA PEREZ RUIZ | CK15: =_xlfn.XLOOKUP($B$2,'BASE DE EXCEL'!C:C,'BASE DE EXCEL'!D:D,"NO HAY REFERENCIA") -> 470 | CL15: =_xlfn.XLOOKUP($B$2,'BASE DE EXCEL'!$C:$C,'BASE DE EXCEL'!F:F,"NO HAY REFERENCIA") -> 3 | CM15: =_xlfn.XLOOKUP($B$2,'BASE DE EXCEL'!$C:$C,'BASE DE EXCEL'!G:G,"NO HAY REFERENCIA") -> 46080 | CN15: =_xlfn.XLOOKUP($B$2,'BASE DE EXCEL'!$C:$C,'BASE DE EXCEL'!H:H,"NO HAY REFERENCIA") -> 46086 | CO15: =_xlfn.XLOOKUP($B$2,'BASE DE EXCEL'!$C:$C,'BASE DE EXCEL'!I:I,"NO HAY REFERENCIA") -> 4 | CP15: =_xlfn.XLOOKUP($B$2,'BASE DE EXCEL'!$C:$C,'BASE DE EXCEL'!J:J,"NO HAY REFERENCIA") -> 4 a 5 días | CQ15: =_xlfn.XLOOKUP($B$2,'BASE DE EXCEL'!$C:$C,'BASE DE EXCEL'!K:K,"NO HAY REFERENCIA") -> 46087 | CR15: =_xlfn.XLOOKUP($B$2,'BASE DE EXCEL'!$C:$C,'BASE DE EXCEL'!L:L,"NO HAY REFERENCIA") -> 5 | CS15: =_xlfn.XLOOKUP($B$2,'BASE DE EXCEL'!$C:$C,'BASE DE EXCEL'!M:M,"NO HAY REFERENCIA") -> 6 | CT15: =_xlfn.XLOOKUP($B$2,'BASE DE EXCEL'!$C:$C,'BASE DE EXCEL'!N:N,"NO HAY REFERENCIA") -> 6 a 10 días | CU15: =_xlfn.XLOOKUP($B$2,'BASE DE EXCEL'!$C:$C,'BASE DE EXCEL'!O:O,"NO HAY REFERENCIA") -> On Time | CV15: =_xlfn.XLOOKUP(B15,'BASE DE EXCEL'!$C:$C,'BASE DE EXCEL'!P:P,"NO HAY REFERENCIA") -> 16 o más días | CW15: =_xlfn.XLOOKUP(B15,'BASE DE EXCEL'!$C:$C,'BASE DE EXCEL'!Q:Q,"NO HAY REFERENCIA") -> 46042 | CX15: =_xlfn.XLOOKUP(B15,'BASE DE EXCEL'!$C:$C,'BASE DE EXCEL'!R:R,"NO HAY REFERENCIA") -> 26 | CY15: =_xlfn.XLOOKUP(B15,'BASE DE EXCEL'!$C:$C,'BASE DE EXCEL'!S:S,"NO HAY REFERENCIA") -> más de 16 días | CZ15: =_xlfn.XLOOKUP(B15,'BASE DE EXCEL'!$C:$C,'BASE DE EXCEL'!T:T,"NO HAY REFERENCIA") -> Delayed | DA15: =_xlfn.XLOOKUP(B15,'BASE DE EXCEL'!$C:$C,'BASE DE EXCEL'!U:U,"NO HAY REFERENCIA") -> 36 | DB15: =_xlfn.XLOOKUP(B15,'BASE DE EXCEL'!$C:$C,'BASE DE EXCEL'!V:V,"NO HAY REFERENCIA") -> mas de 16 dias | DC15: =_xlfn.XLOOKUP(B15,'BASE DE EXCEL'!$C:$C,'BASE DE EXCEL'!W:W,"NO HAY REFERENCIA") -> 28 | DD15: =_xlfn.XLOOKUP(B15,'BASE DE EXCEL'!$C:$C,'BASE DE EXCEL'!X:X,"NO HAY REFERENCIA") -> más de 16 días | DE15: =_xlfn.XLOOKUP(B15,'BASE DE EXCEL'!$C:$C,'BASE DE EXCEL'!Y:Y,"NO HAY REFERENCIA") -> 1 | DF15: =_xlfn.XLOOKUP(B15,'BASE DE EXCEL'!$C:$C,'BASE DE EXCEL'!Z:Z,"NO HAY REFERENCIA") -> 1 día o menos | DG15: =_xlfn.XLOOKUP(B15,'BASE DE EXCEL'!$C:$C,'BASE DE EXCEL'!AA:AA,"NO HAY REFERENCIA") -> 32 | DH15: =_xlfn.XLOOKUP(B15,'BASE DE EXCEL'!$C:$C,'BASE DE EXCEL'!AB:AB,"NO HAY REFERENCIA") -> 1 | DI15: =_xlfn.XLOOKUP(B15,'BASE DE EXCEL'!$C:$C,'BASE DE EXCEL'!AC:AC,"NO HAY REFERENCIA") -> 1 día o menos | DJ15: =_xlfn.XLOOKUP(B15,'BASE DE EXCEL'!$C:$C,'BASE DE EXCEL'!AD:AD,"NO HAY REFERENCIA") -> 46044 | DK15: =_xlfn.XLOOKUP(B15,'BASE DE EXCEL'!$C:$C,'BASE DE EXCEL'!AE:AE,"NO HAY REFERENCIA") -> 2 | DL15: =_xlfn.XLOOKUP(B15,'BASE DE EXCEL'!$C:$C,'BASE DE EXCEL'!AF:AF,"NO HAY REFERENCIA") -> 2 | DM15: =_xlfn.XLOOKUP(B15,'BASE DE EXCEL'!$C:$C,'BASE DE EXCEL'!AG:AG,"NO HAY REFERENCIA") -> 46044 | DN15: =_xlfn.XLOOKUP(B15,'BASE DE EXCEL'!$C:$C,'BASE DE EXCEL'!AH:AH,"NO HAY REFERENCIA") -> 46044 | DO15: =_xlfn.XLOOKUP(B15,'BASE DE EXCEL'!$C:$C,'BASE DE EXCEL'!AI:AI,"NO HAY REFERENCIA") -> 0 | DP15: =_xlfn.XLOOKUP(B15,'BASE DE EXCEL'!$C:$C,'BASE DE EXCEL'!AJ:AJ,"NO HAY REFERENCIA") -> 2 a 3 días | DQ15: =_xlfn.XLOOKUP(B15,'BASE DE EXCEL'!$C:$C,'BASE DE EXCEL'!AK:AK,"NO HAY REFERENCIA") -> 46044 | DR15: =_xlfn.XLOOKUP(B15,'BASE DE EXCEL'!$C:$C,'BASE DE EXCEL'!AL:AL,"NO HAY REFERENCIA") -> 3 | DS15: =_xlfn.XLOOKUP(B15,'BASE DE EXCEL'!$C:$C,'BASE DE EXCEL'!AM:AM,"NO HAY REFERENCIA") -> 2 a 3 días | DT15: =_xlfn.XLOOKUP(B15,'BASE DE EXCEL'!$C:$C,'BASE DE EXCEL'!AN:AN,"NO HAY REFERENCIA") -> On Time | DU15: =_xlfn.XLOOKUP(B15,'BASE DE EXCEL'!$C:$C,'BASE DE EXCEL'!AO:AO,"NO HAY REFERENCIA") -> 1 | DV15: =_xlfn.XLOOKUP(B15,'BASE DE EXCEL'!$C:$C,'BASE DE EXCEL'!AP:AP,"NO HAY REFERENCIA") -> Es anterior | DW15: =_xlfn.XLOOKUP(B15,'BASE DE EXCEL'!$C:$C,'BASE DE EXCEL'!AQ:AQ,"NO HAY REFERENCIA") -> A1 | DX15: =_xlfn.XLOOKUP(B15,'BASE DE EXCEL'!$C:$C,'BASE DE EXCEL'!AR:AR,"NO HAY REFERENCIA") -> ZULEIMA PEREZ RUIZ | DY15: =_xlfn.XLOOKUP(B15,'BASE DE EXCEL'!$C:$C,'BASE DE EXCEL'!AS:AS,"NO HAY REFERENCIA") -> HLCURTM251142982 | DZ15: =_xlfn.XLOOKUP(B15,'BASE DE EXCEL'!$C:$C,'BASE DE EXCEL'!AT:AT,"NO HAY REFERENCIA") -> NULL | EA15: =_xlfn.XLOOKUP(B15,'BASE DE EXCEL'!$C:$C,'BASE DE EXCEL'!AU:AU,"NO HAY REFERENCIA") -> 6000133 | EB15: =_xlfn.XLOOKUP(B15,'BASE DE EXCEL'!$C:$C,'BASE DE EXCEL'!AV:AV,"NO HAY REFERENCIA") -> Importación | EC15: =_xlfn.XLOOKUP(B15,'BASE DE EXCEL'!$C:$C,'BASE DE EXCEL'!AW:AW,"NO HAY REFERENCIA") -> ROTAVEC CORONA (VACUNA DE USO VETERINARIO) | ED15: =_xlfn.XLOOKUP(B15,'BASE DE EXCEL'!$C:$C,'BASE DE EXCEL'!AX:AX,"NO HAY REFERENCIA") -> SIN CLASIFICACION | EE15: =_xlfn.XLOOKUP(B15,'BASE DE EXCEL'!$C:$C,'BASE DE EXCEL'!AY:AY,"NO HAY REFERENCIA") -> 0 | EF15: =_xlfn.XLOOKUP(B15,'BASE DE EXCEL'!$C:$C,'BASE DE EXCEL'!AZ:AZ,"NO HAY REFERENCIA") -> Cargas de Importación | EG15: =_xlfn.XLOOKUP(B15,'BASE DE EXCEL'!$C:$C,'BASE DE EXCEL'!BA:BA,"NO HAY REFERENCIA") -> INTERVET MEXICO SA DE CV | EH15: =_xlfn.XLOOKUP(B15,'BASE DE EXCEL'!$C:$C,'BASE DE EXCEL'!BB:BB,"NO HAY REFERENCIA") -> 0 | EI15: =_xlfn.XLOOKUP(B15,'BASE DE EXCEL'!$C:$C,'BASE DE EXCEL'!BC:BC,"NO HAY REFERENCIA") -> FALTA RRNA | EJ15: =_xlfn.XLOOKUP(B15,'BASE DE EXCEL'!$C:$C,'BASE DE EXCEL'!BD:BD,"NO HAY REFERENCIA") -> FALTA DE HRZ PARA INICIAR TRAMITE CON SADER | EK15: =_xlfn.XLOOKUP(B15,'BASE DE EXCEL'!$C:$C,'BASE DE EXCEL'!BE:BE,"NO HAY REFERENCIA") -> FALTA RRNA | EL15: =_xlfn.XLOOKUP(B15,'BASE DE EXCEL'!$C:$C,'BASE DE EXCEL'!BF:BF,"NO HAY REFERENCIA") -> PRODUCTO TERMINADO | EM15: =_xlfn.XLOOKUP(B15,'BASE DE EXCEL'!$C:$C,'BASE DE EXCEL'!BG:BG,"NO HAY REFERENCIA") -> Verde | EN15: =_xlfn.XLOOKUP(B15,'BASE DE EXCEL'!$C:$C,'BASE DE EXCEL'!BH:BH,"NO HAY REFERENCIA") -> SERVEX TRANSPORTES SA DE CV | EO15: =_xlfn.XLOOKUP(B15,'BASE DE EXCEL'!$C:$C,'BASE DE EXCEL'!BI:BI,"NO HAY REFERENCIA") -> ECONOMICO 09 CAMIONETA | EP15: =_xlfn.XLOOKUP(B15,'BASE DE EXCEL'!$C:$C,'BASE DE EXCEL'!BJ:BJ,"NO HAY REFERENCIA") -> 0 | EQ15: =_xlfn.XLOOKUP(B15,'BASE DE EXCEL'!$C:$C,'BASE DE EXCEL'!BK:BK,"NO HAY REFERENCIA") -> IME850329RH2 | ER15: =_xlfn.XLOOKUP(B15,'BASE DE EXCEL'!$C:$C,'BASE DE EXCEL'!BL:BL,"NO HAY REFERENCIA") -> 0 | ES15: =_xlfn.XLOOKUP(B15,'BASE DE EXCEL'!$C:$C,'BASE DE EXCEL'!BM:BM,"NO HAY REFERENCIA") -> 99 | ET15: =_xlfn.XLOOKUP(B15,'BASE DE EXCEL'!$C:$C,'BASE DE EXCEL'!BN:BN,"NO HAY REFERENCIA") -> LOTE: 1R015B01 | EU15: =_xlfn.XLOOKUP(B15,'BASE DE EXCEL'!$C:$C,'BASE DE EXCEL'!BO:BO,"NO HAY REFERENCIA") -> 90 | EV15: =_xlfn.XLOOKUP(B15,'BASE DE EXCEL'!$C:$C,'BASE DE EXCEL'!BP:BP,"NO HAY REFERENCIA") -> 4939600 | EW15: =_xlfn.XLOOKUP(B15,'BASE DE EXCEL'!$C:$C,'BASE DE EXCEL'!BQ:BQ,"NO HAY REFERENCIA") -> KILO | EX15: =_xlfn.XLOOKUP(B15,'BASE DE EXCEL'!$C:$C,'BASE DE EXCEL'!BR:BR,"NO HAY REFERENCIA") -> 0 | EY15: =_xlfn.XLOOKUP(B15,'BASE DE EXCEL'!$C:$C,'BASE DE EXCEL'!BS:BS,"NO HAY REFERENCIA") -> PAISES BAJOS (REINO DE LOS) (HOLANDA) | EZ15: =_xlfn.XLOOKUP(B15,'BASE DE EXCEL'!$C:$C,'BASE DE EXCEL'!BT:BT,"NO HAY REFERENCIA") -> PAISES BAJOS (REINO DE LOS) (HOLANDA) | FA15: =_xlfn.XLOOKUP(B15,'BASE DE EXCEL'!$C:$C,'BASE DE EXCEL'!BU:BU,"NO HAY REFERENCIA") -> ZYA | FB15: =_xlfn.XLOOKUP(B15,'BASE DE EXCEL'!$C:$C,'BASE DE EXCEL'!BV:BV,"NO HAY REFERENCIA") -> ZYA | FC15: =_xlfn.XLOOKUP(B15,QUERY!$C:$C,QUERY!D:D) -> 430 | FD15: =_xlfn.XLOOKUP(B15,QUERY!$C:$C,QUERY!E:E) -> 46038 | FE15: =_xlfn.XLOOKUP(B15,QUERY!$C:$C,QUERY!F:F) -> 1 | FF15: =_xlfn.XLOOKUP(B15,QUERY!$C:$C,QUERY!G:G) -> 46006 | FG15: =_xlfn.XLOOKUP(B15,QUERY!$C:$C,QUERY!H:H) -> 46038 | FH15: =_xlfn.XLOOKUP(B15,QUERY!$C:$C,QUERY!I:I) -> 24 | FI15: =_xlfn.XLOOKUP(B15,QUERY!$C:$C,QUERY!J:J) -> 16 o más días | FJ15: =_xlfn.XLOOKUP(B15,QUERY!$C:$C,QUERY!K:K) -> 46041 | FK15: =_xlfn.XLOOKUP(B15,QUERY!$C:$C,QUERY!L:L) -> 25 | FL15: =_xlfn.XLOOKUP(B15,QUERY!$C:$C,QUERY!M:M) -> 16 o más días | FM15: =_xlfn.XLOOKUP(B15,QUERY!$C:$C,QUERY!N:N) -> 1 | FN15: =_xlfn.XLOOKUP(B15,QUERY!$C:$C,QUERY!O:O) -> 1 día o menos | FO15: =_xlfn.XLOOKUP(B15,QUERY!$C:$C,QUERY!P:P) -> 1 | FP15: =_xlfn.XLOOKUP(B15,QUERY!$C:$C,QUERY!Q:Q) -> 1 | FQ15: =_xlfn.XLOOKUP(B15,QUERY!$C:$C,QUERY!R:R) -> 1 día o menos | FR15: =_xlfn.XLOOKUP(B15,QUERY!$C:$C,QUERY!S:S) -> 46042 | FS15: =_xlfn.XLOOKUP(B15,QUERY!$C:$C,QUERY!T:T) -> 26 | FT15: =_xlfn.XLOOKUP(B15,QUERY!$C:$C,QUERY!U:U) -> mas de 16 dias | FU15: =_xlfn.XLOOKUP(B15,QUERY!$C:$C,QUERY!V:V) -> 28 | FV15: =_xlfn.XLOOKUP(B15,QUERY!$C:$C,QUERY!W:W) -> más de 16 días | FW15: =_xlfn.XLOOKUP(B15,QUERY!$C:$C,QUERY!X:X) -> 46044 | FX15: =_xlfn.XLOOKUP(B15,QUERY!$C:$C,QUERY!Y:Y) -> 2 | FY15: =_xlfn.XLOOKUP(B15,QUERY!$C:$C,QUERY!Z:Z) -> 2 | FZ15: =_xlfn.XLOOKUP(B15,QUERY!$C:$C,QUERY!AA:AA) -> 2 a 3 días | GA15: =_xlfn.XLOOKUP(B15,QUERY!$C:$C,QUERY!AB:AB) -> 46044 | GB15: =_xlfn.XLOOKUP(B15,QUERY!$C:$C,QUERY!AC:AC) -> 46044 | GC15: =_xlfn.XLOOKUP(B15,QUERY!$C:$C,QUERY!AD:AD) -> 0 | GD15: =_xlfn.XLOOKUP(B15,QUERY!$C:$C,QUERY!AE:AE) -> 46044 | GE15: =_xlfn.XLOOKUP(B15,QUERY!$C:$C,QUERY!AF:AF) -> 1 | GF15: =_xlfn.XLOOKUP(B15,QUERY!$C:$C,QUERY!AG:AG) -> Es anterior | GG15: =_xlfn.XLOOKUP(B15,QUERY!$C:$C,QUERY!AH:AH) -> A1 | GH15: =_xlfn.XLOOKUP(B15,QUERY!$C:$C,QUERY!AI:AI) -> ZULEIMA PEREZ RUIZ | GI15: =_xlfn.XLOOKUP(B15,QUERY!$C:$C,QUERY!AJ:AJ) -> HLCURTM251142982 | GJ15: =_xlfn.XLOOKUP(B15,QUERY!$C:$C,QUERY!AK:AK) -> NULL | GK15: =_xlfn.XLOOKUP(B15,QUERY!$C:$C,QUERY!AL:AL) -> 6000133 | GL15: =_xlfn.XLOOKUP(B15,QUERY!$C:$C,QUERY!AM:AM) -> Importación | GM15: =_xlfn.XLOOKUP(B15,QUERY!$C:$C,QUERY!AN:AN) -> ROTAVEC CORONA (VACUNA DE USO VETERINARIO) | GN15: =_xlfn.XLOOKUP(B15,QUERY!$C:$C,QUERY!AO:AO) -> SIN CLASIFICACION | GO15: =_xlfn.XLOOKUP(B15,QUERY!$C:$C,QUERY!AP:AP) -> 0 | GP15: =_xlfn.XLOOKUP(B15,QUERY!$C:$C,QUERY!AQ:AQ) -> Cargas de Importación | GQ15: =_xlfn.XLOOKUP(B15,QUERY!$C:$C,QUERY!AR:AR) -> INTERVET MEXICO SA DE CV | GR15: =_xlfn.XLOOKUP(B15,QUERY!$C:$C,QUERY!AS:AS) -> 0 | GS15: =_xlfn.XLOOKUP(B15,QUERY!$C:$C,QUERY!AT:AT) -> FALTA RRNA | GT15: =_xlfn.XLOOKUP(B15,QUERY!$C:$C,QUERY!AU:AU) -> FALTA DE HRZ PARA INICIAR TRAMITE CON SADER | GU15: =_xlfn.XLOOKUP(B15,QUERY!$C:$C,QUERY!AV:AV) -> FALTA RRNA | GV15: =_xlfn.XLOOKUP(B15,QUERY!$C:$C,QUERY!AW:AW) -> PRODUCTO TERMINADO | GW15: =_xlfn.XLOOKUP(B15,QUERY!$C:$C,QUERY!AX:AX) -> Verde | GX15: =_xlfn.XLOOKUP(B15,QUERY!$C:$C,QUERY!AY:AY) -> SERVEX TRANSPORTES SA DE CV | GY15: =_xlfn.XLOOKUP(B15,QUERY!$C:$C,QUERY!AZ:AZ) -> ECONOMICO 09 CAMIONETA | GZ15: =_xlfn.XLOOKUP(B15,QUERY!$C:$C,QUERY!BA:BA) -> 0 | HA15: =_xlfn.XLOOKUP(B15,QUERY!$C:$C,QUERY!BB:BB) -> IME850329RH2 | HB15: =_xlfn.XLOOKUP(B15,QUERY!$C:$C,QUERY!BC:BC) -> 0 | HC15: =_xlfn.XLOOKUP(B15,QUERY!$C:$C,QUERY!BD:BD) -> 99 | HD15: =_xlfn.XLOOKUP(B15,QUERY!$C:$C,QUERY!BE:BE) -> LOTE: 1R015B01 | HE15: =_xlfn.XLOOKUP(B15,QUERY!$C:$C,QUERY!BF:BF) -> 90 | HF15: =_xlfn.XLOOKUP(B15,QUERY!$C:$C,QUERY!BG:BG) -> 4939600.00 | HG15: =_xlfn.XLOOKUP(B15,QUERY!$C:$C,QUERY!BH:BH) -> KILO | HH15: =_xlfn.XLOOKUP(B15,QUERY!$C:$C,QUERY!BI:BI) -> 0 | HI15: =_xlfn.XLOOKUP(B15,QUERY!$C:$C,QUERY!BJ:BJ) -> PAISES BAJOS (REINO DE LOS) (HOLANDA) | HJ15: =_xlfn.XLOOKUP(B15,QUERY!$C:$C,QUERY!BK:BK) -> PAISES BAJOS (REINO DE LOS) (HOLANDA) | HK15: =_xlfn.XLOOKUP(B15,QUERY!$C:$C,QUERY!BL:BL) -> ZYA | HL15: =_xlfn.XLOOKUP(B15,QUERY!$C:$C,QUERY!BM:BM) -> ZYA | HM15: =_xlfn.XLOOKUP(B15,QUERY!$C:$C,QUERY!BN:BN) -> 4939600 | HN15: =_xlfn.XLOOKUP(B15,QUERY!$C:$C,QUERY!BO:BO) -> 462.00 | HO15: =_xlfn.XLOOKUP(B15,QUERY!$C:$C,QUERY!BP:BP) -> NULL | HP15: =_xlfn.XLOOKUP(B15,QUERY!$C:$C,QUERY!BQ:BQ) -> NULL | HQ15: =_xlfn.XLOOKUP(B15,QUERY!$C:$C,QUERY!BR:BR) -> 94680.66 | HR15: =_xlfn.XLOOKUP(B15,QUERY!$C:$C,QUERY!BS:BS) -> 0 | HS15: =_xlfn.XLOOKUP(B15,QUERY!$C:$C,QUERY!BT:BT) -> 0 | HT15: =_xlfn.XLOOKUP(B15,QUERY!$C:$C,QUERY!A:A) -> VERACRUZ | HU15: =_xlfn.XLOOKUP(B15,QUERY!$C:$C,QUERY!B:B) -> MARÍTIMO VERACRUZ
